Workbook

Sheet DADOS MATRIZ
H2: INDIVUDUAL (MM) | N2: Armazenamento (TUBOS) (M) | Q2: EMBALAGEM (M) | X2: Reembalagem (Master) (M)
B3: Produto | C3: Descrição | D3: Linha | E3: Família | F3: Unidade | G3: Tipo Embalagem | H3: Peso Bruto (produto + embalagem) | I3: Comprimento | J3: Altura | K3: Largura | L3: Cubagem | M3: Código de Barras | N3: Altur.Armaze | O3: Compr.Armaze | P3: Largu.Armaze | Q3: Larg.Emb | R3: Alt.Emb | S3: Compr.Emb | T3: Quantidade Embalagem | U3: Pos.IPI/NCM | V3: Aliq. IPI | W3: Código de Barras | X3: Larg.Reemb | Y3: Alt.Reemb | Z3: Compr.Reemb | AA3: Cubagem | AB3: Quantidade | AC3: Código de Barras | AD3: Data de validade
B4: 23 | C4: TUBO PVC SOLDAVEL - 6M - 20MM | D4: TUBOS PVC SOLDAVEL | E4: AF | F4: BR | G4: Amarrados | H4: 0.82 | I4: 6000 | J4: 20 | K4: 20 | L4: =J4*I4*K4 -> 2400000 | M4: 7897801304009 | N4: 0.023 | O4: 6 | P4: 0.023 | Q4: 0.085 | R4: 0.085 | S4: 6 | T4: 12 | U4: 3917.23.00 | V4: 0 | W4: 17897801304006 | X4: NÃO APLICA | Y4: NÃO APLICA | Z4: NÃO APLICA | AB4: 0 | AC4: 27897801304003 | AD4: Validade indeterminada
B5: 24 | C5: TUBO PVC SOLDAVEL - 6M - 25MM | D5: TUBOS PVC SOLDAVEL | E5: AF | F5: BR | G5: Amarrados | H5: 1.172 | I5: 6000 | J5: 25 | K5: 25 | L5: =J5*I5*K5 -> 3750000 | M5: 7897801304016 | N5: 0.027 | O5: 6 | P5: 0.027 | Q5: 0.085 | R5: 0.085 | S5: 6 | T5: 8 | U5: 3917.23.00 | V5: 0 | W5: 17897801304013 | X5: NÃO APLICA | Y5: NÃO APLICA | Z5: NÃO APLICA | AB5: 0 | AC5: 27897801304010 | AD5: Validade indeterminada
B6: 25 | C6: TUBO PVC SOLDAVEL - 6M - 32MM | D6: TUBOS PVC SOLDAVEL | E6: AF | F6: BR | G6: Amarrados | H6: 1.845 | I6: 6000 | J6: 32 | K6: 32 | L6: =J6*I6*K6 -> 6144000 | M6: 7897801304023 | N6: 0.035 | O6: 6 | P6: 0.035 | Q6: 0.13 | R6: 0.09 | S6: 6 | T6: 10 | U6: 3917.23.00 | V6: 0 | W6: 17897801304020 | X6: NÃO APLICA | Y6: NÃO APLICA | Z6: NÃO APLICA | AB6: 0 | AC6: 27897801304027 | AD6: Validade indeterminada
B7: 26 | C7: TUBO PVC SOLDAVEL - 6M - 40MM | D7: TUBOS PVC SOLDAVEL | E7: AF | F7: BR | G7: Amarrados | H7: 2.645 | I7: 6000 | J7: 40 | K7: 40 | L7: =J7*I7*K7 -> 9600000 | M7: 7897801304030 | N7: 0.045 | O7: 6 | P7: 0.045 | Q7: 0.12 | R7: 0.075 | S7: 6 | T7: 5 | U7: 3917.23.00 | V7: 0 | W7: 17897801304037 | X7: NÃO APLICA | Y7: NÃO APLICA | Z7: NÃO APLICA | AB7: 0 | AC7: 27897801304034 | AD7: Validade indeterminada
B8: 27 | C8: TUBO PVC SOLDAVEL - 6M - 50MM | D8: TUBOS PVC SOLDAVEL | E8: AF | F8: BR | G8: Amarrados | H8: 4.122 | I8: 6000 | J8: 50 | K8: 50 | L8: =J8*I8*K8 -> 15000000 | M8: 7897801304047 | N8: 0.055 | O8: 6 | P8: 0.055 | Q8: 0.17 | R8: 0.11 | S8: 6 | T8: 5 | U8: 3917.23.00 | V8: 0 | W8: 17897801304044 | X8: NÃO APLICA | Y8: NÃO APLICA | Z8: NÃO APLICA | AB8: 0 | AC8: 27897801304041 | AD8: Validade indeterminada
B9: 28 | C9: TUBO PVC SOLDAVEL - 6M - 60MM | D9: TUBOS PVC SOLDAVEL | E9: AF | F9: BR | G9: Amarrados | H9: 5.382 | I9: 6000 | J9: 60 | K9: 60 | L9: =J9*I9*K9 -> 21600000 | M9: 7897801304054 | N9: 0.067 | O9: 6 | P9: 0.067 | Q9: 0.125 | R9: 0.12 | S9: 6 | T9: 3 | U9: 3917.23.00 | V9: 0 | W9: 17897801304051 | X9: NÃO APLICA | Y9: NÃO APLICA | Z9: NÃO APLICA | AB9: 0 | AC9: 27897801304058 | AD9: Validade indeterminada
B10: 29 | C10: TUBO PVC SOLDAVEL - 6M - 75MM | D10: TUBOS PVC SOLDAVEL | E10: AF | F10: BR | G10: Amarrados | H10: 8.53 | I10: 6000 | J10: 75 | K10: 75 | L10: =J10*I10*K10 -> 33750000 | M10: 7897801308564 | N10: 0.083 | O10: 6 | P10: 0.083 | Q10: 0.0752 | R10: 0.0752 | S10: 6 | T10: 1 | U10: 3917.23.00 | V10: 0 | W10: 17897801308561 | X10: NÃO APLICA | Y10: NÃO APLICA | Z10: NÃO APLICA | AB10: 0 | AC10: 27897801308568 | AD10: Validade indeterminada
B11: 30 | C11: TUBO PVC SOLDAVEL - 6M - 85MM | D11: TUBOS PVC SOLDAVEL | E11: AF | F11: BR | G11: Amarrados | H11: 10.85 | I11: 6000 | J11: 85 | K11: 85 | L11: =J11*I11*K11 -> 43350000 | M11: 7897801308588 | N11: 0.095 | O11: 6 | P11: 0.095 | Q11: 0.0852 | R11: 0.0852 | S11: 6 | T11: 1 | U11: 3917.23.00 | V11: 0 | W11: 17897801308585 | X11: NÃO APLICA | Y11: NÃO APLICA | Z11: NÃO APLICA | AB11: 0 | AC11: 27897801308582 | AD11: Validade indeterminada
B12: 31 | C12: TUBO PVC SOLDAVEL - 6M - 110MM | D12: TUBOS PVC SOLDAVEL | E12: AF | F12: BR | G12: Amarrados | H12: 18.25 | I12: 6000 | J12: 110 | K12: 110 | L12: =J12*I12*K12 -> 72600000 | M12: 7897801308595 | N12: 0.122 | O12: 6 | P12: 0.122 | Q12: 0.1102 | R12: 0.1102 | S12: 6 | T12: 1 | U12: 3917.23.00 | V12: 0 | W12: 17897801308592 | X12: NÃO APLICA | Y12: NÃO APLICA | Z12: NÃO APLICA | AB12: 0 | AC12: 27897801308599 | AD12: Validade indeterminada
B13: 32 | C13: TUBO PVC SOLDAVEL - 3M - 20MM | D13: TUBOS PVC SOLDAVEL | E13: AF | F13: BR | G13: Amarrados | H13: 0.42 | I13: 3000 | J13: 20 | K13: 20 | L13: =J13*I13*K13 -> 1200000 | M13: 7897801304306 | N13: 0.0202 | O13: 3 | P13: 0.0202 | Q13: 0.085 | R13: 0.085 | S13: 3 | T13: 12 | U13: 3917.23.00 | V13: 0 | W13: 17897801304303 | X13: NÃO APLICA | Y13: NÃO APLICA | Z13: NÃO APLICA | AB13: 0 | AC13: 27897801304300 | AD13: Validade indeterminada
B14: 33 | C14: TUBO PVC SOLDAVEL - 3M - 25MM | D14: TUBOS PVC SOLDAVEL | E14: AF | F14: BR | G14: Amarrados | H14: 0.579 | I14: 3000 | J14: 25 | K14: 25 | L14: =J14*I14*K14 -> 1875000 | M14: 7897801304313 | N14: 0.0252 | O14: 3 | P14: 0.0252 | Q14: 0.1 | R14: 0.09 | S14: 3 | T14: 8 | U14: 3917.23.00 | V14: 0 | W14: 17897801304310 | X14: NÃO APLICA | Y14: NÃO APLICA | Z14: NÃO APLICA | AB14: 0 | AC14: 27897801304317 | AD14: Validade indeterminada
B15: 34 | C15: TUBO PVC SOLDAVEL - 3M - 32MM | D15: TUBOS PVC SOLDAVEL | E15: AF | F15: BR | G15: Amarrados | H15: 0.925 | I15: 3000 | J15: 32 | K15: 32 | L15: =J15*I15*K15 -> 3072000 | M15: 7897801308991 | N15: 0.0322 | O15: 3 | P15: 0.0322 | Q15: 0.13 | R15: 0.09 | S15: 3 | T15: 10 | U15: 3917.23.00 | V15: 0 | W15: 17897801308998 | X15: NÃO APLICA | Y15: NÃO APLICA | Z15: NÃO APLICA | AB15: 0 | AC15: 27897801308995 | AD15: Validade indeterminada
... B22: 52 | C22: TUBO ULTRATERM 3M - 28MM | D22: CPVC - ULTRATERM - TUBOS | E22: AQ | F22: BR | G22: Amarrados | H22: 0.95 | I22: 3000 | J22: 28 | K22: 28 | L22: =J22*I22*K22 -> 2352000 | M22: 7897801320283 | N22: 0.028 | O22: 3 | P22: 0.028 | Q22: 0.028 | R22: 3 | S22: 0.028 | T22: 10 | U22: 3917.23.00 | V22: 0 | W22: 17897801320280 | X22: NÃO APLICA | Y22: NÃO APLICA | Z22: NÃO APLICA | AB22: 0 | AC22: 27897801320287 | AD22: Validade indeterminada
B23: 78 | C23: RALO QUADRADO OCULTO 10x10 cm KRONA | D23: CAIXAS E RALOS | E23: ESGOTO | F23: PC | G23: Blister | H23: 0.715 | I23: 125 | J23: 48 | K23: 125 | L23: =J23*I23*K23 -> 750000 | M23: 7898708518384 | N23: NÃO APLICA | O23: NÃO APLICA | P23: NÃO APLICA | Q23: 0.1 | R23: 0.024 | S23: 0.1 | T23: 1 | U23: 3917.40.90 | V23: 0 | W23: 17898708518381 | X23: 0.066 | Y23: 0.25 | Z23: 0.165 | AA23: =Y23*X23*Z23 -> 0.0027225 | AB23: 20 | AC23: 27898708518388 | AD23: Validade indeterminada
B24: 79 | C24: RALO QUADRADO OCULTO 15x15 cm KRONA | D24: CAIXAS E RALOS | E24: ESGOTO | F24: PC | G24: Blister | H24: 1.083 | I24: 195 | J24: 39 | K24: 195 | L24: =J24*I24*K24 -> 1482975 | M24: 7898708518391 | N24: NÃO APLICA | O24: NÃO APLICA | P24: NÃO APLICA | Q24: 0.152 | R24: 0.02 | S24: 0.152 | T24: 1 | U24: 3917.40.90 | V24: 0 | W24: 17898708518398 | X24: 0.045 | Y24: 0.222 | Z24: 0.223 | AA24: =Y24*X24*Z24 -> 0.00222777 | AB24: 45 | AC24: 27898708518395 | AD24: Validade indeterminada
B25: 80 | C25: RALO LINEAR PVC SECO 50CM OCULTO KRONA | D25: CAIXAS E RALOS | E25: ESGOTO | F25: PC | G25: Filme | H25: 0.696 | I25: 523 | J25: 25 | K25: 100 | L25: =J25*I25*K25 -> 1307500 | M25: 7898708518407 | N25: NÃO APLICA | O25: NÃO APLICA | P25: NÃO APLICA | Q25: 0.076 | R25: 0.012 | S25: 0.248 | T25: 1 | U25: 3917.40.90 | V25: 0 | W25: 17898708518404 | X25: 0.105 | Y25: 0.075 | Z25: 0.53 | AA25: =Y25*X25*Z25 -> 0.00417375 | AB25: 30 | AC25: 27898708518401 | AD25: Validade indeterminada
B26: 81 | C26: RALO LINEAR PVC SECO 50CM ACAB. POLIDO KRONA | D26: CAIXAS E RALOS | E26: ESGOTO | F26: PC | G26: Caixa | H26: 0.514 | I26: 523 | J26: 25 | K26: 100 | L26: =J26*I26*K26 -> 1307500 | M26: 7898708518414 | N26: NÃO APLICA | O26: NÃO APLICA | P26: NÃO APLICA | Q26: 0.076 | R26: 0.026 | S26: 0.248 | T26: 1 | U26: 3917.40.90 | V26: 0 | W26: 17898708518411 | X26: 0.105 | Y26: 0.075 | Z26: 0.53 | AA26: =Y26*X26*Z26 -> 0.00417375 | AB26: 24 | AC26: 27898708518418 | AD26: Validade indeterminada
B27: 82 | C27: RALO LINEAR PVC SIFONADO 50CM OCULTO KRONA | D27: CAIXAS E RALOS | E27: ESGOTO | F27: PC | G27: Filme | H27: 1.064 | I27: 523 | J27: 25 | K27: 100 | L27: =J27*I27*K27 -> 1307500 | M27: 7898708518421 | N27: NÃO APLICA | O27: NÃO APLICA | P27: NÃO APLICA | Q27: 0.076 | R27: 0.012 | S27: 0.248 | T27: 1 | U27: 3917.40.90 | V27: 0 | W27: 17898708518428 | X27: 0.105 | Y27: 0.075 | Z27: 0.53 | AA27: =Y27*X27*Z27 -> 0.00417375 | AB27: 30 | AC27: 27898708518425 | AD27: Validade indeterminada
B28: 83 | C28: RALO LINEAR PVC SIFONADO 50CM ACAB. POLIDO KRONA | D28: CAIXAS E RALOS | E28: ESGOTO | F28: PC | G28: Caixa | H28: 0.729 | I28: 523 | J28: 25 | K28: 100 | L28: =J28*I28*K28 -> 1307500 | M28: 7898708518438 | N28: NÃO APLICA | O28: NÃO APLICA | P28: NÃO APLICA | Q28: 0.076 | R28: 0.026 | S28: 0.248 | T28: 1 | U28: 3917.40.90 | V28: 0 | W28: 17898708518435 | X28: 0.105 | Y28: 0.075 | Z28: 0.53 | AA28: =Y28*X28*Z28 -> 0.00417375 | AB28: 24 | AC28: 27898708518432 | AD28: Validade indeterminada
B29: 84 | C29: RALO LINEAR PVC SECO 75CM SAIDA CENTRAL OCULTO KRONA | D29: CAIXAS E RALOS | E29: ESGOTO | F29: PC | G29: Filme | H29: 0.495 | I29: 773 | J29: 33 | K29: 100 | L29: =J29*I29*K29 -> 2550900 | M29: 7898708518445 | N29: NÃO APLICA | O29: NÃO APLICA | P29: NÃO APLICA | Q29: 0.076 | R29: 0.012 | S29: 0.248 | T29: 1 | U29: 3917.40.90 | V29: 0 | W29: 17898708518442 | X29: 0.105 | Y29: 0.075 | Z29: 0.775 | AA29: =Y29*X29*Z29 -> 0.006103125 | AB29: 20 | AC29: 27898708518449 | AD29: Validade indeterminada
B30: 85 | C30: RALO LINEAR PVC SECO 75CM SAIDA CENTRAL POLIDO KRONA | D30: CAIXAS E RALOS | E30: ESGOTO | F30: PC | G30: Caixa | H30: 0.197 | I30: 773 | J30: 33 | K30: 100 | L30: =J30*I30*K30 -> 2550900 | M30: 7898708518452 | N30: NÃO APLICA | O30: NÃO APLICA | P30: NÃO APLICA | Q30: 0.076 | R30: 0.026 | S30: 0.748 | T30: 1 | U30: 3917.40.90 | V30: 0 | W30: 17898708518459 | X30: 0.105 | Y30: 0.075 | Z30: 0.775 | AA30: =Y30*X30*Z30 -> 0.006103125 | AB30: 18 | AC30: 27898708518456 | AD30: Validade indeterminada
B31: 86 | C31: RALO LINEAR PVC SIFONADO 75CM SAIDA CENTRAL OCULTO KRONA | D31: CAIXAS E RALOS | E31: ESGOTO | F31: PC | G31: Filme | H31: 0.71 | I31: 773 | J31: 33 | K31: 100 | L31: =J31*I31*K31 -> 2550900 | M31: 7898708518469 | N31: NÃO APLICA | O31: NÃO APLICA | P31: NÃO APLICA | Q31: 0.076 | R31: 0.012 | S31: 0.248 | T31: 1 | U31: 3917.40.90 | V31: 0 | W31: 17898708518466 | X31: 0.105 | Y31: 0.075 | Z31: 0.775 | AA31: =Y31*X31*Z31 -> 0.006103125 | AB31: 20 | AC31: 27898708518463 | AD31: Validade indeterminada
B32: 87 | C32: RALO LINEAR PVC SIFONADO 75CM SAIDA CENTRAL POLIDO KRONA | D32: CAIXAS E RALOS | E32: ESGOTO | F32: PC | G32: Caixa | H32: 0.424 | I32: 773 | J32: 33 | K32: 100 | L32: =J32*I32*K32 -> 2550900 | M32: 7898708518476 | N32: NÃO APLICA | O32: NÃO APLICA | P32: NÃO APLICA | Q32: 0.076 | R32: 0.026 | S32: 0.748 | T32: 1 | U32: 3917.40.90 | V32: 0 | W32: 17898708518473 | X32: 0.105 | Y32: 0.075 | Z32: 0.775 | AA32: =Y32*X32*Z32 -> 0.006103125 | AB32: 18 | AC32: 27898708518470 | AD32: Validade indeterminada
B33: 88 | C33: SIFAO 50MM PARA RALOS KRONA | D33: CAIXAS E RALOS | E33: ESGOTO | F33: PC | G33: Blister | H33: 0.059 | I33: 50 | J33: 80 | K33: 50 | L33: =J33*I33*K33 -> 200000 | M33: 7898708518483 | N33: NÃO APLICA | O33: NÃO APLICA | P33: NÃO APLICA | Q33: 0.054 | R33: 0.185 | S33: 0.131 | T33: 1 | U33: 3917.40.90 | V33: 0 | W33: 17898708518480 | X33: 0.27 | Y33: 0.27 | Z33: 0.33 | AA33: =Y33*X33*Z33 -> 0.024057 | AB33: 20 | AC33: 27898708518487 | AD33: Validade indeterminada
B34: 89 | C34: BOLSA ACOPLAVEL CX SIFONADA 100MM PVC | D34: CAIXAS E RALOS | E34: ESGOTO | F34: PC | G34: Sacos | H34: 0.056 | I34: 95 | J34: 30 | K34: 95 | L34: =J34*I34*K34 -> 270750 | M34: 7898708518490 | N34: NÃO APLICA | O34: NÃO APLICA | P34: NÃO APLICA | Q34: 0.19 | R34: 0.03 | S34: 0.265 | T34: 1 | U34: 3917.40.90 | V34: 0 | W34: 17898708518497 | X34: 0.27 | Y34: 0.27 | Z34: 0.33 | AA34: =Y34*X34*Z34 -> 0.024057 | AB34: 20 | AC34: 27898708518494 | AD34: Validade indeterminada
B35: 90 | C35: BOLSA ACOPLAVEL CX SIFONADA 150MM PVC | D35: CAIXAS E RALOS | E35: ESGOTO | F35: PC | G35: Sacos | H35: 0.092 | I35: 143 | J35: 30 | K35: 143 | L35: =J35*I35*K35 -> 613470 | M35: 7898708518506 | N35: NÃO APLICA | O35: NÃO APLICA | P35: NÃO APLICA | Q35: 0.19 | R35: 0.03 | S35: 0.265 | T35: 1 | U35: 3917.40.90 | V35: 0 | W35: 17898708518503 | X35: 0.27 | Y35: 0.27 | Z35: 0.33 | AA35: =Y35*X35*Z35 -> 0.024057 | AB35: 20 | AC35: 27898708518500 | AD35: Validade indeterminada
B36: 100 | C36: TUBO PVC ESGOTO SEC. - 6M - DN 40 | D36: TUBOS PVC ESGOTO | E36: ESGOTO | F36: BR | G36: Amarrados | H36: 1.415 | I36: 6000 | J36: 40 | K36: 40 | L36: =J36*I36*K36 -> 9600000 | M36: 7897801304108 | N36: 0.0426 | O36: 6 | P36: 0.0426 | Q36: 0.17 | R36: 0.12 | S36: 6 | T36: 10 | U36: 3917.23.00 | V36: 0 | W36: 17897801304105 | X36: NÃO APLICA | Y36: NÃO APLICA | Z36: NÃO APLICA | AB36: 0 | AC36: 27897801304102 | AD36: Validade indeterminada
B37: 101 | C37: TUBO PVC ESGOTO PRIM. - 6M - DN 50 | D37: TUBOS PVC ESGOTO | E37: ESGOTO | F37: BR | G37: Amarrados | H37: 2.345 | I37: 6000 | J37: 50 | K37: 50 | L37: =J37*I37*K37 -> 15000000 | M37: 7897801304115 | N37: 0.062 | O37: 6 | P37: 0.062 | Q37: 0.24 | R37: 0.16 | S37: 6.002 | T37: 10 | U37: 3917.23.00 | V37: 0 | W37: 17897801304112 | X37: NÃO APLICA | Y37: NÃO APLICA | Z37: NÃO APLICA | AB37: 0 | AC37: 27897801304119 | AD37: Validade indeterminada
B38: 102 | C38: TUBO PVC ESGOTO PRIM. - 6M - DN 75 | D38: TUBOS PVC ESGOTO | E38: ESGOTO | F38: BR | G38: Amarrados | H38: 3.74 | I38: 6000 | J38: 75 | K38: 75 | L38: =J38*I38*K38 -> 33750000 | M38: 7897801304122 | N38: 0.0836 | O38: 6 | P38: 0.0836 | Q38: 0.25 | R38: 0.16 | S38: 6.002 | T38: 5 | U38: 3917.23.00 | V38: 0 | W38: 17897801304129 | X38: NÃO APLICA | Y38: NÃO APLICA | Z38: NÃO APLICA | AB38: 0 | AC38: 27897801304126 | AD38: Validade indeterminada
B39: 103 | C39: TUBO PVC ESGOTO PRIM. - 6M - DN 100 | D39: TUBOS PVC ESGOTO | E39: ESGOTO | F39: BR | G39: Amarrados | H39: 5.317 | I39: 6000 | J39: 101 | K39: 101 | L39: =J39*I39*K39 -> 61206000 | M39: 7897801304139 | N39: 0.1066 | O39: 6 | P39: 0.1066 | Q39: 0.335 | R39: 0.2 | S39: 6.002 | T39: 5 | U39: 3917.23.00 | V39: 0 | W39: 17897801304136 | X39: NÃO APLICA | Y39: NÃO APLICA | Z39: NÃO APLICA | AB39: 0 | AC39: 27897801304133 | AD39: Validade indeterminada
B40: 104 | C40: TUBO PVC ESGOTO PRIM. - 6M - DN 150 | D40: TUBOS PVC ESGOTO | E40: ESGOTO | F40: BR | G40: Amarrados | H40: 11.55 | I40: 6000 | J40: 150 | K40: 150 | L40: =J40*I40*K40 -> 135000000 | M40: 7897801304146 | N40: 0.155 | O40: 6 | P40: 0.155 | Q40: 0.1504 | R40: 0.1504 | S40: 6 | T40: 1 | U40: 3917.23.00 | V40: 0 | W40: 17897801304143 | X40: NÃO APLICA | Y40: NÃO APLICA | Z40: NÃO APLICA | AB40: 0 | AC40: 27897801304140 | AD40: Validade indeterminada
B41: 105 | C41: TUBO PVC ESGOTO PRIM. - 6M - DN 200 | D41: TUBOS PVC ESGOTO | E41: ESGOTO | F41: BR | G41: Amarrados | H41: 20.44 | I41: 6000 | J41: 200 | K41: 200 | L41: =J41*I41*K41 -> 240000000 | M41: 7897801308557 | N41: 0.208 | O41: 6 | P41: 0.208 | Q41: 0.2004 | R41: 0.2004 | S41: 6 | T41: 1 | U41: 3917.23.00 | V41: 0 | W41: 17897801308554 | X41: NÃO APLICA | Y41: NÃO APLICA | Z41: NÃO APLICA | AB41: 0 | AC41: 27897801308551 | AD41: Validade indeterminada
B42: 106 | C42: TUBO PVC LEVE - 6M - DN 250 | D42: TUBOS PVC ESGOTO | E42: ESGOTO | F42: BR | G42: Amarrados | H42: 20.77 | I42: 6000 | J42: 250 | K42: 250 | L42: =J42*I42*K42 -> 375000000 | M42: 7897801308571 | N42: 0.256 | O42: 6 | P42: 0.256 | Q42: 0.2504 | R42: 0.2504 | S42: 6 | T42: 1 | U42: 3917.23.00 | V42: 0 | W42: 17897801308578 | X42: NÃO APLICA | Y42: NÃO APLICA | Z42: NÃO APLICA | AB42: 0 | AC42: 27897801308575 | AD42: Validade indeterminada
B43: 110 | C43: TUBO PVC ESGOTO SEC. - 3M- DN 40 | D43: TUBOS PVC ESGOTO | E43: ESGOTO | F43: BR | G43: Amarrados | H43: 0.7055 | I43: 3000 | J43: 40 | K43: 40 | L43: =J43*I43*K43 -> 4800000 | M43: 7897801308625 | N43: 0.0402 | O43: 3 | P43: 0.0402 | Q43: 0.17 | R43: 0.12 | S43: 3 | T43: 10 | U43: 3917.23.00 | V43: 0 | W43: 17897801308622 | X43: NÃO APLICA | Y43: NÃO APLICA | Z43: NÃO APLICA | AB43: 0 | AC43: 27897801308629 | AD43: Validade indeterminada
B44: 111 | C44: TUBO PVC ESGOTO PRIM. - 3M- DN 50 | D44: TUBOS PVC ESGOTO | E44: ESGOTO | F44: BR | G44: Amarrados | H44: 1.185 | I44: 3000 | J44: 50 | K44: 50 | L44: =J44*I44*K44 -> 7500000 | M44: 7897801308632 | N44: 0.051 | O44: 3 | P44: 0.051 | Q44: 0.205 | R44: 0.14 | S44: 3.002 | T44: 10 | U44: 3917.23.00 | V44: 0 | W44: 17897801308639 | X44: NÃO APLICA | Y44: NÃO APLICA | Z44: NÃO APLICA | AB44: 0 | AC44: 27897801308636 | AD44: Validade indeterminada
B45: 112 | C45: TUBO PVC ESGOTO PRIM. - 3M- DN 75 | D45: TUBOS PVC ESGOTO | E45: ESGOTO | F45: BR | G45: Amarrados | H45: 1.855 | I45: 3000 | J45: 75 | K45: 75 | L45: =J45*I45*K45 -> 16875000 | M45: 7897801308649 | N45: 0.0759 | O45: 3 | P45: 0.0759 | Q45: 0.27 | R45: 0.16 | S45: 3.002 | T45: 5 | U45: 3917.23.00 | V45: 0 | W45: 17897801308646 | X45: NÃO APLICA | Y45: NÃO APLICA | Z45: NÃO APLICA | AB45: 0 | AC45: 27897801308643 | AD45: Validade indeterminada
B46: 113 | C46: TUBO PVC ESGOTO PRIM. - 3M- DN 100 | D46: TUBOS PVC ESGOTO | E46: ESGOTO | F46: BR | G46: Amarrados | H46: 2.658 | I46: 3000 | J46: 100 | K46: 100 | L46: =J46*I46*K46 -> 30000000 | M46: 7897801308656 | N46: 0.102 | O46: 3 | P46: 0.102 | Q46: 0.335 | R46: 0.2 | S46: 3.002 | T46: 5 | U46: 3917.23.00 | V46: 0 | W46: 17897801308653 | X46: NÃO APLICA | Y46: NÃO APLICA | Z46: NÃO APLICA | AB46: 0 | AC46: 27897801308650 | AD46: Validade indeterminada
B47: 114 | C47: TUBO PVC ESGOTO PRIM. - 3M- DN 150 | D47: TUBOS PVC ESGOTO | E47: ESGOTO | F47: BR | G47: Amarrados | H47: 5.82 | I47: 3000 | J47: 150 | K47: 150 | L47: =J47*I47*K47 -> 67500000 | M47: 7897801308663 | N47: 0.1504 | O47: 3.001 | P47: 0.1504 | Q47: 0.1504 | R47: 0.1504 | S47: 3.001 | T47: 1 | U47: 3917.23.00 | V47: 0 | W47: 17897801308660 | X47: NÃO APLICA | Y47: NÃO APLICA | Z47: NÃO APLICA | AB47: 0 | AC47: 27897801308667 | AD47: Validade indeterminada
... B78: 164 | C78: TUBO PPR PN25 110MMX3M | D78: TUBOS PPR | E78: AQ | F78: BR | G78: Amarrados | H78: 14.79 | I78: 2980 | J78: 110 | K78: 110 | L78: =J78*I78*K78 -> 36058000 | M78: 7897801314282 | N78: 0.115 | O78: 2.98 | P78: 0.115 | Q78: 0.115 | R78: 2.98 | S78: 0.115 | T78: 1 | U78: 3917.22.90 | V78: 0 | W78: 17897801314289 | X78: NÃO APLICA | Y78: NÃO APLICA | Z78: NÃO APLICA | AB78: 0 | AC78: 27897801314286 | AD78: Validade indeterminada
B79: 200 | C79: ADAPTADOR ROSC. P/CX.DAGUA 1/2 | D79: ADAP.P/CX.D AGUA ROSC. | E79: AF | F79: PC | G79: Sacos | H79: 0.0782 | I79: 70 | J79: 60 | K79: 70 | L79: =J79*I79*K79 -> 294000 | M79: 7897801312806 | N79: NÃO APLICA | O79: NÃO APLICA | P79: NÃO APLICA | Q79: 0.14 | R79: 0.07 | S79: 0.25 | T79: 10 | U79: 3917.40.90 | V79: 0 | W79: 17897801312803 | X79: 0.48 | Y79: 0.2 | Z79: 0.73 | AA79: =Y79*X79*Z79 -> 0.07008 | AB79: 300 | AC79: 27897801312800 | AD79: Validade indeterminada
B80: 201 | C80: ADAPTADOR ROSC. P/CX.DAGUA 3/4 | D80: ADAP.P/CX.D AGUA ROSC. | E80: AF | F80: PC | G80: Sacos | H80: 0.0972 | I80: 60 | J80: 60 | K80: 70 | L80: =J80*I80*K80 -> 252000 | M80: 7897801312820 | N80: NÃO APLICA | O80: NÃO APLICA | P80: NÃO APLICA | Q80: 0.17 | R80: 0.07 | S80: 0.26 | T80: 10 | U80: 3917.40.90 | V80: 0 | W80: 17897801312827 | X80: 0.49 | Y80: 0.17 | Z80: 0.65 | AA80: =Y80*X80*Z80 -> 0.054145 | AB80: 200 | AC80: 27897801312824 | AD80: Validade indeterminada
B81: 202 | C81: ADAPTADOR ROSC. P/CX.DAGUA 1 | D81: ADAP.P/CX.D AGUA ROSC. | E81: AF | F81: PC | G81: Sacos | H81: 0.1344 | I81: 70 | J81: 70 | K81: 80 | L81: =J81*I81*K81 -> 392000 | M81: 7897801312851 | N81: NÃO APLICA | O81: NÃO APLICA | P81: NÃO APLICA | Q81: 0.2 | R81: 0.7 | S81: 0.3 | T81: 10 | U81: 3917.40.90 | V81: 0 | W81: 17897801312858 | X81: 0.45 | Y81: 0.23 | Z81: 0.6 | AA81: =Y81*X81*Z81 -> 0.0621 | AB81: 120 | AC81: 27897801312855 | AD81: Validade indeterminada
B82: 203 | C82: ADAPTADOR ROSC. P/CX.DAGUA 1.1/4 | D82: ADAP.P/CX.D AGUA ROSC. | E82: AF | F82: PC | G82: Sacos | H82: 0.1562 | I82: 70 | J82: 70 | K82: 90 | L82: =J82*I82*K82 -> 441000 | M82: 7897801312844 | N82: NÃO APLICA | O82: NÃO APLICA | P82: NÃO APLICA | Q82: 0.185 | R82: 0.09 | S82: 0.25 | T82: 5 | U82: 3917.40.90 | V82: 0 | W82: 17897801312841 | X82: 0.49 | Y82: 0.22 | Z82: 0.7 | AA82: =Y82*X82*Z82 -> 0.07546 | AB82: 125 | AC82: 27897801312848 | AD82: Validade indeterminada
B83: 204 | C83: ADAPTADOR ROSC. P/CX.DAGUA 1.1/2 | D83: ADAP.P/CX.D AGUA ROSC. | E83: AF | F83: PC | G83: Sacos | H83: 0.1941 | I83: 80 | J83: 90 | K83: 80 | L83: =J83*I83*K83 -> 576000 | M83: 7897801312837 | N83: NÃO APLICA | O83: NÃO APLICA | P83: NÃO APLICA | Q83: 0.18 | R83: 0.07 | S83: 0.21 | T83: 5 | U83: 3917.40.90 | V83: 0 | W83: 17897801312834 | X83: 0.5 | Y83: 0.21 | Z83: 0.65 | AA83: =Y83*X83*Z83 -> 0.06825 | AB83: 100 | AC83: 27897801312831 | AD83: Validade indeterminada
B84: 205 | C84: ADAPTADOR ROSC. P/CX.DAGUA 2 | D84: ADAP.P/CX.D AGUA ROSC. | E84: AF | F84: PC | G84: Sacos | H84: 0.2541 | I84: 100 | J84: 90 | K84: 10 | L84: =J84*I84*K84 -> 90000 | M84: 7897801312868 | N84: NÃO APLICA | O84: NÃO APLICA | P84: NÃO APLICA | Q84: 0.225 | R84: 0.085 | S84: 0.275 | T84: 5 | U84: 3917.40.90 | V84: 0 | W84: 17897801312865 | X84: 0.42 | Y84: 0.22 | Z84: 0.64 | AA84: =Y84*X84*Z84 -> 0.059136 | AB84: 60 | AC84: 27897801312862 | AD84: Validade indeterminada
B85: 208 | C85: BUCHA RED.ROSC. 3/4 X 1/2 | D85: CONEXOES ROSCAVEIS | E85: AF | F85: PC | G85: Sacos | H85: 0.01 | I85: 30 | J85: 30 | K85: 27 | L85: =J85*I85*K85 -> 24300 | M85: 7897801302128 | N85: NÃO APLICA | O85: NÃO APLICA | P85: NÃO APLICA | Q85: 0.23 | R85: 0.04 | S85: 0.24 | T85: 50 | U85: 3917.40.90 | V85: 0 | W85: 17897801302125 | X85: 0.42 | Y85: 0.22 | Z85: 0.67 | AA85: =Y85*X85*Z85 -> 0.061908 | AB85: 2000 | AC85: 47897801302126 | AD85: Validade indeterminada
B86: 209 | C86: BUCHA RED.ROSC. 1 X 1/2 | D86: CONEXOES ROSCAVEIS | E86: AF | F86: PC | G86: Sacos | H86: 0.0223 | I86: 30 | J86: 30 | K86: 40 | L86: =J86*I86*K86 -> 36000 | M86: 7897801312189 | N86: NÃO APLICA | O86: NÃO APLICA | P86: NÃO APLICA | Q86: 0.19 | R86: 0.04 | S86: 0.235 | T86: 16 | U86: 3917.40.90 | V86: 0 | W86: 17897801312186 | X86: 0.53 | Y86: 0.21 | Z86: 0.79 | AA86: =Y86*X86*Z86 -> 0.087927 | AB86: 960 | AC86: 27897801312183 | AD86: Validade indeterminada
B87: 210 | C87: BUCHA RED.ROSC. 1 X 3/4 | D87: CONEXOES ROSCAVEIS | E87: AF | F87: PC | G87: Sacos | H87: 0.0162 | I87: 36 | J87: 30 | K87: 36 | L87: =J87*I87*K87 -> 38880 | M87: 7897801307673 | N87: NÃO APLICA | O87: NÃO APLICA | P87: NÃO APLICA | Q87: 0.16 | R87: 0.035 | S87: 0.2 | T87: 24 | U87: 3917.40.90 | V87: 0 | W87: 17897801307670 | X87: 0.5 | Y87: 0.18 | Z87: 0.7 | AA87: =Y87*X87*Z87 -> 0.063 | AB87: 1320 | AC87: 47897801307671 | AD87: Validade indeterminada
B88: 211 | C88: BUCHA RED.ROSC. 1.1/4 X 1 | D88: CONEXOES ROSCAVEIS | E88: AF | F88: PC | G88: Sacos | H88: 0.0258 | I88: 30 | J88: 50 | K88: 40 | L88: =J88*I88*K88 -> 60000 | M88: 7897801312196 | N88: NÃO APLICA | O88: NÃO APLICA | P88: NÃO APLICA | Q88: 0.15 | R88: 0.06 | S88: 0.2 | T88: 16 | U88: 3917.40.90 | V88: 0 | W88: 17897801312193 | X88: 0.56 | Y88: 0.215 | Z88: 0.65 | AA88: =Y88*X88*Z88 -> 0.07826 | AB88: 720 | AC88: 27897801312190 | AD88: Validade indeterminada
B89: 212 | C89: BUCHA RED.ROSC. 1.1/4 X 3/4 | D89: CONEXOES ROSCAVEIS | E89: AF | F89: PC | G89: Sacos | H89: 0.0308 | I89: 30 | J89: 30 | K89: 40 | L89: =J89*I89*K89 -> 36000 | M89: 7897801312202 | N89: NÃO APLICA | O89: NÃO APLICA | P89: NÃO APLICA | Q89: 0.15 | R89: 0.05 | S89: 0.2 | T89: 16 | U89: 3917.40.90 | V89: 0 | W89: 17897801312209 | X89: 0.45 | Y89: 0.2 | Z89: 0.65 | AA89: =Y89*X89*Z89 -> 0.0585 | AB89: 720 | AC89: 27897801312206 | AD89: Validade indeterminada
B90: 213 | C90: BUCHA RED.ROSC. 1.1/2 X 1/2 | D90: CONEXOES ROSCAVEIS | E90: AF | F90: PC | G90: Sacos | H90: 0.0407 | I90: 50 | J90: 30 | K90: 50 | L90: =J90*I90*K90 -> 75000 | M90: 7897801311533 | N90: NÃO APLICA | O90: NÃO APLICA | P90: NÃO APLICA | Q90: 0.15 | R90: 0.07 | S90: 0.18 | T90: 16 | U90: 3917.40.90 | V90: 0 | W90: 17897801311530 | X90: 0.45 | Y90: 0.2 | Z90: 0.7 | AA90: =Y90*X90*Z90 -> 0.063 | AB90: 480 | AC90: 27897801311537 | AD90: Validade indeterminada
... B99: 223 | C99: CAP ROSCAVEL 1.1/2 | D99: CONEXOES ROSCAVEIS | E99: AF | F99: PC | G99: Sacos | H99: 0.0641 | I99: 60 | J99: 40 | K99: 60 | L99: =J99*I99*K99 -> 144000 | M99: 7897801311434 | N99: NÃO APLICA | O99: NÃO APLICA | P99: NÃO APLICA | Q99: 0.185 | R99: 0.063 | S99: 0.215 | T99: 10 | U99: 3917.40.90 | V99: 0 | W99: 17897801311431 | X99: 0.52 | Y99: 0.2 | Z99: 0.8 | AA99: =Y99*X99*Z99 -> 0.0832 | AB99: 350 | AC99: 27897801311438 | AD99: Validade indeterminada
B100: 224 | C100: CAP ROSCAVEL 1.1/4 | D100: CONEXOES ROSCAVEIS | E100: AF | F100: PC | G100: Sacos | H100: 0.0383 | I100: 16 | J100: 15 | K100: 4 | L100: =J100*I100*K100 -> 960 | M100: 7897801319423 | N100: 0.16 | O100: 0.66 | P100: 0.47 | Q100: 0.15 | R100: 0.04 | S100: 0.16 | T100: 10 | U100: 3917.40.90 | V100: 0 | W100: 17897801319420 | X100: 0.47 | Y100: 0.16 | Z100: 0.16 | AA100: =Y100*X100*Z100 -> 0.012032 | AB100: 500 | AC100: 27897801319427 | AD100: Validade indeterminada
B101: 225 | C101: CAP ROSCAVEL 2 | D101: CONEXOES ROSCAVEIS | E101: AF | F101: PC | G101: Sacos | H101: 0.07 | I101: 71 | J101: 17 | K101: 50 | L101: =J101*I101*K101 -> 60350 | M101: 7897801319430 | N101: NÃO APLICA | O101: NÃO APLICA | P101: NÃO APLICA | Q101: 0.155 | R101: 0.05 | S101: 0.19 | T101: 5 | U101: 3917.40.90 | V101: 0 | W101: 17897801319437 | X101: 0.49 | Y101: 0.22 | Z101: 0.71 | AA101: =Y101*X101*Z101 -> 0.076538 | AB101: 250 | AC101: 27897801319434 | AD101: Validade indeterminada
B102: 226 | C102: CURVA ROSC 1/2 | D102: CONEXOES ROSCAVEIS | E102: AF | F102: PC | G102: Sacos | H102: 0.019 | I102: 60 | J102: 20 | K102: 60 | L102: =J102*I102*K102 -> 72000 | M102: 7897801312721 | N102: NÃO APLICA | O102: NÃO APLICA | P102: NÃO APLICA | Q102: 0.15 | R102: 0.05 | S102: 0.2 | T102: 24 | U102: 3917.40.90 | V102: 0 | W102: 17897801312728 | X102: 0.5 | Y102: 0.2 | Z102: 0.65 | AA102: =Y102*X102*Z102 -> 0.065 | AB102: 960 | AC102: 27897801312725 | AD102: Validade indeterminada
B103: 227 | C103: CURVA ROSC 3/4 | D103: CONEXOES ROSCAVEIS | E103: AF | F103: PC | G103: Sacos | H103: 0.031 | I103: 130 | J103: 20 | K103: 80 | L103: =J103*I103*K103 -> 208000 | M103: 7897801312738 | N103: NÃO APLICA | O103: NÃO APLICA | P103: NÃO APLICA | Q103: 0.23 | R103: 0.07 | S103: 0.3 | T103: 24 | U103: 3917.40.90 | V103: 0 | W103: 17897801312735 | X103: 0.5 | Y103: 0.25 | Z103: 0.7 | AA103: =Y103*X103*Z103 -> 0.0875 | AB103: 480 | AC103: 27897801312732 | AD103: Validade indeterminada
B104: 228 | C104: CURVA ROSC 1.1/4 | D104: CONEXOES ROSCAVEIS | E104: AF | F104: PC | G104: Sacos | H104: 0.0947 | I104: 150 | J104: 40 | K104: 40 | L104: =J104*I104*K104 -> 240000 | M104: 7897801312639 | N104: NÃO APLICA | O104: NÃO APLICA | P104: NÃO APLICA | Q104: 0.18 | R104: 0.09 | S104: 0.26 | T104: 8 | U104: 3917.40.90 | V104: 0 | W104: 17897801312636 | X104: 0.45 | Y104: 0.25 | Z104: 0.65 | AA104: =Y104*X104*Z104 -> 0.073125 | AB104: 160 | AC104: 27897801312633 | AD104: Validade indeterminada
B105: 229 | C105: CURVA ROSC 1.1/2 | D105: CONEXOES ROSCAVEIS | E105: AF | F105: PC | G105: Sacos | H105: 0.151 | I105: 30 | J105: 30 | K105: 40 | L105: =J105*I105*K105 -> 36000 | M105: 7897801312646 | N105: NÃO APLICA | O105: NÃO APLICA | P105: NÃO APLICA | Q105: 0.25 | R105: 0.1 | S105: 0.385 | T105: 10 | U105: 3917.40.90 | V105: 0 | W105: 17897801312643 | X105: 0.59 | Y105: 0.2 | Z105: 0.86 | AA105: =Y105*X105*Z105 -> 0.10148 | AB105: 100 | AC105: 27897801312640 | AD105: Validade indeterminada
B106: 230 | C106: CURVA ROSC 1 | D106: CONEXOES ROSCAVEIS | E106: AF | F106: PC | G106: Sacos | H106: 0.0588 | I106: 10 | J106: 30 | K106: 30 | L106: =J106*I106*K106 -> 9000 | M106: 7897801312745 | N106: NÃO APLICA | O106: NÃO APLICA | P106: NÃO APLICA | Q106: 0.2 | R106: 0.055 | S106: 0.25 | T106: 12 | U106: 3917.40.90 | V106: 0 | W106: 17897801312742 | X106: 0.45 | Y106: 0.2 | Z106: 0.68 | AA106: =Y106*X106*Z106 -> 0.0612 | AB106: 240 | AC106: 27897801312749 | AD106: Validade indeterminada
B107: 250 | C107: JOELHO 45 1/2 | D107: CONEXOES ROSCAVEIS | E107: AF | F107: PC | G107: Sacos | H107: 0.0265 | I107: 50 | J107: 35 | K107: 30 | L107: =J107*I107*K107 -> 52500 | M107: 7897801311656 | N107: NÃO APLICA | O107: NÃO APLICA | P107: NÃO APLICA | Q107: 0.16 | R107: 0.031 | S107: 0.195 | T107: 15 | U107: 3917.40.90 | V107: 0 | W107: 17897801311653 | X107: 0.54 | Y107: 0.175 | Z107: 0.79 | AA107: =Y107*X107*Z107 -> 0.074655 | AB107: 825 | AC107: 27897801311650 | AD107: Validade indeterminada
B108: 251 | C108: JOELHO 45 3/4 | D108: CONEXOES ROSCAVEIS | E108: AF | F108: PC | G108: Sacos | H108: 0.037 | I108: 65 | J108: 45 | K108: 35 | L108: =J108*I108*K108 -> 102375 | M108: 7897801311496 | N108: NÃO APLICA | O108: NÃO APLICA | P108: NÃO APLICA | Q108: 0.24 | R108: 0.05 | S108: 0.24 | T108: 15 | U108: 3917.40.90 | V108: 0 | W108: 17897801311493 | X108: 0.56 | Y108: 0.21 | Z108: 0.81 | AA108: =Y108*X108*Z108 -> 0.095256 | AB108: 600 | AC108: 27897801311490 | AD108: Validade indeterminada
B109: 252 | C109: JOELHO 45 1 | D109: CONEXOES ROSCAVEIS | E109: AF | F109: PC | G109: Sacos | H109: 0.0387 | I109: 78 | J109: 50 | K109: 44 | L109: =J109*I109*K109 -> 171600 | M109: 7897801312240 | N109: NÃO APLICA | O109: NÃO APLICA | P109: NÃO APLICA | Q109: 0.14 | R109: 0.08 | S109: 0.18 | T109: 8 | U109: 3917.40.90 | V109: 0 | W109: 17897801312247 | X109: 0.45 | Y109: 0.18 | Z109: 0.65 | AA109: =Y109*X109*Z109 -> 0.05265 | AB109: 336 | AC109: 27897801312244 | AD109: Validade indeterminada
B110: 254 | C110: JOELHO 45 1.1/2 | D110: CONEXOES ROSCAVEIS | E110: AF | F110: PC | G110: Sacos | H110: 0.114 | I110: 90 | J110: 60 | K110: 60 | L110: =J110*I110*K110 -> 324000 | M110: 7897801312257 | N110: NÃO APLICA | O110: NÃO APLICA | P110: NÃO APLICA | Q110: 0.2 | R110: 0.08 | S110: 0.26 | T110: 8 | U110: 3917.40.90 | V110: 0 | W110: 17897801312254 | X110: 0.45 | Y110: 0.24 | Z110: 0.65 | AA110: =Y110*X110*Z110 -> 0.0702 | AB110: 192 | AC110: 27897801312251 | AD110: Validade indeterminada
B111: 256 | C111: JOELHO 90 ROSC 1/2 | D111: CONEXOES ROSCAVEIS | E111: AF | F111: PC | G111: Sacos | H111: 0.0267 | I111: 43 | J111: 30 | K111: 43 | L111: =J111*I111*K111 -> 55470 | M111: 7897801302418 | N111: NÃO APLICA | O111: NÃO APLICA | P111: NÃO APLICA | Q111: 0.21 | R111: 0.05 | S111: 0.25 | T111: 20 | U111: 3917.40.90 | V111: 0 | W111: 17897801302415 | X111: 0.55 | Y111: 0.21 | Z111: 0.74 | AA111: =Y111*X111*Z111 -> 0.08547 | AB111: 800 | AC111: 47897801302416 | AD111: Validade indeterminada
B112: 257 | C112: JOELHO 90 ROSC 3/4 | D112: CONEXOES ROSCAVEIS | E112: AF | F112: PC | G112: Sacos | H112: 0.0385 | I112: 48 | J112: 36 | K112: 48 | L112: =J112*I112*K112 -> 82944 | M112: 7897801301404 | N112: NÃO APLICA | O112: NÃO APLICA | P112: NÃO APLICA | Q112: 0.22 | R112: 0.06 | S112: 0.24 | T112: 20 | U112: 3917.40.90 | V112: 0 | W112: 17897801301401 | X112: 0.52 | Y112: 0.18 | Z112: 0.78 | AA112: =Y112*X112*Z112 -> 0.073008 | AB112: 560 | AC112: 47897801301402 | AD112: Validade indeterminada
... B130: 290 | C130: NIPEL ROSCAVEL 1.1/2 | D130: CONEXOES ROSCAVEIS | E130: AF | F130: PC | G130: Sacos | H130: 0.0636 | I130: 80 | J130: 56 | K130: 56 | L130: =J130*I130*K130 -> 250880 | M130: 7897801308601 | N130: NÃO APLICA | O130: NÃO APLICA | P130: NÃO APLICA | Q130: 0.22 | R130: 0.052 | S130: 0.2 | T130: 10 | U130: 3917.40.90 | V130: 0 | W130: 17897801308608 | X130: 0.6 | Y130: 0.19 | Z130: 0.83 | AA130: =Y130*X130*Z130 -> 0.09462 | AB130: 350 | AC130: 47897801308609 | AD130: Validade indeterminada
B131: 291 | C131: NIPEL ROSCAVEL 1.1/4 | D131: CONEXOES ROSCAVEIS | E131: AF | F131: PC | G131: Sacos | H131: 0.0409 | I131: 76 | J131: 21 | K131: 48 | L131: =J131*I131*K131 -> 76608 | M131: 7897801319447 | N131: 0.76 | O131: 0.76 | P131: 0.48 | Q131: 0.05 | R131: 0.16 | S131: 0.19 | T131: 10 | U131: 3917.40.90 | V131: 0 | W131: 17897801319444 | X131: 0.19 | Y131: 0.49 | Z131: 0.7 | AA131: =Y131*X131*Z131 -> 0.06517 | AB131: 420 | AC131: 27897801319441 | AD131: Validade indeterminada
B132: 292 | C132: NIPEL ROSCAVEL 2 | D132: CONEXOES ROSCAVEIS | E132: AF | F132: PC | G132: Sacos | H132: 0.0839 | I132: 60 | J132: 30 | K132: 200 | L132: =J132*I132*K132 -> 360000 | M132: 7897801319454 | N132: 0.21 | O132: 0.69 | P132: 0.48 | Q132: 0.2 | R132: 0.06 | S132: 0.25 | T132: 10 | U132: 3917.40.90 | V132: 0 | W132: 17897801319451 | X132: 0.48 | Y132: 0.21 | Z132: 0.69 | AA132: =Y132*X132*Z132 -> 0.069552 | AB132: 200 | AC132: 27897801319458 | AD132: Validade indeterminada
B133: 293 | C133: PLUG ROSCAVEL 1/2 | D133: CONEXOES ROSCAVEIS | E133: AF | F133: PC | G133: Sacos | H133: 0.0055 | I133: 23.5 | J133: 23.5 | K133: 21.5 | L133: =J133*I133*K133 -> 11873.375 | M133: 7897801301473 | N133: NÃO APLICA | O133: NÃO APLICA | P133: NÃO APLICA | Q133: 0.255 | R133: 0.025 | S133: 0.225 | T133: 50 | U133: 3917.40.90 | V133: 0 | W133: 17897801301470 | X133: 0.52 | Y133: 0.17 | Z133: 0.77 | AA133: =Y133*X133*Z133 -> 0.068068 | AB133: 3750 | AC133: 47897801301471 | AD133: Validade indeterminada
B134: 294 | C134: PLUG ROSCAVEL 3/4 | D134: CONEXOES ROSCAVEIS | E134: AF | F134: PC | G134: Sacos | H134: 0.0092 | I134: 26.9 | J134: 26.9 | K134: 27 | L134: =J134*I134*K134 -> 19537.47 | M134: 7897801302111 | N134: NÃO APLICA | O134: NÃO APLICA | P134: NÃO APLICA | Q134: 0.16 | R134: 0.04 | S134: 0.2 | T134: 50 | U134: 3917.40.90 | V134: 0 | W134: 17897801302118 | X134: 0.45 | Y134: 0.18 | Z134: 0.65 | AA134: =Y134*X134*Z134 -> 0.05265 | AB134: 2200 | AC134: 47897801302119 | AD134: Validade indeterminada
B135: 295 | C135: PLUG ROSCAVEL 1 | D135: CONEXOES ROSCAVEIS | E135: AF | F135: PC | G135: Sacos | H135: 0.0161 | I135: 34 | J135: 34 | K135: 34 | L135: =J135*I135*K135 -> 39304 | M135: 7897801308694 | N135: NÃO APLICA | O135: NÃO APLICA | P135: NÃO APLICA | Q135: 0.25 | R135: 0.055 | S135: 0.26 | T135: 50 | U135: 3917.40.90 | V135: 0 | W135: 17897801308691 | X135: 0.5 | Y135: 0.19 | Z135: 0.81 | AA135: =Y135*X135*Z135 -> 0.07695 | AB135: 1400 | AC135: 47897801308692 | AD135: Validade indeterminada
B136: 296 | C136: PLUG ROSCAVEL 1.1/2 | D136: CONEXOES ROSCAVEIS | E136: AF | F136: PC | G136: Sacos | H136: 0.0521 | I136: 51 | J136: 45 | K136: 51 | L136: =J136*I136*K136 -> 117045 | M136: 7897801311465 | N136: NÃO APLICA | O136: NÃO APLICA | P136: NÃO APLICA | Q136: 0.235 | R136: 0.06 | S136: 0.26 | T136: 20 | U136: 3917.40.90 | V136: 0 | W136: 17897801311462 | X136: 0.49 | Y136: 0.18 | Z136: 0.79 | AA136: =Y136*X136*Z136 -> 0.069678 | AB136: 400 | AC136: 27897801311469 | AD136: Validade indeterminada
B137: 297 | C137: PLUG ROSCAVEL 1.1/4 | D137: CONEXOES ROSCAVEIS | E137: AF | F137: PC | G137: Sacos | H137: 0.0308 | I137: 40 | J137: 40 | K137: 40 | L137: =J137*I137*K137 -> 64000 | M137: 7897801312288 | N137: NÃO APLICA | O137: NÃO APLICA | P137: NÃO APLICA | Q137: 0.21 | R137: 0.05 | S137: 0.235 | T137: 20 | U137: 3917.40.90 | V137: 0 | W137: 17897801312285 | X137: 0.49 | Y137: 0.21 | Z137: 0.79 | AA137: =Y137*X137*Z137 -> 0.081291 | AB137: 700 | AC137: 27897801312282 | AD137: Validade indeterminada
B138: 298 | C138: PLUG ROSCAVEL 2 | D138: CONEXOES ROSCAVEIS | E138: AF | F138: PC | G138: Sacos | H138: 0.0612 | I138: 60 | J138: 60 | K138: 50 | L138: =J138*I138*K138 -> 180000 | M138: 7897801312295 | N138: NÃO APLICA | O138: NÃO APLICA | P138: NÃO APLICA | Q138: 0.12 | R138: 0.05 | S138: 0.17 | T138: 5 | U138: 3917.40.90 | V138: 0 | W138: 17897801312292 | X138: 0.5 | Y138: 0.17 | Z138: 0.65 | AA138: =Y138*X138*Z138 -> 0.05525 | AB138: 250 | AC138: 27897801312299 | AD138: Validade indeterminada
B139: 299 | C139: TE ROSCAVEL 1/2 | D139: CONEXOES ROSCAVEIS | E139: AF | F139: PC | G139: Sacos | H139: 0.0364 | I139: 56 | J139: 30 | K139: 43 | L139: =J139*I139*K139 -> 72240 | M139: 7897801302517 | N139: NÃO APLICA | O139: NÃO APLICA | P139: NÃO APLICA | Q139: 0.25 | R139: 0.05 | S139: 0.25 | T139: 20 | U139: 3917.40.90 | V139: 0 | W139: 17897801302514 | X139: 0.52 | Y139: 0.22 | Z139: 0.76 | AA139: =Y139*X139*Z139 -> 0.086944 | AB139: 640 | AC139: 47897801302515 | AD139: Validade indeterminada
B140: 300 | C140: TE ROSCAVEL 3/4 | D140: CONEXOES ROSCAVEIS | E140: AF | F140: PC | G140: Sacos | H140: 0.0512 | I140: 60 | J140: 36 | K140: 48 | L140: =J140*I140*K140 -> 103680 | M140: 7897801301350 | N140: NÃO APLICA | O140: NÃO APLICA | P140: NÃO APLICA | Q140: 0.23 | R140: 0.07 | S140: 0.27 | T140: 20 | U140: 3917.40.90 | V140: 0 | W140: 17897801301357 | X140: 0.51 | Y140: 0.19 | Z140: 0.79 | AA140: =Y140*X140*Z140 -> 0.076551 | AB140: 400 | AC140: 27897801301354 | AD140: Validade indeterminada
B141: 301 | C141: TE ROSCAVEL 1 | D141: CONEXOES ROSCAVEIS | E141: AF | F141: PC | G141: Sacos | H141: 0.0916 | I141: 61 | J141: 78 | K141: 78 | L141: =J141*I141*K141 -> 371124 | M141: 7897801308953 | N141: NÃO APLICA | O141: NÃO APLICA | P141: NÃO APLICA | Q141: 0.2 | R141: 0.08 | S141: 0.3 | T141: 16 | U141: 3917.40.90 | V141: 0 | W141: 17897801308950 | X141: 0.42 | Y141: 0.23 | Z141: 0.6 | AA141: =Y141*X141*Z141 -> 0.05796 | AB141: 224 | AC141: 27897801308957 | AD141: Validade indeterminada
B142: 302 | C142: TE ROSCAVEL 1.1/4 | D142: CONEXOES ROSCAVEIS | E142: AF | F142: PC | G142: Sacos | H142: 0.1498 | I142: 60 | J142: 80 | K142: 10 | L142: =J142*I142*K142 -> 48000 | M142: 7897801311861 | N142: NÃO APLICA | O142: NÃO APLICA | P142: NÃO APLICA | Q142: 0.2 | R142: 0.12 | S142: 0.3 | T142: 12 | U142: 3917.40.90 | V142: 0 | W142: 17897801311868 | X142: 0.42 | Y142: 0.23 | Z142: 0.65 | AA142: =Y142*X142*Z142 -> 0.06279 | AB142: 108 | AC142: 27897801311865 | AD142: Validade indeterminada
B143: 303 | C143: TE ROSCAVEL 1.1/2 | D143: CONEXOES ROSCAVEIS | E143: AF | F143: PC | G143: Sacos | H143: 0.197 | I143: 61 | J143: 104 | K143: 84 | L143: =J143*I143*K143 -> 532896 | M143: 7897801311632 | N143: NÃO APLICA | O143: NÃO APLICA | P143: NÃO APLICA | Q143: 0.25 | R143: 0.105 | S143: 0.37 | T143: 10 | U143: 3917.40.90 | V143: 0 | W143: 17897801311639 | X143: 0.58 | Y143: 0.22 | Z143: 0.76 | AA143: =Y143*X143*Z143 -> 0.096976 | AB143: 100 | AC143: 27897801311636 | AD143: Validade indeterminada
B144: 304 | C144: TE ROSCAVEL 2 | D144: CONEXOES ROSCAVEIS | E144: AF | F144: PC | G144: Sacos | H144: 0.3011 | I144: 10 | J144: 70 | K144: 70 | L144: =J144*I144*K144 -> 49000 | M144: 7897801311878 | N144: NÃO APLICA | O144: NÃO APLICA | P144: NÃO APLICA | Q144: 0.24 | R144: 0.12 | S144: 0.33 | T144: 6 | U144: 3917.40.90 | V144: 0 | W144: 17897801311875 | X144: 0.4 | Y144: 0.25 | Z144: 0.65 | AA144: =Y144*X144*Z144 -> 0.065 | AB144: 54 | AC144: 27897801311872 | AD144: Validade indeterminada
... B330: 519 | C330: ADESIVO FRASCO 850 G | D330: ADESIVOS E COMPLEMENTOS | E330: AF | F330: PC | G330: Caixas | H330: 0.85 | I330: 95 | J330: 200 | K330: 95 | L330: =J330*I330*K330 -> 1805000 | M330: 7897801302678 | N330: NÃO APLICA | O330: NÃO APLICA | P330: NÃO APLICA | Q330: 0.19 | R330: 0.22 | S330: 0.28 | T330: 6 | U330: 3506.10.90 | V330: 0 | W330: 17897801302675 | X330: 0.3 | Y330: 0.25 | Z330: 0.6 | AA330: =Y330*X330*Z330 -> 0.045 | AB330: 18 | AC330: 27897801302672 | AD330: 18 meses
B331: 520 | C331: SOLUCAO PREPARADORA 200 ML | D331: ADESIVOS E COMPLEMENTOS | E331: AF | F331: PC | G331: Caixas | H331: 0.158 | I331: 70 | J331: 83 | K331: 70 | L331: =J331*I331*K331 -> 406700 | M331: 7897801302685 | N331: NÃO APLICA | O331: NÃO APLICA | P331: NÃO APLICA | Q331: 0.145 | R331: 0.235 | S331: 0.205 | T331: 12 | U331: 3814.00.90 | V331: 0 | W331: 17897801302682 | X331: NÃO APLICA | Y331: NÃO APLICA | Z331: NÃO APLICA | AB331: 120 | AC331: 27897801302689 | AD331: 12 meses
B332: 521 | C332: SOLUCAO PREPARADORA 1000 ML | D332: ADESIVOS E COMPLEMENTOS | E332: AF | F332: PC | G332: Caixas | H332: 0.79 | I332: 98 | J332: 190 | K332: 98 | L332: =J332*I332*K332 -> 1824760 | M332: 7897801302692 | N332: NÃO APLICA | O332: NÃO APLICA | P332: NÃO APLICA | Q332: 0.195 | R332: 0.235 | S332: 0.28 | T332: 6 | U332: 3814.00.90 | V332: 0 | W332: 17897801302699 | X332: 0.3 | Y332: 0.24 | Z332: 0.595 | AA332: =Y332*X332*Z332 -> 0.04284 | AB332: 18 | AC332: 27897801302696 | AD332: 12 meses
B333: 522 | C333: ADESIVO PLÁSTICO EXTRAFORTE PARA PVC 175g C/ PINCEL APLICADOR | D333: ADESIVOS E COMPLEMENTOS | E333: AF | F333: PC | G333: Caixas | H333: 0.175 | I333: 68 | J333: 103 | K333: 68 | L333: 431200 | M333: 7897801320894 | N333: NÃO APLICA | O333: NÃO APLICA | P333: NÃO APLICA | Q333: 0.16 | R333: 0.21 | S333: 0.205 | T333: 12 | U333: 3506.10.90 | V333: 0 | W333: 17897801320891 | X333: 0.37 | Y333: 0.44 | Z333: 0.485 | AA333: 0.079 | AB333: 120 | AC333: 27897801320898 | AD333: 18 meses
B334: 523 | C334: ADESIVO PLÁSTICO EXTRAFORTE PARA PVC 850g | D334: ADESIVOS E COMPLEMENTOS | E334: AF | F334: PC | G334: Caixas | H334: 0.85 | I334: 94 | J334: 220 | K334: 94 | L334: 1805000 | M334: 7897801320900 | N334: NÃO APLICA | O334: NÃO APLICA | P334: NÃO APLICA | Q334: 0.205 | R334: 0.242 | S334: 0.285 | T334: 6 | U334: 3506.10.90 | V334: 0 | W334: 17897801320907 | X334: 0.295 | Y334: 0.255 | Z334: 0.605 | AA334: 0.0455 | AB334: 18 | AC334: 27897801320904 | AD334: 18 meses
B335: 540 | C335: REGISTRO ESFERA SOLD - 20MM | D335: REGISTROS ESFERA COMPACTO | E335: AF | F335: PC | G335: Sacos | H335: 0.0419 | I335: 66 | J335: 58 | K335: 33 | L335: =J335*I335*K335 -> 126324 | M335: 7897801301008 | N335: NÃO APLICA | O335: NÃO APLICA | P335: NÃO APLICA | Q335: 0.13 | R335: 0.055 | S335: 0.16 | T335: 6 | U335: 8481.80.95 | V335: 0 | W335: 17897801301005 | X335: 0.49 | Y335: 0.19 | Z335: 0.65 | AA335: =Y335*X335*Z335 -> 0.060515 | AB335: 390 | AC335: 27897801301002 | AD335: Validade indeterminada
B336: 541 | C336: REGISTRO ESFERA SOLD - 25MM | D336: REGISTROS ESFERA COMPACTO | E336: AF | F336: PC | G336: Sacos | H336: 0.0546 | I336: 66 | J336: 65 | K336: 38 | L336: =J336*I336*K336 -> 163020 | M336: 7897801301015 | N336: NÃO APLICA | O336: NÃO APLICA | P336: NÃO APLICA | Q336: 0.15 | R336: 0.04 | S336: 0.2 | T336: 6 | U336: 8481.80.95 | V336: 0 | W336: 17897801301012 | X336: 0.52 | Y336: 0.18 | Z336: 0.7 | AA336: =Y336*X336*Z336 -> 0.06552 | AB336: 330 | AC336: 27897801301019 | AD336: Validade indeterminada
B337: 542 | C337: REGISTRO ESFERA SOLD - 32MM | D337: REGISTROS ESFERA COMPACTO | E337: AF | F337: PC | G337: Sacos | H337: 0.1082 | I337: 82 | J337: 80 | K337: 47 | L337: =J337*I337*K337 -> 308320 | M337: 7897801301022 | N337: NÃO APLICA | O337: NÃO APLICA | P337: NÃO APLICA | Q337: 0.15 | R337: 0.05 | S337: 0.2 | T337: 4 | U337: 8481.80.95 | V337: 0 | W337: 17897801301029 | X337: 0.45 | Y337: 0.2 | Z337: 0.65 | AA337: =Y337*X337*Z337 -> 0.0585 | AB337: 160 | AC337: 27897801301026 | AD337: Validade indeterminada
B338: 543 | C338: REGISTRO ESFERA SOLD - 40MM | D338: REGISTROS ESFERA COMPACTO | E338: AF | F338: PC | G338: Sacos | H338: 0.2037 | I338: 111 | J338: 102 | K338: 58 | L338: =J338*I338*K338 -> 656676 | M338: 7897801301060 | N338: NÃO APLICA | O338: NÃO APLICA | P338: NÃO APLICA | Q338: 0.23 | R338: 0.06 | S338: 0.23 | T338: 3 | U338: 8481.80.95 | V338: 0 | W338: 17897801301067 | X338: 0.51 | Y338: 0.19 | Z338: 0.74 | AA338: =Y338*X338*Z338 -> 0.071706 | AB338: 75 | AC338: 27897801301064 | AD338: Validade indeterminada
B339: 544 | C339: REGISTRO ESFERA SOLD - 50MM | D339: REGISTROS ESFERA COMPACTO | E339: AF | F339: PC | G339: Sacos | H339: 0.2697 | I339: 115 | J339: 109 | K339: 70 | L339: =J339*I339*K339 -> 877450 | M339: 7897801301077 | N339: NÃO APLICA | O339: NÃO APLICA | P339: NÃO APLICA | Q339: 0.2 | R339: 0.08 | S339: 0.2 | T339: 3 | U339: 8481.80.95 | V339: 0 | W339: 17897801301074 | X339: 0.45 | Y339: 0.17 | Z339: 0.7 | AA339: =Y339*X339*Z339 -> 0.05355 | AB339: 60 | AC339: 27897801301071 | AD339: Validade indeterminada
B340: 545 | C340: REGISTRO ESFERA SOLD - 60MM | D340: REGISTROS ESFERA COMPACTO | E340: AF | F340: PC | G340: Sacos | H340: 0.4226 | I340: 129 | J340: 125 | K340: 81 | L340: =J340*I340*K340 -> 1306125 | M340: 7897801301084 | N340: NÃO APLICA | O340: NÃO APLICA | P340: NÃO APLICA | Q340: 0.2 | R340: 0.08 | S340: 0.3 | T340: 2 | U340: 8481.80.95 | V340: 0 | W340: 17897801301081 | X340: 0.5 | Y340: 0.17 | Z340: 0.65 | AA340: =Y340*X340*Z340 -> 0.05525 | AB340: 38 | AC340: 27897801301088 | AD340: Validade indeterminada
B341: 546 | C341: REGISTRO ESFERA SOLD - 75MM | D341: REGISTROS ESFERA COMPACTO | E341: AF | F341: PC | G341: Sacos | H341: 1.0342 | I341: 180 | J341: 115 | K341: 165 | L341: =J341*I341*K341 -> 3415500 | M341: 7897801312400 | N341: NÃO APLICA | O341: NÃO APLICA | P341: NÃO APLICA | Q341: 0.172 | R341: 0.202 | S341: 0.23 | T341: 2 | U341: 8481.80.95 | V341: 0 | W341: 17897801312407 | X341: 0 | Y341: 0 | Z341: 0 | AA341: 0 | AB341: 0 | AC341: 0 | AD341: Validade indeterminada
B342: 547 | C342: REGISTRO ESFERA SOLD - 85MM | D342: REGISTROS ESFERA COMPACTO | E342: AF | F342: PC | G342: Sacos | H342: 1.5453 | I342: 205 | J342: 130 | K342: 180 | L342: =J342*I342*K342 -> 4797000 | M342: 7897801312417 | N342: NÃO APLICA | O342: NÃO APLICA | P342: NÃO APLICA | Q342: 0.255 | R342: 0.162 | S342: 0.31 | T342: 2 | U342: 8481.80.95 | V342: 0 | W342: 17897801312414 | X342: 0 | Y342: 0 | Z342: 0 | AA342: 0 | AB342: 0 | AC342: 0 | AD342: Validade indeterminada
B343: 548 | C343: REGISTRO ESFERA SOLD - 110MM | D343: REGISTROS ESFERA COMPACTO | E343: AF | F343: PC | G343: Sacos | H343: 2.4063 | I343: 235 | J343: 160 | K343: 210 | L343: =J343*I343*K343 -> 7896000 | M343: 7897801313858 | N343: NÃO APLICA | O343: NÃO APLICA | P343: NÃO APLICA | Q343: 0.193 | R343: 0.167 | S343: 0.26 | T343: 1 | U343: 8481.80.95 | V343: 0 | W343: 17897801313855 | X343: 0 | Y343: 0 | Z343: 0 | AA343: 0 | AB343: 0 | AC343: 0 | AD343: Validade indeterminada
B344: 551 | C344: REGISTRO ESFERA ROSCAVEL - 1/2 | D344: REGISTROS ESFERA COMPACTO | E344: AF | F344: PC | G344: Sacos | H344: 0.0511 | I344: 66 | J344: 58 | K344: 33 | L344: =J344*I344*K344 -> 126324 | M344: 7897801301039 | N344: NÃO APLICA | O344: NÃO APLICA | P344: NÃO APLICA | Q344: 0.175 | R344: 0.035 | S344: 0.175 | T344: 6 | U344: 8481.80.95 | V344: 0 | W344: 17897801301036 | X344: 0.525 | Y344: 0.16 | Z344: 0.78 | AA344: =Y344*X344*Z344 -> 0.06552 | AB344: 390 | AC344: 27897801301033 | AD344: Validade indeterminada
B345: 552 | C345: REGISTRO ESFERA ROSCAVEL - 3/4 | D345: REGISTROS ESFERA COMPACTO | E345: AF | F345: PC | G345: Sacos | H345: 0.0625 | I345: 66 | J345: 65 | K345: 38 | L345: =J345*I345*K345 -> 163020 | M345: 7897801301046 | N345: NÃO APLICA | O345: NÃO APLICA | P345: NÃO APLICA | Q345: 0.15 | R345: 0.04 | S345: 0.2 | T345: 6 | U345: 8481.80.95 | V345: 0 | W345: 17897801301043 | X345: 0.52 | Y345: 0.18 | Z345: 0.7 | AA345: =Y345*X345*Z345 -> 0.06552 | AB345: 330 | AC345: 27897801301040 | AD345: Validade indeterminada
B346: 553 | C346: REGISTRO ESFERA ROSCAVEL - 1 | D346: REGISTROS ESFERA COMPACTO | E346: AF | F346: PC | G346: Sacos | H346: 0.12 | I346: 82 | J346: 80 | K346: 47 | L346: =J346*I346*K346 -> 308320 | M346: 7897801301053 | N346: NÃO APLICA | O346: NÃO APLICA | P346: NÃO APLICA | Q346: 0.15 | R346: 0.05 | S346: 0.2 | T346: 2 | U346: 8481.80.95 | V346: 0 | W346: 17897801301050 | X346: 0.45 | Y346: 0.2 | Z346: 0.65 | AA346: =Y346*X346*Z346 -> 0.0585 | AB346: 160 | AC346: 27897801301057 | AD346: Validade indeterminada
B347: 554 | C347: REGISTRO ESFERA ROSCAVEL - 1.1/4 | D347: REGISTROS ESFERA COMPACTO | E347: AF | F347: PC | G347: Sacos | H347: 0.2059 | I347: 111 | J347: 70 | K347: 95 | L347: =J347*I347*K347 -> 738150 | M347: 7897801301091 | N347: NÃO APLICA | O347: NÃO APLICA | P347: NÃO APLICA | Q347: 0.14 | R347: 0.08 | S347: 0.26 | T347: 3 | U347: 8481.80.95 | V347: 0 | W347: 17897801301098 | X347: 0.52 | Y347: 0.22 | Z347: 0.7 | AA347: =Y347*X347*Z347 -> 0.08008 | AB347: 75 | AC347: 27897801301095 | AD347: Validade indeterminada
...

Sheet DADOS NE_GO
H2: INDIVUDUAL (MM) | N2: Armazenamento (TUBOS) (M) | Q2: EMBALAGEM (M) | X2: Reembalagem (Master) (M)
B3: Produto | C3: Descrição | D3: Linha | E3: Família | F3: Unidade | G3: Tipo Embalagem | H3: Peso Bruto (produto + embalagem) | I3: Comprimento | J3: Altura | K3: Largura | L3: Cubagem | M3: Código de Barras | N3: Altur.Armaze | O3: Compr.Armaze | P3: Largu.Armaze | Q3: Larg.Emb | R3: Alt.Emb | S3: Compr.Emb | T3: Quantidade Embalagem | U3: Pos.IPI/NCM | V3: Aliq. IPI | W3: Código de Barras | X3: Larg.Reemb | Y3: Alt.Reemb | Z3: Compr.Reemb | AA3: Cubagem | AB3: Quantidade | AC3: Código de Barras | AD3: Data de validade
B4: 23 | C4: TUBO PVC SOLDAVEL - 6M - 20MM | D4: TUBOS PVC SOLDAVEL | E4: AF | F4: BR | G4: Amarrados | H4: 0.82 | I4: 6000 | J4: 20 | K4: 20 | L4: =J4*I4*K4 -> 2400000 | M4: 7897801304009 | N4: 0.023 | O4: 6 | P4: 0.023 | Q4: 0.085 | R4: 0.085 | S4: 6 | T4: 12 | U4: 3917.23.00 | V4: 0 | W4: 17897801304006 | X4: NÃO APLICA | Y4: NÃO APLICA | Z4: NÃO APLICA | AB4: 0 | AC4: 27897801304003 | AD4: Validade indeterminada
B5: 24 | C5: TUBO PVC SOLDAVEL - 6M - 25MM | D5: TUBOS PVC SOLDAVEL | E5: AF | F5: BR | G5: Amarrados | H5: 1.172 | I5: 6000 | J5: 25 | K5: 25 | L5: =J5*I5*K5 -> 3750000 | M5: 7897801304016 | N5: 0.027 | O5: 6 | P5: 0.027 | Q5: 0.085 | R5: 0.085 | S5: 6 | T5: 8 | U5: 3917.23.00 | V5: 0 | W5: 17897801304013 | X5: NÃO APLICA | Y5: NÃO APLICA | Z5: NÃO APLICA | AB5: 0 | AC5: 27897801304010 | AD5: Validade indeterminada
B6: 25 | C6: TUBO PVC SOLDAVEL - 6M - 32MM | D6: TUBOS PVC SOLDAVEL | E6: AF | F6: BR | G6: Amarrados | H6: 1.845 | I6: 6000 | J6: 32 | K6: 32 | L6: =J6*I6*K6 -> 6144000 | M6: 7897801304023 | N6: 0.035 | O6: 6 | P6: 0.035 | Q6: 0.13 | R6: 0.09 | S6: 6 | T6: 10 | U6: 3917.23.00 | V6: 0 | W6: 17897801304020 | X6: NÃO APLICA | Y6: NÃO APLICA | Z6: NÃO APLICA | AB6: 0 | AC6: 27897801304027 | AD6: Validade indeterminada
B7: 26 | C7: TUBO PVC SOLDAVEL - 6M - 40MM | D7: TUBOS PVC SOLDAVEL | E7: AF | F7: BR | G7: Amarrados | H7: 2.645 | I7: 6000 | J7: 40 | K7: 40 | L7: =J7*I7*K7 -> 9600000 | M7: 7897801304030 | N7: 0.045 | O7: 6 | P7: 0.045 | Q7: 0.12 | R7: 0.075 | S7: 6 | T7: 5 | U7: 3917.23.00 | V7: 0 | W7: 17897801304037 | X7: NÃO APLICA | Y7: NÃO APLICA | Z7: NÃO APLICA | AB7: 0 | AC7: 27897801304034 | AD7: Validade indeterminada
B8: 27 | C8: TUBO PVC SOLDAVEL - 6M - 50MM | D8: TUBOS PVC SOLDAVEL | E8: AF | F8: BR | G8: Amarrados | H8: 4.122 | I8: 6000 | J8: 50 | K8: 50 | L8: =J8*I8*K8 -> 15000000 | M8: 7897801304047 | N8: 0.055 | O8: 6 | P8: 0.055 | Q8: 0.17 | R8: 0.11 | S8: 6 | T8: 5 | U8: 3917.23.00 | V8: 0 | W8: 17897801304044 | X8: NÃO APLICA | Y8: NÃO APLICA | Z8: NÃO APLICA | AB8: 0 | AC8: 27897801304041 | AD8: Validade indeterminada
B9: 28 | C9: TUBO PVC SOLDAVEL - 6M - 60MM | D9: TUBOS PVC SOLDAVEL | E9: AF | F9: BR | G9: Amarrados | H9: 5.382 | I9: 6000 | J9: 60 | K9: 60 | L9: =J9*I9*K9 -> 21600000 | M9: 7897801304054 | N9: 0.067 | O9: 6 | P9: 0.067 | Q9: 0.125 | R9: 0.12 | S9: 6 | T9: 3 | U9: 3917.23.00 | V9: 0 | W9: 17897801304051 | X9: NÃO APLICA | Y9: NÃO APLICA | Z9: NÃO APLICA | AB9: 0 | AC9: 27897801304058 | AD9: Validade indeterminada
B10: 29 | C10: TUBO PVC SOLDAVEL - 6M - 75MM | D10: TUBOS PVC SOLDAVEL | E10: AF | F10: BR | G10: Amarrados | H10: 8.53 | I10: 6000 | J10: 75 | K10: 75 | L10: =J10*I10*K10 -> 33750000 | M10: 7897801308564 | N10: 0.083 | O10: 6 | P10: 0.083 | Q10: 0.0752 | R10: 0.0752 | S10: 6 | T10: 1 | U10: 3917.23.00 | V10: 0 | W10: 17897801308561 | X10: NÃO APLICA | Y10: NÃO APLICA | Z10: NÃO APLICA | AB10: 0 | AC10: 27897801308568 | AD10: Validade indeterminada
B11: 30 | C11: TUBO PVC SOLDAVEL - 6M - 85MM | D11: TUBOS PVC SOLDAVEL | E11: AF | F11: BR | G11: Amarrados | H11: 10.85 | I11: 6000 | J11: 85 | K11: 85 | L11: =J11*I11*K11 -> 43350000 | M11: 7897801308588 | N11: 0.095 | O11: 6 | P11: 0.095 | Q11: 0.0852 | R11: 0.0852 | S11: 6 | T11: 1 | U11: 3917.23.00 | V11: 0 | W11: 17897801308585 | X11: NÃO APLICA | Y11: NÃO APLICA | Z11: NÃO APLICA | AB11: 0 | AC11: 27897801308582 | AD11: Validade indeterminada
B12: 31 | C12: TUBO PVC SOLDAVEL - 6M - 110MM | D12: TUBOS PVC SOLDAVEL | E12: AF | F12: BR | G12: Amarrados | H12: 18.25 | I12: 6000 | J12: 110 | K12: 110 | L12: =J12*I12*K12 -> 72600000 | M12: 7897801308595 | N12: 0.122 | O12: 6 | P12: 0.122 | Q12: 0.1102 | R12: 0.1102 | S12: 6 | T12: 1 | U12: 3917.23.00 | V12: 0 | W12: 17897801308592 | X12: NÃO APLICA | Y12: NÃO APLICA | Z12: NÃO APLICA | AB12: 0 | AC12: 27897801308599 | AD12: Validade indeterminada
B13: 32 | C13: TUBO PVC SOLDAVEL - 3M - 20MM | D13: TUBOS PVC SOLDAVEL | E13: AF | F13: BR | G13: Amarrados | H13: 0.42 | I13: 3000 | J13: 20 | K13: 20 | L13: =J13*I13*K13 -> 1200000 | M13: 7897801304306 | N13: 0.0202 | O13: 3 | P13: 0.0202 | Q13: 0.085 | R13: 0.085 | S13: 3 | T13: 12 | U13: 3917.23.00 | V13: 0 | W13: 17897801304303 | X13: NÃO APLICA | Y13: NÃO APLICA | Z13: NÃO APLICA | AB13: 0 | AC13: 27897801304300 | AD13: Validade indeterminada
B14: 33 | C14: TUBO PVC SOLDAVEL - 3M - 25MM | D14: TUBOS PVC SOLDAVEL | E14: AF | F14: BR | G14: Amarrados | H14: 0.579 | I14: 3000 | J14: 25 | K14: 25 | L14: =J14*I14*K14 -> 1875000 | M14: 7897801304313 | N14: 0.0252 | O14: 3 | P14: 0.0252 | Q14: 0.1 | R14: 0.09 | S14: 3 | T14: 8 | U14: 3917.23.00 | V14: 0 | W14: 17897801304310 | X14: NÃO APLICA | Y14: NÃO APLICA | Z14: NÃO APLICA | AB14: 0 | AC14: 27897801304317 | AD14: Validade indeterminada
B15: 34 | C15: TUBO PVC SOLDAVEL - 3M - 32MM | D15: TUBOS PVC SOLDAVEL | E15: AF | F15: BR | G15: Amarrados | H15: 0.925 | I15: 3000 | J15: 32 | K15: 32 | L15: =J15*I15*K15 -> 3072000 | M15: 7897801308991 | N15: 0.0322 | O15: 3 | P15: 0.0322 | Q15: 0.13 | R15: 0.09 | S15: 3 | T15: 10 | U15: 3917.23.00 | V15: 0 | W15: 17897801308998 | X15: NÃO APLICA | Y15: NÃO APLICA | Z15: NÃO APLICA | AB15: 0 | AC15: 27897801308995 | AD15: Validade indeterminada
... B22: 52 | C22: TUBO ULTRATERM 3M - 28MM | D22: CPVC - ULTRATERM - TUBOS | E22: AQ | F22: BR | G22: Amarrados | H22: 0.95 | I22: 3000 | J22: 28 | K22: 28 | L22: =J22*I22*K22 -> 2352000 | M22: 7897801320283 | N22: 0.028 | O22: 3 | P22: 0.028 | Q22: 0.028 | R22: 3 | S22: 0.028 | T22: 10 | U22: 3917.23.00 | V22: 0 | W22: 17897801320280 | X22: NÃO APLICA | Y22: NÃO APLICA | Z22: NÃO APLICA | AB22: 0 | AC22: 27897801320287 | AD22: Validade indeterminada
B23: 78 | C23: RALO QUADRADO OCULTO 10x10 cm KRONA | D23: CAIXAS E RALOS | E23: ESGOTO | F23: PC | G23: Blister | H23: 0.715 | I23: 125 | J23: 48 | K23: 125 | L23: 750000 | M23: 7898708518384 | N23: NÃO APLICA | O23: NÃO APLICA | P23: NÃO APLICA | Q23: 0.1 | R23: 0.024 | S23: 0.1 | T23: 1 | U23: 3917.40.90 | V23: 0 | W23: 17898708518381 | X23: 0.066 | Y23: 0.25 | Z23: 0.165 | AA23: 0.0027225 | AB23: 20 | AC23: 27898708518388 | AD23: Validade indeterminada
B24: 79 | C24: RALO QUADRADO OCULTO 15x15 cm KRONA | D24: CAIXAS E RALOS | E24: ESGOTO | F24: PC | G24: Blister | H24: 1.083 | I24: 195 | J24: 39 | K24: 195 | L24: 1482975 | M24: 7898708518391 | N24: NÃO APLICA | O24: NÃO APLICA | P24: NÃO APLICA | Q24: 0.152 | R24: 0.02 | S24: 0.152 | T24: 1 | U24: 3917.40.90 | V24: 0 | W24: 17898708518398 | X24: 0.045 | Y24: 0.222 | Z24: 0.223 | AA24: 0.00222777 | AB24: 45 | AC24: 27898708518395 | AD24: Validade indeterminada
B25: 80 | C25: RALO LINEAR PVC SECO 50CM OCULTO KRONA | D25: CAIXAS E RALOS | E25: ESGOTO | F25: PC | G25: Filme | H25: 0.696 | I25: 523 | J25: 25 | K25: 100 | L25: 1307500 | M25: 7898708518407 | N25: NÃO APLICA | O25: NÃO APLICA | P25: NÃO APLICA | Q25: 0.076 | R25: 0.012 | S25: 0.248 | T25: 1 | U25: 3917.40.90 | V25: 0 | W25: 17898708518404 | X25: 0.105 | Y25: 0.075 | Z25: 0.53 | AA25: 0.00417375 | AB25: 30 | AC25: 27898708518401 | AD25: Validade indeterminada
B26: 81 | C26: RALO LINEAR PVC SECO 50CM ACAB. POLIDO KRONA | D26: CAIXAS E RALOS | E26: ESGOTO | F26: PC | G26: Caixa | H26: 0.514 | I26: 523 | J26: 25 | K26: 100 | L26: 1307500 | M26: 7898708518414 | N26: NÃO APLICA | O26: NÃO APLICA | P26: NÃO APLICA | Q26: 0.076 | R26: 0.026 | S26: 0.248 | T26: 1 | U26: 3917.40.90 | V26: 0 | W26: 17898708518411 | X26: 0.105 | Y26: 0.075 | Z26: 0.53 | AA26: 0.00417375 | AB26: 24 | AC26: 27898708518418 | AD26: Validade indeterminada
B27: 82 | C27: RALO LINEAR PVC SIFONADO 50CM OCULTO KRONA | D27: CAIXAS E RALOS | E27: ESGOTO | F27: PC | G27: Filme | H27: 1.064 | I27: 523 | J27: 25 | K27: 100 | L27: 1307500 | M27: 7898708518421 | N27: NÃO APLICA | O27: NÃO APLICA | P27: NÃO APLICA | Q27: 0.076 | R27: 0.012 | S27: 0.248 | T27: 1 | U27: 3917.40.90 | V27: 0 | W27: 17898708518428 | X27: 0.105 | Y27: 0.075 | Z27: 0.53 | AA27: 0.00417375 | AB27: 30 | AC27: 27898708518425 | AD27: Validade indeterminada
B28: 83 | C28: RALO LINEAR PVC SIFONADO 50CM ACAB. POLIDO KRONA | D28: CAIXAS E RALOS | E28: ESGOTO | F28: PC | G28: Caixa | H28: 0.729 | I28: 523 | J28: 25 | K28: 100 | L28: 1307500 | M28: 7898708518438 | N28: NÃO APLICA | O28: NÃO APLICA | P28: NÃO APLICA | Q28: 0.076 | R28: 0.026 | S28: 0.248 | T28: 1 | U28: 3917.40.90 | V28: 0 | W28: 17898708518435 | X28: 0.105 | Y28: 0.075 | Z28: 0.53 | AA28: 0.00417375 | AB28: 24 | AC28: 27898708518432 | AD28: Validade indeterminada
B29: 84 | C29: RALO LINEAR PVC SECO 75CM SAIDA CENTRAL OCULTO KRONA | D29: CAIXAS E RALOS | E29: ESGOTO | F29: PC | G29: Filme | H29: 0.495 | I29: 773 | J29: 33 | K29: 100 | L29: 2550900 | M29: 7898708518445 | N29: NÃO APLICA | O29: NÃO APLICA | P29: NÃO APLICA | Q29: 0.076 | R29: 0.012 | S29: 0.248 | T29: 1 | U29: 3917.40.90 | V29: 0 | W29: 17898708518442 | X29: 0.105 | Y29: 0.075 | Z29: 0.775 | AA29: 0.006103125 | AB29: 20 | AC29: 27898708518449 | AD29: Validade indeterminada
B30: 85 | C30: RALO LINEAR PVC SECO 75CM SAIDA CENTRAL POLIDO KRONA | D30: CAIXAS E RALOS | E30: ESGOTO | F30: PC | G30: Caixa | H30: 0.197 | I30: 773 | J30: 33 | K30: 100 | L30: 2550900 | M30: 7898708518452 | N30: NÃO APLICA | O30: NÃO APLICA | P30: NÃO APLICA | Q30: 0.076 | R30: 0.026 | S30: 0.748 | T30: 1 | U30: 3917.40.90 | V30: 0 | W30: 17898708518459 | X30: 0.105 | Y30: 0.075 | Z30: 0.775 | AA30: 0.006103125 | AB30: 18 | AC30: 27898708518456 | AD30: Validade indeterminada
B31: 86 | C31: RALO LINEAR PVC SIFONADO 75CM SAIDA CENTRAL OCULTO KRONA | D31: CAIXAS E RALOS | E31: ESGOTO | F31: PC | G31: Filme | H31: 0.71 | I31: 773 | J31: 33 | K31: 100 | L31: 2550900 | M31: 7898708518469 | N31: NÃO APLICA | O31: NÃO APLICA | P31: NÃO APLICA | Q31: 0.076 | R31: 0.012 | S31: 0.248 | T31: 1 | U31: 3917.40.90 | V31: 0 | W31: 17898708518466 | X31: 0.105 | Y31: 0.075 | Z31: 0.775 | AA31: 0.006103125 | AB31: 20 | AC31: 27898708518463 | AD31: Validade indeterminada
B32: 87 | C32: RALO LINEAR PVC SIFONADO 75CM SAIDA CENTRAL POLIDO KRONA | D32: CAIXAS E RALOS | E32: ESGOTO | F32: PC | G32: Caixa | H32: 0.424 | I32: 773 | J32: 33 | K32: 100 | L32: 2550900 | M32: 7898708518476 | N32: NÃO APLICA | O32: NÃO APLICA | P32: NÃO APLICA | Q32: 0.076 | R32: 0.026 | S32: 0.748 | T32: 1 | U32: 3917.40.90 | V32: 0 | W32: 17898708518473 | X32: 0.105 | Y32: 0.075 | Z32: 0.775 | AA32: 0.006103125 | AB32: 18 | AC32: 27898708518470 | AD32: Validade indeterminada
B33: 88 | C33: SIFAO 50MM PARA RALOS KRONA | D33: CAIXAS E RALOS | E33: ESGOTO | F33: PC | G33: Blister | H33: 0.059 | I33: 50 | J33: 80 | K33: 50 | L33: 200000 | M33: 7898708518483 | N33: NÃO APLICA | O33: NÃO APLICA | P33: NÃO APLICA | Q33: 0.054 | R33: 0.185 | S33: 0.131 | T33: 1 | U33: 3917.40.90 | V33: 0 | W33: 17898708518480 | X33: 0.27 | Y33: 0.27 | Z33: 0.33 | AA33: 0.024057 | AB33: 20 | AC33: 27898708518487 | AD33: Validade indeterminada
B34: 89 | C34: BOLSA ACOPLAVEL CX SIFONADA 100MM PVC | D34: CAIXAS E RALOS | E34: ESGOTO | F34: PC | G34: Sacos | H34: 0.056 | I34: 95 | J34: 30 | K34: 95 | L34: 270750 | M34: 7898708518490 | N34: NÃO APLICA | O34: NÃO APLICA | P34: NÃO APLICA | Q34: 0.19 | R34: 0.03 | S34: 0.265 | T34: 1 | U34: 3917.40.90 | V34: 0 | W34: 17898708518497 | X34: 0.27 | Y34: 0.27 | Z34: 0.33 | AA34: 0.024057 | AB34: 20 | AC34: 27898708518494 | AD34: Validade indeterminada
B35: 90 | C35: BOLSA ACOPLAVEL CX SIFONADA 150MM PVC | D35: CAIXAS E RALOS | E35: ESGOTO | F35: PC | G35: Sacos | H35: 0.092 | I35: 143 | J35: 30 | K35: 143 | L35: 613470 | M35: 7898708518506 | N35: NÃO APLICA | O35: NÃO APLICA | P35: NÃO APLICA | Q35: 0.19 | R35: 0.03 | S35: 0.265 | T35: 1 | U35: 3917.40.90 | V35: 0 | W35: 17898708518503 | X35: 0.27 | Y35: 0.27 | Z35: 0.33 | AA35: 0.024057 | AB35: 20 | AC35: 27898708518500 | AD35: Validade indeterminada
B36: 100 | C36: TUBO PVC ESGOTO SEC. - 6M - DN 40 | D36: TUBOS PVC ESGOTO | E36: ESGOTO | F36: BR | G36: Amarrados | H36: 1.415 | I36: 6000 | J36: 40 | K36: 40 | L36: =J36*I36*K36 -> 9600000 | M36: 7897801304108 | N36: 0.0426 | O36: 6 | P36: 0.0426 | Q36: 0.17 | R36: 0.12 | S36: 6 | T36: 10 | U36: 3917.23.00 | V36: 0 | W36: 17897801304105 | X36: NÃO APLICA | Y36: NÃO APLICA | Z36: NÃO APLICA | AB36: 0 | AC36: 27897801304102 | AD36: Validade indeterminada
B37: 101 | C37: TUBO PVC ESGOTO PRIM. - 6M - DN 50 | D37: TUBOS PVC ESGOTO | E37: ESGOTO | F37: BR | G37: Amarrados | H37: 2.345 | I37: 6000 | J37: 50 | K37: 50 | L37: =J37*I37*K37 -> 15000000 | M37: 7897801304115 | N37: 0.062 | O37: 6 | P37: 0.062 | Q37: 0.24 | R37: 0.16 | S37: 6.002 | T37: 10 | U37: 3917.23.00 | V37: 0 | W37: 17897801304112 | X37: NÃO APLICA | Y37: NÃO APLICA | Z37: NÃO APLICA | AB37: 0 | AC37: 27897801304119 | AD37: Validade indeterminada
B38: 102 | C38: TUBO PVC ESGOTO PRIM. - 6M - DN 75 | D38: TUBOS PVC ESGOTO | E38: ESGOTO | F38: BR | G38: Amarrados | H38: 3.74 | I38: 6000 | J38: 75 | K38: 75 | L38: =J38*I38*K38 -> 33750000 | M38: 7897801304122 | N38: 0.0836 | O38: 6 | P38: 0.0836 | Q38: 0.25 | R38: 0.16 | S38: 6.002 | T38: 5 | U38: 3917.23.00 | V38: 0 | W38: 17897801304129 | X38: NÃO APLICA | Y38: NÃO APLICA | Z38: NÃO APLICA | AB38: 0 | AC38: 27897801304126 | AD38: Validade indeterminada
B39: 103 | C39: TUBO PVC ESGOTO PRIM. - 6M - DN 100 | D39: TUBOS PVC ESGOTO | E39: ESGOTO | F39: BR | G39: Amarrados | H39: 5.317 | I39: 6000 | J39: 101 | K39: 101 | L39: =J39*I39*K39 -> 61206000 | M39: 7897801304139 | N39: 0.1066 | O39: 6 | P39: 0.1066 | Q39: 0.335 | R39: 0.2 | S39: 6.002 | T39: 5 | U39: 3917.23.00 | V39: 0 | W39: 17897801304136 | X39: NÃO APLICA | Y39: NÃO APLICA | Z39: NÃO APLICA | AB39: 0 | AC39: 27897801304133 | AD39: Validade indeterminada
B40: 104 | C40: TUBO PVC ESGOTO PRIM. - 6M - DN 150 | D40: TUBOS PVC ESGOTO | E40: ESGOTO | F40: BR | G40: Amarrados | H40: 11.55 | I40: 6000 | J40: 150 | K40: 150 | L40: =J40*I40*K40 -> 135000000 | M40: 7897801304146 | N40: 0.155 | O40: 6 | P40: 0.155 | Q40: 0.1504 | R40: 0.1504 | S40: 6 | T40: 1 | U40: 3917.23.00 | V40: 0 | W40: 17897801304143 | X40: NÃO APLICA | Y40: NÃO APLICA | Z40: NÃO APLICA | AB40: 0 | AC40: 27897801304140 | AD40: Validade indeterminada
B41: 105 | C41: TUBO PVC ESGOTO PRIM. - 6M - DN 200 | D41: TUBOS PVC ESGOTO | E41: ESGOTO | F41: BR | G41: Amarrados | H41: 20.44 | I41: 6000 | J41: 200 | K41: 200 | L41: =J41*I41*K41 -> 240000000 | M41: 7897801308557 | N41: 0.208 | O41: 6 | P41: 0.208 | Q41: 0.2004 | R41: 0.2004 | S41: 6 | T41: 1 | U41: 3917.23.00 | V41: 0 | W41: 17897801308554 | X41: NÃO APLICA | Y41: NÃO APLICA | Z41: NÃO APLICA | AB41: 0 | AC41: 27897801308551 | AD41: Validade indeterminada
B42: 106 | C42: TUBO PVC LEVE - 6M - DN 250 | D42: TUBOS PVC ESGOTO | E42: ESGOTO | F42: BR | G42: Amarrados | H42: 20.77 | I42: 6000 | J42: 250 | K42: 250 | L42: =J42*I42*K42 -> 375000000 | M42: 7897801308571 | N42: 0.256 | O42: 6 | P42: 0.256 | Q42: 0.2504 | R42: 0.2504 | S42: 6 | T42: 1 | U42: 3917.23.00 | V42: 0 | W42: 17897801308578 | X42: NÃO APLICA | Y42: NÃO APLICA | Z42: NÃO APLICA | AB42: 0 | AC42: 27897801308575 | AD42: Validade indeterminada
B43: 110 | C43: TUBO PVC ESGOTO SEC. - 3M- DN 40 | D43: TUBOS PVC ESGOTO | E43: ESGOTO | F43: BR | G43: Amarrados | H43: 0.7055 | I43: 3000 | J43: 40 | K43: 40 | L43: =J43*I43*K43 -> 4800000 | M43: 7897801308625 | N43: 0.0402 | O43: 3 | P43: 0.0402 | Q43: 0.17 | R43: 0.12 | S43: 3 | T43: 10 | U43: 3917.23.00 | V43: 0 | W43: 17897801308622 | X43: NÃO APLICA | Y43: NÃO APLICA | Z43: NÃO APLICA | AB43: 0 | AC43: 27897801308629 | AD43: Validade indeterminada
B44: 111 | C44: TUBO PVC ESGOTO PRIM. - 3M- DN 50 | D44: TUBOS PVC ESGOTO | E44: ESGOTO | F44: BR | G44: Amarrados | H44: 1.185 | I44: 3000 | J44: 50 | K44: 50 | L44: =J44*I44*K44 -> 7500000 | M44: 7897801308632 | N44: 0.051 | O44: 3 | P44: 0.051 | Q44: 0.205 | R44: 0.14 | S44: 3.002 | T44: 10 | U44: 3917.23.00 | V44: 0 | W44: 17897801308639 | X44: NÃO APLICA | Y44: NÃO APLICA | Z44: NÃO APLICA | AB44: 0 | AC44: 27897801308636 | AD44: Validade indeterminada
B45: 112 | C45: TUBO PVC ESGOTO PRIM. - 3M- DN 75 | D45: TUBOS PVC ESGOTO | E45: ESGOTO | F45: BR | G45: Amarrados | H45: 1.855 | I45: 3000 | J45: 75 | K45: 75 | L45: =J45*I45*K45 -> 16875000 | M45: 7897801308649 | N45: 0.0759 | O45: 3 | P45: 0.0759 | Q45: 0.27 | R45: 0.16 | S45: 3.002 | T45: 5 | U45: 3917.23.00 | V45: 0 | W45: 17897801308646 | X45: NÃO APLICA | Y45: NÃO APLICA | Z45: NÃO APLICA | AB45: 0 | AC45: 27897801308643 | AD45: Validade indeterminada
B46: 113 | C46: TUBO PVC ESGOTO PRIM. - 3M- DN 100 | D46: TUBOS PVC ESGOTO | E46: ESGOTO | F46: BR | G46: Amarrados | H46: 2.658 | I46: 3000 | J46: 100 | K46: 100 | L46: =J46*I46*K46 -> 30000000 | M46: 7897801308656 | N46: 0.102 | O46: 3 | P46: 0.102 | Q46: 0.335 | R46: 0.2 | S46: 3.002 | T46: 5 | U46: 3917.23.00 | V46: 0 | W46: 17897801308653 | X46: NÃO APLICA | Y46: NÃO APLICA | Z46: NÃO APLICA | AB46: 0 | AC46: 27897801308650 | AD46: Validade indeterminada
B47: 114 | C47: TUBO PVC ESGOTO PRIM. - 3M- DN 150 | D47: TUBOS PVC ESGOTO | E47: ESGOTO | F47: BR | G47: Amarrados | H47: 5.82 | I47: 3000 | J47: 150 | K47: 150 | L47: =J47*I47*K47 -> 67500000 | M47: 7897801308663 | N47: 0.1504 | O47: 3.001 | P47: 0.1504 | Q47: 0.1504 | R47: 0.1504 | S47: 3.001 | T47: 1 | U47: 3917.23.00 | V47: 0 | W47: 17897801308660 | X47: NÃO APLICA | Y47: NÃO APLICA | Z47: NÃO APLICA | AB47: 0 | AC47: 27897801308667 | AD47: Validade indeterminada
... B78: 164 | C78: TUBO PPR PN25 110MMX3M | D78: TUBOS PPR | E78: AQ | F78: BR | G78: Amarrados | H78: 14.79 | I78: 2980 | J78: 110 | K78: 110 | L78: =J78*I78*K78 -> 36058000 | M78: 7897801314282 | N78: 0.115 | O78: 2.98 | P78: 0.115 | Q78: 0.115 | R78: 2.98 | S78: 0.115 | T78: 1 | U78: 3917.22.90 | V78: 0 | W78: 17897801314289 | X78: NÃO APLICA | Y78: NÃO APLICA | Z78: NÃO APLICA | AB78: 0 | AC78: 27897801314286 | AD78: Validade indeterminada
B79: 200 | C79: ADAPTADOR ROSC. P/CX.DAGUA 1/2 | D79: ADAP.P/CX.D AGUA ROSC. | E79: AF | F79: PC | G79: Sacos | H79: 0.0782 | I79: 70 | J79: 60 | K79: 70 | L79: =J79*I79*K79 -> 294000 | M79: 7897801312806 | N79: NÃO APLICA | O79: NÃO APLICA | P79: NÃO APLICA | Q79: 0.14 | R79: 0.07 | S79: 0.25 | T79: 10 | U79: 3917.40.90 | V79: 0 | W79: 17897801312803 | X79: 0.48 | Y79: 0.2 | Z79: 0.73 | AA79: =Y79*X79*Z79 -> 0.07008 | AB79: 300 | AC79: 27897801312800 | AD79: Validade indeterminada
B80: 201 | C80: ADAPTADOR ROSC. P/CX.DAGUA 3/4 | D80: ADAP.P/CX.D AGUA ROSC. | E80: AF | F80: PC | G80: Sacos | H80: 0.0972 | I80: 60 | J80: 60 | K80: 70 | L80: =J80*I80*K80 -> 252000 | M80: 7897801312820 | N80: NÃO APLICA | O80: NÃO APLICA | P80: NÃO APLICA | Q80: 0.17 | R80: 0.07 | S80: 0.26 | T80: 10 | U80: 3917.40.90 | V80: 0 | W80: 17897801312827 | X80: 0.49 | Y80: 0.17 | Z80: 0.65 | AA80: =Y80*X80*Z80 -> 0.054145 | AB80: 200 | AC80: 27897801312824 | AD80: Validade indeterminada
B81: 202 | C81: ADAPTADOR ROSC. P/CX.DAGUA 1 | D81: ADAP.P/CX.D AGUA ROSC. | E81: AF | F81: PC | G81: Sacos | H81: 0.1344 | I81: 70 | J81: 70 | K81: 80 | L81: =J81*I81*K81 -> 392000 | M81: 7897801312851 | N81: NÃO APLICA | O81: NÃO APLICA | P81: NÃO APLICA | Q81: 0.2 | R81: 0.7 | S81: 0.3 | T81: 10 | U81: 3917.40.90 | V81: 0 | W81: 17897801312858 | X81: 0.45 | Y81: 0.23 | Z81: 0.6 | AA81: =Y81*X81*Z81 -> 0.0621 | AB81: 120 | AC81: 27897801312855 | AD81: Validade indeterminada
B82: 203 | C82: ADAPTADOR ROSC. P/CX.DAGUA 1.1/4 | D82: ADAP.P/CX.D AGUA ROSC. | E82: AF | F82: PC | G82: Sacos | H82: 0.1562 | I82: 70 | J82: 70 | K82: 90 | L82: =J82*I82*K82 -> 441000 | M82: 7897801312844 | N82: NÃO APLICA | O82: NÃO APLICA | P82: NÃO APLICA | Q82: 0.185 | R82: 0.09 | S82: 0.25 | T82: 5 | U82: 3917.40.90 | V82: 0 | W82: 17897801312841 | X82: 0.49 | Y82: 0.22 | Z82: 0.7 | AA82: =Y82*X82*Z82 -> 0.07546 | AB82: 125 | AC82: 27897801312848 | AD82: Validade indeterminada
B83: 204 | C83: ADAPTADOR ROSC. P/CX.DAGUA 1.1/2 | D83: ADAP.P/CX.D AGUA ROSC. | E83: AF | F83: PC | G83: Sacos | H83: 0.1941 | I83: 80 | J83: 90 | K83: 80 | L83: =J83*I83*K83 -> 576000 | M83: 7897801312837 | N83: NÃO APLICA | O83: NÃO APLICA | P83: NÃO APLICA | Q83: 0.18 | R83: 0.07 | S83: 0.21 | T83: 5 | U83: 3917.40.90 | V83: 0 | W83: 17897801312834 | X83: 0.5 | Y83: 0.21 | Z83: 0.65 | AA83: =Y83*X83*Z83 -> 0.06825 | AB83: 100 | AC83: 27897801312831 | AD83: Validade indeterminada
B84: 205 | C84: ADAPTADOR ROSC. P/CX.DAGUA 2 | D84: ADAP.P/CX.D AGUA ROSC. | E84: AF | F84: PC | G84: Sacos | H84: 0.2541 | I84: 100 | J84: 90 | K84: 10 | L84: =J84*I84*K84 -> 90000 | M84: 7897801312868 | N84: NÃO APLICA | O84: NÃO APLICA | P84: NÃO APLICA | Q84: 0.225 | R84: 0.085 | S84: 0.275 | T84: 5 | U84: 3917.40.90 | V84: 0 | W84: 17897801312865 | X84: 0.42 | Y84: 0.22 | Z84: 0.64 | AA84: =Y84*X84*Z84 -> 0.059136 | AB84: 60 | AC84: 27897801312862 | AD84: Validade indeterminada
B85: 208 | C85: BUCHA RED.ROSC. 3/4 X 1/2 | D85: CONEXOES ROSCAVEIS | E85: AF | F85: PC | G85: Sacos | H85: 0.01 | I85: 30 | J85: 30 | K85: 27 | L85: =J85*I85*K85 -> 24300 | M85: 7897801302128 | N85: NÃO APLICA | O85: NÃO APLICA | P85: NÃO APLICA | Q85: 0.23 | R85: 0.04 | S85: 0.24 | T85: 50 | U85: 3917.40.90 | V85: 0 | W85: 17897801302125 | X85: 0.42 | Y85: 0.22 | Z85: 0.67 | AA85: =Y85*X85*Z85 -> 0.061908 | AB85: 2000 | AC85: 47897801302126 | AD85: Validade indeterminada
B86: 209 | C86: BUCHA RED.ROSC. 1 X 1/2 | D86: CONEXOES ROSCAVEIS | E86: AF | F86: PC | G86: Sacos | H86: 0.0223 | I86: 30 | J86: 30 | K86: 40 | L86: =J86*I86*K86 -> 36000 | M86: 7897801312189 | N86: NÃO APLICA | O86: NÃO APLICA | P86: NÃO APLICA | Q86: 0.19 | R86: 0.04 | S86: 0.235 | T86: 16 | U86: 3917.40.90 | V86: 0 | W86: 17897801312186 | X86: 0.53 | Y86: 0.21 | Z86: 0.79 | AA86: =Y86*X86*Z86 -> 0.087927 | AB86: 960 | AC86: 27897801312183 | AD86: Validade indeterminada
B87: 210 | C87: BUCHA RED.ROSC. 1 X 3/4 | D87: CONEXOES ROSCAVEIS | E87: AF | F87: PC | G87: Sacos | H87: 0.0162 | I87: 36 | J87: 30 | K87: 36 | L87: =J87*I87*K87 -> 38880 | M87: 7897801307673 | N87: NÃO APLICA | O87: NÃO APLICA | P87: NÃO APLICA | Q87: 0.16 | R87: 0.035 | S87: 0.2 | T87: 24 | U87: 3917.40.90 | V87: 0 | W87: 17897801307670 | X87: 0.5 | Y87: 0.18 | Z87: 0.7 | AA87: =Y87*X87*Z87 -> 0.063 | AB87: 1320 | AC87: 47897801307671 | AD87: Validade indeterminada
B88: 211 | C88: BUCHA RED.ROSC. 1.1/4 X 1 | D88: CONEXOES ROSCAVEIS | E88: AF | F88: PC | G88: Sacos | H88: 0.0258 | I88: 30 | J88: 50 | K88: 40 | L88: =J88*I88*K88 -> 60000 | M88: 7897801312196 | N88: NÃO APLICA | O88: NÃO APLICA | P88: NÃO APLICA | Q88: 0.15 | R88: 0.06 | S88: 0.2 | T88: 16 | U88: 3917.40.90 | V88: 0 | W88: 17897801312193 | X88: 0.56 | Y88: 0.215 | Z88: 0.65 | AA88: =Y88*X88*Z88 -> 0.07826 | AB88: 720 | AC88: 27897801312190 | AD88: Validade indeterminada
B89: 212 | C89: BUCHA RED.ROSC. 1.1/4 X 3/4 | D89: CONEXOES ROSCAVEIS | E89: AF | F89: PC | G89: Sacos | H89: 0.0308 | I89: 30 | J89: 30 | K89: 40 | L89: =J89*I89*K89 -> 36000 | M89: 7897801312202 | N89: NÃO APLICA | O89: NÃO APLICA | P89: NÃO APLICA | Q89: 0.15 | R89: 0.05 | S89: 0.2 | T89: 16 | U89: 3917.40.90 | V89: 0 | W89: 17897801312209 | X89: 0.45 | Y89: 0.2 | Z89: 0.65 | AA89: =Y89*X89*Z89 -> 0.0585 | AB89: 720 | AC89: 27897801312206 | AD89: Validade indeterminada
B90: 213 | C90: BUCHA RED.ROSC. 1.1/2 X 1/2 | D90: CONEXOES ROSCAVEIS | E90: AF | F90: PC | G90: Sacos | H90: 0.0407 | I90: 50 | J90: 30 | K90: 50 | L90: =J90*I90*K90 -> 75000 | M90: 7897801311533 | N90: NÃO APLICA | O90: NÃO APLICA | P90: NÃO APLICA | Q90: 0.15 | R90: 0.07 | S90: 0.18 | T90: 16 | U90: 3917.40.90 | V90: 0 | W90: 17897801311530 | X90: 0.45 | Y90: 0.2 | Z90: 0.7 | AA90: =Y90*X90*Z90 -> 0.063 | AB90: 480 | AC90: 27897801311537 | AD90: Validade indeterminada
... B99: 223 | C99: CAP ROSCAVEL 1.1/2 | D99: CONEXOES ROSCAVEIS | E99: AF | F99: PC | G99: Sacos | H99: 0.0641 | I99: 60 | J99: 40 | K99: 60 | L99: =J99*I99*K99 -> 144000 | M99: 7897801311434 | N99: NÃO APLICA | O99: NÃO APLICA | P99: NÃO APLICA | Q99: 0.185 | R99: 0.063 | S99: 0.215 | T99: 10 | U99: 3917.40.90 | V99: 0 | W99: 17897801311431 | X99: 0.52 | Y99: 0.2 | Z99: 0.8 | AA99: =Y99*X99*Z99 -> 0.0832 | AB99: 350 | AC99: 27897801311438 | AD99: Validade indeterminada
B100: 224 | C100: CAP ROSCAVEL 1.1/4 | D100: CONEXOES ROSCAVEIS | E100: AF | F100: PC | G100: Sacos | H100: 0.0383 | I100: 16 | J100: 15 | K100: 4 | L100: =J100*I100*K100 -> 960 | M100: 7897801319423 | N100: 0.16 | O100: 0.66 | P100: 0.47 | Q100: 0.15 | R100: 0.04 | S100: 0.16 | T100: 10 | U100: 3917.40.90 | V100: 0 | W100: 17897801319420 | X100: 0.47 | Y100: 0.16 | Z100: 0.16 | AA100: =Y100*X100*Z100 -> 0.012032 | AB100: 500 | AC100: 27897801319427 | AD100: Validade indeterminada
B101: 225 | C101: CAP ROSCAVEL 2 | D101: CONEXOES ROSCAVEIS | E101: AF | F101: PC | G101: Sacos | H101: 0.07 | I101: 71 | J101: 17 | K101: 50 | L101: =J101*I101*K101 -> 60350 | M101: 7897801319430 | N101: NÃO APLICA | O101: NÃO APLICA | P101: NÃO APLICA | Q101: 0.155 | R101: 0.05 | S101: 0.19 | T101: 5 | U101: 3917.40.90 | V101: 0 | W101: 17897801319437 | X101: 0.49 | Y101: 0.22 | Z101: 0.71 | AA101: =Y101*X101*Z101 -> 0.076538 | AB101: 250 | AC101: 27897801319434 | AD101: Validade indeterminada
B102: 226 | C102: CURVA ROSC 1/2 | D102: CONEXOES ROSCAVEIS | E102: AF | F102: PC | G102: Sacos | H102: 0.019 | I102: 60 | J102: 20 | K102: 60 | L102: =J102*I102*K102 -> 72000 | M102: 7897801312721 | N102: NÃO APLICA | O102: NÃO APLICA | P102: NÃO APLICA | Q102: 0.15 | R102: 0.05 | S102: 0.2 | T102: 24 | U102: 3917.40.90 | V102: 0 | W102: 17897801312728 | X102: 0.5 | Y102: 0.2 | Z102: 0.65 | AA102: =Y102*X102*Z102 -> 0.065 | AB102: 960 | AC102: 27897801312725 | AD102: Validade indeterminada
B103: 227 | C103: CURVA ROSC 3/4 | D103: CONEXOES ROSCAVEIS | E103: AF | F103: PC | G103: Sacos | H103: 0.031 | I103: 130 | J103: 20 | K103: 80 | L103: =J103*I103*K103 -> 208000 | M103: 7897801312738 | N103: NÃO APLICA | O103: NÃO APLICA | P103: NÃO APLICA | Q103: 0.23 | R103: 0.07 | S103: 0.3 | T103: 24 | U103: 3917.40.90 | V103: 0 | W103: 17897801312735 | X103: 0.5 | Y103: 0.25 | Z103: 0.7 | AA103: =Y103*X103*Z103 -> 0.0875 | AB103: 480 | AC103: 27897801312732 | AD103: Validade indeterminada
B104: 228 | C104: CURVA ROSC 1.1/4 | D104: CONEXOES ROSCAVEIS | E104: AF | F104: PC | G104: Sacos | H104: 0.0947 | I104: 150 | J104: 40 | K104: 40 | L104: =J104*I104*K104 -> 240000 | M104: 7897801312639 | N104: NÃO APLICA | O104: NÃO APLICA | P104: NÃO APLICA | Q104: 0.18 | R104: 0.09 | S104: 0.26 | T104: 8 | U104: 3917.40.90 | V104: 0 | W104: 17897801312636 | X104: 0.45 | Y104: 0.25 | Z104: 0.65 | AA104: =Y104*X104*Z104 -> 0.073125 | AB104: 160 | AC104: 27897801312633 | AD104: Validade indeterminada
B105: 229 | C105: CURVA ROSC 1.1/2 | D105: CONEXOES ROSCAVEIS | E105: AF | F105: PC | G105: Sacos | H105: 0.151 | I105: 30 | J105: 30 | K105: 40 | L105: =J105*I105*K105 -> 36000 | M105: 7897801312646 | N105: NÃO APLICA | O105: NÃO APLICA | P105: NÃO APLICA | Q105: 0.25 | R105: 0.1 | S105: 0.385 | T105: 10 | U105: 3917.40.90 | V105: 0 | W105: 17897801312643 | X105: 0.59 | Y105: 0.2 | Z105: 0.86 | AA105: =Y105*X105*Z105 -> 0.10148 | AB105: 100 | AC105: 27897801312640 | AD105: Validade indeterminada
B106: 230 | C106: CURVA ROSC 1 | D106: CONEXOES ROSCAVEIS | E106: AF | F106: PC | G106: Sacos | H106: 0.0588 | I106: 10 | J106: 30 | K106: 30 | L106: =J106*I106*K106 -> 9000 | M106: 7897801312745 | N106: NÃO APLICA | O106: NÃO APLICA | P106: NÃO APLICA | Q106: 0.2 | R106: 0.055 | S106: 0.25 | T106: 12 | U106: 3917.40.90 | V106: 0 | W106: 17897801312742 | X106: 0.45 | Y106: 0.2 | Z106: 0.68 | AA106: =Y106*X106*Z106 -> 0.0612 | AB106: 240 | AC106: 27897801312749 | AD106: Validade indeterminada
B107: 250 | C107: JOELHO 45 1/2 | D107: CONEXOES ROSCAVEIS | E107: AF | F107: PC | G107: Sacos | H107: 0.0265 | I107: 50 | J107: 35 | K107: 30 | L107: =J107*I107*K107 -> 52500 | M107: 7897801311656 | N107: NÃO APLICA | O107: NÃO APLICA | P107: NÃO APLICA | Q107: 0.16 | R107: 0.031 | S107: 0.195 | T107: 15 | U107: 3917.40.90 | V107: 0 | W107: 17897801311653 | X107: 0.54 | Y107: 0.175 | Z107: 0.79 | AA107: =Y107*X107*Z107 -> 0.074655 | AB107: 825 | AC107: 27897801311650 | AD107: Validade indeterminada
B108: 251 | C108: JOELHO 45 3/4 | D108: CONEXOES ROSCAVEIS | E108: AF | F108: PC | G108: Sacos | H108: 0.037 | I108: 65 | J108: 45 | K108: 35 | L108: =J108*I108*K108 -> 102375 | M108: 7897801311496 | N108: NÃO APLICA | O108: NÃO APLICA | P108: NÃO APLICA | Q108: 0.24 | R108: 0.05 | S108: 0.24 | T108: 15 | U108: 3917.40.90 | V108: 0 | W108: 17897801311493 | X108: 0.56 | Y108: 0.21 | Z108: 0.81 | AA108: =Y108*X108*Z108 -> 0.095256 | AB108: 600 | AC108: 27897801311490 | AD108: Validade indeterminada
B109: 252 | C109: JOELHO 45 1 | D109: CONEXOES ROSCAVEIS | E109: AF | F109: PC | G109: Sacos | H109: 0.0387 | I109: 78 | J109: 50 | K109: 44 | L109: =J109*I109*K109 -> 171600 | M109: 7897801312240 | N109: NÃO APLICA | O109: NÃO APLICA | P109: NÃO APLICA | Q109: 0.14 | R109: 0.08 | S109: 0.18 | T109: 8 | U109: 3917.40.90 | V109: 0 | W109: 17897801312247 | X109: 0.45 | Y109: 0.18 | Z109: 0.65 | AA109: =Y109*X109*Z109 -> 0.05265 | AB109: 336 | AC109: 27897801312244 | AD109: Validade indeterminada
B110: 254 | C110: JOELHO 45 1.1/2 | D110: CONEXOES ROSCAVEIS | E110: AF | F110: PC | G110: Sacos | H110: 0.114 | I110: 90 | J110: 60 | K110: 60 | L110: =J110*I110*K110 -> 324000 | M110: 7897801312257 | N110: NÃO APLICA | O110: NÃO APLICA | P110: NÃO APLICA | Q110: 0.2 | R110: 0.08 | S110: 0.26 | T110: 8 | U110: 3917.40.90 | V110: 0 | W110: 17897801312254 | X110: 0.45 | Y110: 0.24 | Z110: 0.65 | AA110: =Y110*X110*Z110 -> 0.0702 | AB110: 192 | AC110: 27897801312251 | AD110: Validade indeterminada
B111: 256 | C111: JOELHO 90 ROSC 1/2 | D111: CONEXOES ROSCAVEIS | E111: AF | F111: PC | G111: Sacos | H111: 0.0267 | I111: 43 | J111: 30 | K111: 43 | L111: =J111*I111*K111 -> 55470 | M111: 7897801302418 | N111: NÃO APLICA | O111: NÃO APLICA | P111: NÃO APLICA | Q111: 0.21 | R111: 0.05 | S111: 0.25 | T111: 20 | U111: 3917.40.90 | V111: 0 | W111: 17897801302415 | X111: 0.55 | Y111: 0.21 | Z111: 0.74 | AA111: =Y111*X111*Z111 -> 0.08547 | AB111: 800 | AC111: 47897801302416 | AD111: Validade indeterminada
B112: 257 | C112: JOELHO 90 ROSC 3/4 | D112: CONEXOES ROSCAVEIS | E112: AF | F112: PC | G112: Sacos | H112: 0.0385 | I112: 48 | J112: 36 | K112: 48 | L112: =J112*I112*K112 -> 82944 | M112: 7897801301404 | N112: NÃO APLICA | O112: NÃO APLICA | P112: NÃO APLICA | Q112: 0.22 | R112: 0.06 | S112: 0.24 | T112: 20 | U112: 3917.40.90 | V112: 0 | W112: 17897801301401 | X112: 0.52 | Y112: 0.18 | Z112: 0.78 | AA112: =Y112*X112*Z112 -> 0.073008 | AB112: 560 | AC112: 47897801301402 | AD112: Validade indeterminada
... B130: 290 | C130: NIPEL ROSCAVEL 1.1/2 | D130: CONEXOES ROSCAVEIS | E130: AF | F130: PC | G130: Sacos | H130: 0.0636 | I130: 80 | J130: 56 | K130: 56 | L130: =J130*I130*K130 -> 250880 | M130: 7897801308601 | N130: NÃO APLICA | O130: NÃO APLICA | P130: NÃO APLICA | Q130: 0.22 | R130: 0.052 | S130: 0.2 | T130: 10 | U130: 3917.40.90 | V130: 0 | W130: 17897801308608 | X130: 0.6 | Y130: 0.19 | Z130: 0.83 | AA130: =Y130*X130*Z130 -> 0.09462 | AB130: 350 | AC130: 47897801308609 | AD130: Validade indeterminada
B131: 291 | C131: NIPEL ROSCAVEL 1.1/4 | D131: CONEXOES ROSCAVEIS | E131: AF | F131: PC | G131: Sacos | H131: 0.0409 | I131: 76 | J131: 21 | K131: 48 | L131: =J131*I131*K131 -> 76608 | M131: 7897801319447 | N131: 0.76 | O131: 0.76 | P131: 0.48 | Q131: 0.05 | R131: 0.16 | S131: 0.19 | T131: 10 | U131: 3917.40.90 | V131: 0 | W131: 17897801319444 | X131: 0.19 | Y131: 0.49 | Z131: 0.7 | AA131: =Y131*X131*Z131 -> 0.06517 | AB131: 420 | AC131: 27897801319441 | AD131: Validade indeterminada
B132: 292 | C132: NIPEL ROSCAVEL 2 | D132: CONEXOES ROSCAVEIS | E132: AF | F132: PC | G132: Sacos | H132: 0.0839 | I132: 60 | J132: 30 | K132: 200 | L132: =J132*I132*K132 -> 360000 | M132: 7897801319454 | N132: 0.21 | O132: 0.69 | P132: 0.48 | Q132: 0.2 | R132: 0.06 | S132: 0.25 | T132: 10 | U132: 3917.40.90 | V132: 0 | W132: 17897801319451 | X132: 0.48 | Y132: 0.21 | Z132: 0.69 | AA132: =Y132*X132*Z132 -> 0.069552 | AB132: 200 | AC132: 27897801319458 | AD132: Validade indeterminada
B133: 293 | C133: PLUG ROSCAVEL 1/2 | D133: CONEXOES ROSCAVEIS | E133: AF | F133: PC | G133: Sacos | H133: 0.0055 | I133: 23.5 | J133: 23.5 | K133: 21.5 | L133: =J133*I133*K133 -> 11873.375 | M133: 7897801301473 | N133: NÃO APLICA | O133: NÃO APLICA | P133: NÃO APLICA | Q133: 0.255 | R133: 0.025 | S133: 0.225 | T133: 50 | U133: 3917.40.90 | V133: 0 | W133: 17897801301470 | X133: 0.52 | Y133: 0.17 | Z133: 0.77 | AA133: =Y133*X133*Z133 -> 0.068068 | AB133: 3750 | AC133: 47897801301471 | AD133: Validade indeterminada
B134: 294 | C134: PLUG ROSCAVEL 3/4 | D134: CONEXOES ROSCAVEIS | E134: AF | F134: PC | G134: Sacos | H134: 0.0092 | I134: 26.9 | J134: 26.9 | K134: 27 | L134: =J134*I134*K134 -> 19537.47 | M134: 7897801302111 | N134: NÃO APLICA | O134: NÃO APLICA | P134: NÃO APLICA | Q134: 0.16 | R134: 0.04 | S134: 0.2 | T134: 50 | U134: 3917.40.90 | V134: 0 | W134: 17897801302118 | X134: 0.45 | Y134: 0.18 | Z134: 0.65 | AA134: =Y134*X134*Z134 -> 0.05265 | AB134: 2200 | AC134: 47897801302119 | AD134: Validade indeterminada
B135: 295 | C135: PLUG ROSCAVEL 1 | D135: CONEXOES ROSCAVEIS | E135: AF | F135: PC | G135: Sacos | H135: 0.0161 | I135: 34 | J135: 34 | K135: 34 | L135: =J135*I135*K135 -> 39304 | M135: 7897801308694 | N135: NÃO APLICA | O135: NÃO APLICA | P135: NÃO APLICA | Q135: 0.25 | R135: 0.055 | S135: 0.26 | T135: 50 | U135: 3917.40.90 | V135: 0 | W135: 17897801308691 | X135: 0.5 | Y135: 0.19 | Z135: 0.81 | AA135: =Y135*X135*Z135 -> 0.07695 | AB135: 1400 | AC135: 47897801308692 | AD135: Validade indeterminada
B136: 296 | C136: PLUG ROSCAVEL 1.1/2 | D136: CONEXOES ROSCAVEIS | E136: AF | F136: PC | G136: Sacos | H136: 0.0521 | I136: 51 | J136: 45 | K136: 51 | L136: =J136*I136*K136 -> 117045 | M136: 7897801311465 | N136: NÃO APLICA | O136: NÃO APLICA | P136: NÃO APLICA | Q136: 0.235 | R136: 0.06 | S136: 0.26 | T136: 20 | U136: 3917.40.90 | V136: 0 | W136: 17897801311462 | X136: 0.49 | Y136: 0.18 | Z136: 0.79 | AA136: =Y136*X136*Z136 -> 0.069678 | AB136: 400 | AC136: 27897801311469 | AD136: Validade indeterminada
B137: 297 | C137: PLUG ROSCAVEL 1.1/4 | D137: CONEXOES ROSCAVEIS | E137: AF | F137: PC | G137: Sacos | H137: 0.0308 | I137: 40 | J137: 40 | K137: 40 | L137: =J137*I137*K137 -> 64000 | M137: 7897801312288 | N137: NÃO APLICA | O137: NÃO APLICA | P137: NÃO APLICA | Q137: 0.21 | R137: 0.05 | S137: 0.235 | T137: 20 | U137: 3917.40.90 | V137: 0 | W137: 17897801312285 | X137: 0.49 | Y137: 0.21 | Z137: 0.79 | AA137: =Y137*X137*Z137 -> 0.081291 | AB137: 700 | AC137: 27897801312282 | AD137: Validade indeterminada
B138: 298 | C138: PLUG ROSCAVEL 2 | D138: CONEXOES ROSCAVEIS | E138: AF | F138: PC | G138: Sacos | H138: 0.0612 | I138: 60 | J138: 60 | K138: 50 | L138: =J138*I138*K138 -> 180000 | M138: 7897801312295 | N138: NÃO APLICA | O138: NÃO APLICA | P138: NÃO APLICA | Q138: 0.12 | R138: 0.05 | S138: 0.17 | T138: 5 | U138: 3917.40.90 | V138: 0 | W138: 17897801312292 | X138: 0.5 | Y138: 0.17 | Z138: 0.65 | AA138: =Y138*X138*Z138 -> 0.05525 | AB138: 250 | AC138: 27897801312299 | AD138: Validade indeterminada
B139: 299 | C139: TE ROSCAVEL 1/2 | D139: CONEXOES ROSCAVEIS | E139: AF | F139: PC | G139: Sacos | H139: 0.0364 | I139: 56 | J139: 30 | K139: 43 | L139: =J139*I139*K139 -> 72240 | M139: 7897801302517 | N139: NÃO APLICA | O139: NÃO APLICA | P139: NÃO APLICA | Q139: 0.25 | R139: 0.05 | S139: 0.25 | T139: 20 | U139: 3917.40.90 | V139: 0 | W139: 17897801302514 | X139: 0.52 | Y139: 0.22 | Z139: 0.76 | AA139: =Y139*X139*Z139 -> 0.086944 | AB139: 640 | AC139: 47897801302515 | AD139: Validade indeterminada
B140: 300 | C140: TE ROSCAVEL 3/4 | D140: CONEXOES ROSCAVEIS | E140: AF | F140: PC | G140: Sacos | H140: 0.0512 | I140: 60 | J140: 36 | K140: 48 | L140: =J140*I140*K140 -> 103680 | M140: 7897801301350 | N140: NÃO APLICA | O140: NÃO APLICA | P140: NÃO APLICA | Q140: 0.23 | R140: 0.07 | S140: 0.27 | T140: 20 | U140: 3917.40.90 | V140: 0 | W140: 17897801301357 | X140: 0.51 | Y140: 0.19 | Z140: 0.79 | AA140: =Y140*X140*Z140 -> 0.076551 | AB140: 400 | AC140: 27897801301354 | AD140: Validade indeterminada
B141: 301 | C141: TE ROSCAVEL 1 | D141: CONEXOES ROSCAVEIS | E141: AF | F141: PC | G141: Sacos | H141: 0.0916 | I141: 61 | J141: 78 | K141: 78 | L141: =J141*I141*K141 -> 371124 | M141: 7897801308953 | N141: NÃO APLICA | O141: NÃO APLICA | P141: NÃO APLICA | Q141: 0.2 | R141: 0.08 | S141: 0.3 | T141: 16 | U141: 3917.40.90 | V141: 0 | W141: 17897801308950 | X141: 0.42 | Y141: 0.23 | Z141: 0.6 | AA141: =Y141*X141*Z141 -> 0.05796 | AB141: 224 | AC141: 27897801308957 | AD141: Validade indeterminada
B142: 302 | C142: TE ROSCAVEL 1.1/4 | D142: CONEXOES ROSCAVEIS | E142: AF | F142: PC | G142: Sacos | H142: 0.1498 | I142: 60 | J142: 80 | K142: 10 | L142: =J142*I142*K142 -> 48000 | M142: 7897801311861 | N142: NÃO APLICA | O142: NÃO APLICA | P142: NÃO APLICA | Q142: 0.2 | R142: 0.12 | S142: 0.3 | T142: 12 | U142: 3917.40.90 | V142: 0 | W142: 17897801311868 | X142: 0.42 | Y142: 0.23 | Z142: 0.65 | AA142: =Y142*X142*Z142 -> 0.06279 | AB142: 108 | AC142: 27897801311865 | AD142: Validade indeterminada
B143: 303 | C143: TE ROSCAVEL 1.1/2 | D143: CONEXOES ROSCAVEIS | E143: AF | F143: PC | G143: Sacos | H143: 0.197 | I143: 61 | J143: 104 | K143: 84 | L143: =J143*I143*K143 -> 532896 | M143: 7897801311632 | N143: NÃO APLICA | O143: NÃO APLICA | P143: NÃO APLICA | Q143: 0.25 | R143: 0.105 | S143: 0.37 | T143: 10 | U143: 3917.40.90 | V143: 0 | W143: 17897801311639 | X143: 0.58 | Y143: 0.22 | Z143: 0.76 | AA143: =Y143*X143*Z143 -> 0.096976 | AB143: 100 | AC143: 27897801311636 | AD143: Validade indeterminada
B144: 304 | C144: TE ROSCAVEL 2 | D144: CONEXOES ROSCAVEIS | E144: AF | F144: PC | G144: Sacos | H144: 0.3011 | I144: 10 | J144: 70 | K144: 70 | L144: =J144*I144*K144 -> 49000 | M144: 7897801311878 | N144: NÃO APLICA | O144: NÃO APLICA | P144: NÃO APLICA | Q144: 0.24 | R144: 0.12 | S144: 0.33 | T144: 6 | U144: 3917.40.90 | V144: 0 | W144: 17897801311875 | X144: 0.4 | Y144: 0.25 | Z144: 0.65 | AA144: =Y144*X144*Z144 -> 0.065 | AB144: 54 | AC144: 27897801311872 | AD144: Validade indeterminada
... B330: 519 | C330: ADESIVO FRASCO 850 G | D330: ADESIVOS E COMPLEMENTOS | E330: AF | F330: PC | G330: Caixas | H330: 0.85 | I330: 95 | J330: 200 | K330: 95 | L330: =J330*I330*K330 -> 1805000 | M330: 7897801302678 | N330: NÃO APLICA | O330: NÃO APLICA | P330: NÃO APLICA | Q330: 0.19 | R330: 0.22 | S330: 0.28 | T330: 6 | U330: 3506.91.10 | V330: 0 | W330: 17897801302675 | X330: 0.3 | Y330: 0.25 | Z330: 0.6 | AA330: =Y330*X330*Z330 -> 0.045 | AB330: 18 | AC330: 27897801302672 | AD330: 18 meses
B331: 520 | C331: SOLUCAO PREPARADORA 200 ML | D331: ADESIVOS E COMPLEMENTOS | E331: AF | F331: PC | G331: Caixas | H331: 0.158 | I331: 70 | J331: 83 | K331: 70 | L331: =J331*I331*K331 -> 406700 | M331: 7897801302685 | N331: NÃO APLICA | O331: NÃO APLICA | P331: NÃO APLICA | Q331: 0.145 | R331: 0.235 | S331: 0.205 | T331: 12 | U331: 3814.00.90 | V331: 0.065 | W331: 17897801302682 | X331: NÃO APLICA | Y331: NÃO APLICA | Z331: NÃO APLICA | AB331: 120 | AC331: 27897801302689 | AD331: 12 meses
B332: 521 | C332: SOLUCAO PREPARADORA 1000 ML | D332: ADESIVOS E COMPLEMENTOS | E332: AF | F332: PC | G332: Caixas | H332: 0.79 | I332: 98 | J332: 190 | K332: 98 | L332: =J332*I332*K332 -> 1824760 | M332: 7897801302692 | N332: NÃO APLICA | O332: NÃO APLICA | P332: NÃO APLICA | Q332: 0.195 | R332: 0.235 | S332: 0.28 | T332: 6 | U332: 3814.00.90 | V332: 0.065 | W332: 17897801302699 | X332: 0.3 | Y332: 0.24 | Z332: 0.595 | AA332: =Y332*X332*Z332 -> 0.04284 | AB332: 18 | AC332: 27897801302696 | AD332: 12 meses
B333: 522 | C333: ADESIVO PLÁSTICO EXTRAFORTE PARA PVC 175g C/ PINCEL APLICADOR | D333: ADESIVOS E COMPLEMENTOS | E333: AF | F333: PC | G333: Caixas | H333: 0.175 | I333: 68 | J333: 103 | K333: 68 | L333: 431200 | M333: 7897801320894 | N333: NÃO APLICA | O333: NÃO APLICA | P333: NÃO APLICA | Q333: 0.16 | R333: 0.21 | S333: 0.205 | T333: 12 | U333: 3506.91.10 | V333: 0 | W333: 17897801320891 | X333: 0.37 | Y333: 0.44 | Z333: 0.485 | AA333: 0.079 | AB333: 120 | AC333: 27897801320898 | AD333: 18 meses
B334: 523 | C334: ADESIVO PLÁSTICO EXTRAFORTE PARA PVC 850g | D334: ADESIVOS E COMPLEMENTOS | E334: AF | F334: PC | G334: Caixas | H334: 0.85 | I334: 94 | J334: 220 | K334: 94 | L334: 1805000 | M334: 7897801320900 | N334: NÃO APLICA | O334: NÃO APLICA | P334: NÃO APLICA | Q334: 0.205 | R334: 0.242 | S334: 0.285 | T334: 6 | U334: 3506.91.10 | V334: 0 | W334: 17897801320907 | X334: 0.295 | Y334: 0.255 | Z334: 0.605 | AA334: 0.0455 | AB334: 18 | AC334: 27897801320904 | AD334: 18 meses
B335: 540 | C335: REGISTRO ESFERA SOLD - 20MM | D335: REGISTROS ESFERA COMPACTO | E335: AF | F335: PC | G335: Sacos | H335: 0.0419 | I335: 66 | J335: 58 | K335: 33 | L335: =J335*I335*K335 -> 126324 | M335: 7897801301008 | N335: NÃO APLICA | O335: NÃO APLICA | P335: NÃO APLICA | Q335: 0.13 | R335: 0.055 | S335: 0.16 | T335: 6 | U335: 8481.80.95 | V335: 0 | W335: 17897801301005 | X335: 0.49 | Y335: 0.19 | Z335: 0.65 | AA335: =Y335*X335*Z335 -> 0.060515 | AB335: 390 | AC335: 27897801301002 | AD335: Validade indeterminada
B336: 541 | C336: REGISTRO ESFERA SOLD - 25MM | D336: REGISTROS ESFERA COMPACTO | E336: AF | F336: PC | G336: Sacos | H336: 0.0546 | I336: 66 | J336: 65 | K336: 38 | L336: =J336*I336*K336 -> 163020 | M336: 7897801301015 | N336: NÃO APLICA | O336: NÃO APLICA | P336: NÃO APLICA | Q336: 0.15 | R336: 0.04 | S336: 0.2 | T336: 6 | U336: 8481.80.95 | V336: 0 | W336: 17897801301012 | X336: 0.52 | Y336: 0.18 | Z336: 0.7 | AA336: =Y336*X336*Z336 -> 0.06552 | AB336: 330 | AC336: 27897801301019 | AD336: Validade indeterminada
B337: 542 | C337: REGISTRO ESFERA SOLD - 32MM | D337: REGISTROS ESFERA COMPACTO | E337: AF | F337: PC | G337: Sacos | H337: 0.1082 | I337: 82 | J337: 80 | K337: 47 | L337: =J337*I337*K337 -> 308320 | M337: 7897801301022 | N337: NÃO APLICA | O337: NÃO APLICA | P337: NÃO APLICA | Q337: 0.15 | R337: 0.05 | S337: 0.2 | T337: 4 | U337: 8481.80.95 | V337: 0 | W337: 17897801301029 | X337: 0.45 | Y337: 0.2 | Z337: 0.65 | AA337: =Y337*X337*Z337 -> 0.0585 | AB337: 160 | AC337: 27897801301026 | AD337: Validade indeterminada
B338: 543 | C338: REGISTRO ESFERA SOLD - 40MM | D338: REGISTROS ESFERA COMPACTO | E338: AF | F338: PC | G338: Sacos | H338: 0.2037 | I338: 111 | J338: 102 | K338: 58 | L338: =J338*I338*K338 -> 656676 | M338: 7897801301060 | N338: NÃO APLICA | O338: NÃO APLICA | P338: NÃO APLICA | Q338: 0.23 | R338: 0.06 | S338: 0.23 | T338: 3 | U338: 8481.80.95 | V338: 0 | W338: 17897801301067 | X338: 0.51 | Y338: 0.19 | Z338: 0.74 | AA338: =Y338*X338*Z338 -> 0.071706 | AB338: 75 | AC338: 27897801301064 | AD338: Validade indeterminada
B339: 544 | C339: REGISTRO ESFERA SOLD - 50MM | D339: REGISTROS ESFERA COMPACTO | E339: AF | F339: PC | G339: Sacos | H339: 0.2697 | I339: 115 | J339: 109 | K339: 70 | L339: =J339*I339*K339 -> 877450 | M339: 7897801301077 | N339: NÃO APLICA | O339: NÃO APLICA | P339: NÃO APLICA | Q339: 0.2 | R339: 0.08 | S339: 0.2 | T339: 3 | U339: 8481.80.95 | V339: 0 | W339: 17897801301074 | X339: 0.45 | Y339: 0.17 | Z339: 0.7 | AA339: =Y339*X339*Z339 -> 0.05355 | AB339: 60 | AC339: 27897801301071 | AD339: Validade indeterminada
B340: 545 | C340: REGISTRO ESFERA SOLD - 60MM | D340: REGISTROS ESFERA COMPACTO | E340: AF | F340: PC | G340: Sacos | H340: 0.4226 | I340: 129 | J340: 125 | K340: 81 | L340: =J340*I340*K340 -> 1306125 | M340: 7897801301084 | N340: NÃO APLICA | O340: NÃO APLICA | P340: NÃO APLICA | Q340: 0.2 | R340: 0.08 | S340: 0.3 | T340: 2 | U340: 8481.80.95 | V340: 0 | W340: 17897801301081 | X340: 0.5 | Y340: 0.17 | Z340: 0.65 | AA340: =Y340*X340*Z340 -> 0.05525 | AB340: 38 | AC340: 27897801301088 | AD340: Validade indeterminada
B341: 546 | C341: REGISTRO ESFERA SOLD - 75MM | D341: REGISTROS ESFERA COMPACTO | E341: AF | F341: PC | G341: Sacos | H341: 1.0342 | I341: 180 | J341: 115 | K341: 165 | L341: =J341*I341*K341 -> 3415500 | M341: 7897801312400 | N341: NÃO APLICA | O341: NÃO APLICA | P341: NÃO APLICA | Q341: 0.172 | R341: 0.202 | S341: 0.23 | T341: 2 | U341: 8481.80.95 | V341: 0 | W341: 17897801312407 | X341: 0 | Y341: 0 | Z341: 0 | AA341: 0 | AB341: 0 | AC341: 0 | AD341: Validade indeterminada
B342: 547 | C342: REGISTRO ESFERA SOLD - 85MM | D342: REGISTROS ESFERA COMPACTO | E342: AF | F342: PC | G342: Sacos | H342: 1.5453 | I342: 205 | J342: 130 | K342: 180 | L342: =J342*I342*K342 -> 4797000 | M342: 7897801312417 | N342: NÃO APLICA | O342: NÃO APLICA | P342: NÃO APLICA | Q342: 0.255 | R342: 0.162 | S342: 0.31 | T342: 2 | U342: 8481.80.95 | V342: 0 | W342: 17897801312414 | X342: 0 | Y342: 0 | Z342: 0 | AA342: 0 | AB342: 0 | AC342: 0 | AD342: Validade indeterminada
B343: 548 | C343: REGISTRO ESFERA SOLD - 110MM | D343: REGISTROS ESFERA COMPACTO | E343: AF | F343: PC | G343: Sacos | H343: 2.4063 | I343: 235 | J343: 160 | K343: 210 | L343: =J343*I343*K343 -> 7896000 | M343: 7897801313858 | N343: NÃO APLICA | O343: NÃO APLICA | P343: NÃO APLICA | Q343: 0.193 | R343: 0.167 | S343: 0.26 | T343: 1 | U343: 8481.80.95 | V343: 0 | W343: 17897801313855 | X343: 0 | Y343: 0 | Z343: 0 | AA343: 0 | AB343: 0 | AC343: 0 | AD343: Validade indeterminada
B344: 551 | C344: REGISTRO ESFERA ROSCAVEL - 1/2 | D344: REGISTROS ESFERA COMPACTO | E344: AF | F344: PC | G344: Sacos | H344: 0.0511 | I344: 66 | J344: 58 | K344: 33 | L344: =J344*I344*K344 -> 126324 | M344: 7897801301039 | N344: NÃO APLICA | O344: NÃO APLICA | P344: NÃO APLICA | Q344: 0.175 | R344: 0.035 | S344: 0.175 | T344: 6 | U344: 8481.80.95 | V344: 0 | W344: 17897801301036 | X344: 0.525 | Y344: 0.16 | Z344: 0.78 | AA344: =Y344*X344*Z344 -> 0.06552 | AB344: 390 | AC344: 27897801301033 | AD344: Validade indeterminada
B345: 552 | C345: REGISTRO ESFERA ROSCAVEL - 3/4 | D345: REGISTROS ESFERA COMPACTO | E345: AF | F345: PC | G345: Sacos | H345: 0.0625 | I345: 66 | J345: 65 | K345: 38 | L345: =J345*I345*K345 -> 163020 | M345: 7897801301046 | N345: NÃO APLICA | O345: NÃO APLICA | P345: NÃO APLICA | Q345: 0.15 | R345: 0.04 | S345: 0.2 | T345: 6 | U345: 8481.80.95 | V345: 0 | W345: 17897801301043 | X345: 0.52 | Y345: 0.18 | Z345: 0.7 | AA345: =Y345*X345*Z345 -> 0.06552 | AB345: 330 | AC345: 27897801301040 | AD345: Validade indeterminada
B346: 553 | C346: REGISTRO ESFERA ROSCAVEL - 1 | D346: REGISTROS ESFERA COMPACTO | E346: AF | F346: PC | G346: Sacos | H346: 0.12 | I346: 82 | J346: 80 | K346: 47 | L346: =J346*I346*K346 -> 308320 | M346: 7897801301053 | N346: NÃO APLICA | O346: NÃO APLICA | P346: NÃO APLICA | Q346: 0.15 | R346: 0.05 | S346: 0.2 | T346: 2 | U346: 8481.80.95 | V346: 0 | W346: 17897801301050 | X346: 0.45 | Y346: 0.2 | Z346: 0.65 | AA346: =Y346*X346*Z346 -> 0.0585 | AB346: 160 | AC346: 27897801301057 | AD346: Validade indeterminada
B347: 554 | C347: REGISTRO ESFERA ROSCAVEL - 1.1/4 | D347: REGISTROS ESFERA COMPACTO | E347: AF | F347: PC | G347: Sacos | H347: 0.2059 | I347: 111 | J347: 70 | K347: 95 | L347: =J347*I347*K347 -> 738150 | M347: 7897801301091 | N347: NÃO APLICA | O347: NÃO APLICA | P347: NÃO APLICA | Q347: 0.14 | R347: 0.08 | S347: 0.26 | T347: 3 | U347: 8481.80.95 | V347: 0 | W347: 17897801301098 | X347: 0.52 | Y347: 0.22 | Z347: 0.7 | AA347: =Y347*X347*Z347 -> 0.08008 | AB347: 75 | AC347: 27897801301095 | AD347: Validade indeterminada
...

Sheet informações de produtos
B2: Produto | C2: Descrição | D2: Linha | E2: Função | F2: Aplicação | G2: Características técnicas | H2: Normas de referência | I2: Benefícios
B3: 23 | C3: TUBO PVC SOLDAVEL - 6M - 20MM | D3: TUBOS PVC SOLDAVEL
B4: 24 | C4: TUBO PVC SOLDAVEL - 6M - 25MM | D4: TUBOS PVC SOLDAVEL
B5: 25 | C5: TUBO PVC SOLDAVEL - 6M - 32MM | D5: TUBOS PVC SOLDAVEL
B6: 26 | C6: TUBO PVC SOLDAVEL - 6M - 40MM | D6: TUBOS PVC SOLDAVEL
B7: 27 | C7: TUBO PVC SOLDAVEL - 6M - 50MM | D7: TUBOS PVC SOLDAVEL
B8: 28 | C8: TUBO PVC SOLDAVEL - 6M - 60MM | D8: TUBOS PVC SOLDAVEL
B9: 29 | C9: TUBO PVC SOLDAVEL - 6M - 75MM | D9: TUBOS PVC SOLDAVEL
B10: 30 | C10: TUBO PVC SOLDAVEL - 6M - 85MM | D10: TUBOS PVC SOLDAVEL
B11: 31 | C11: TUBO PVC SOLDAVEL - 6M - 110MM | D11: TUBOS PVC SOLDAVEL
B12: 32 | C12: TUBO PVC SOLDAVEL - 3M - 20MM | D12: TUBOS PVC SOLDAVEL
B13: 33 | C13: TUBO PVC SOLDAVEL - 3M - 25MM | D13: TUBOS PVC SOLDAVEL
B14: 34 | C14: TUBO PVC SOLDAVEL - 3M - 32MM | D14: TUBOS PVC SOLDAVEL
... B18: 38 | C18: TUBO PVC SOLDAVEL - 3M - 75MM | D18: TUBOS PVC SOLDAVEL
B19: 50 | C19: TUBO ULTRATERM 3M - 15MM | D19: CPVC - ULTRATERM - TUBOS | E19: Conduzir por longos trechos o fluido em elevadas temperaturas ou pressões sem comprometer a instalação e suas propriedades. | F19: Utilizada em instalação hidráulica residencial, comercial e industrial na geração de água quente ou sistemas de água fria com alta pressão, Por exemplo: Ramais de água quente, linhas de prumada de água fria. | G19: *Material: CPVC (Policloreto de Vinila Clorado). *Processo: Extrusão * Cor: Bege *Conexão: Ponta / Ponta *Temperatura x Pressão: *20 ͦC x 24 kgf/cm² *70 ͦC x 9 kgf/cm² | H19: *ABNT NBR 15884 *ABNT NBR 5626 | I19: *Sem efeito nocivo ao organismo, atóxico. *Baixa condutividade térmica, isolante. * Resistente a corrosão, não enferruja. *Superfície interna lisa, não incrusta.
B20: 51 | C20: TUBO ULTRATERM 3M - 22MM | D20: CPVC - ULTRATERM - TUBOS | E20: Conduzir por longos trechos o fluido em elevadas temperaturas ou pressões sem comprometer a instalação e suas propriedades. | F20: Utilizada em instalação hidráulica residencial, comercial e industrial na geração de água quente ou sistemas de água fria com alta pressão, Por exemplo: Ramais de água quente, linhas de prumada de água fria. | G20: *Material: CPVC (Policloreto de Vinila Clorado). *Processo: Extrusão * Cor: Bege *Conexão: Ponta / Ponta *Temperatura x Pressão: *20 ͦC x 24 kgf/cm² *70 ͦC x 9 kgf/cm² | H20: *ABNT NBR 15884 *ABNT NBR 5626 | I20: *Sem efeito nocivo ao organismo, atóxico. *Baixa condutividade térmica, isolante. * Resistente a corrosão, não enferruja. *Superfície interna lisa, não incrusta.
B21: 52 | C21: TUBO ULTRATERM 3M - 28MM | D21: CPVC - ULTRATERM - TUBOS | E21: Conduzir por longos trechos o fluido em elevadas temperaturas ou pressões sem comprometer a instalação e suas propriedades. | F21: Utilizada em instalação hidráulica residencial, comercial e industrial na geração de água quente ou sistemas de água fria com alta pressão, Por exemplo: Ramais de água quente, linhas de prumada de água fria. | G21: *Material: CPVC (Policloreto de Vinila Clorado). *Processo: Extrusão * Cor: Bege *Conexão: Ponta / Ponta *Temperatura x Pressão: *20 ͦC x 24 kgf/cm² *70 ͦC x 9 kgf/cm² | H21: *ABNT NBR 15884 *ABNT NBR 5626 | I21: *Sem efeito nocivo ao organismo, atóxico. *Baixa condutividade térmica, isolante. * Resistente a corrosão, não enferruja. *Superfície interna lisa, não incrusta.
B22: 100 | C22: TUBO PVC ESGOTO SEC. - 6M - DN 40 | D22: TUBOS PVC ESGOTO
B23: 101 | C23: TUBO PVC ESGOTO PRIM. - 6M - DN 50 | D23: TUBOS PVC ESGOTO
B24: 102 | C24: TUBO PVC ESGOTO PRIM. - 6M - DN 75 | D24: TUBOS PVC ESGOTO
B25: 103 | C25: TUBO PVC ESGOTO PRIM. - 6M - DN 100 | D25: TUBOS PVC ESGOTO
B26: 104 | C26: TUBO PVC ESGOTO PRIM. - 6M - DN 150 | D26: TUBOS PVC ESGOTO
B27: 105 | C27: TUBO PVC ESGOTO PRIM. - 6M - DN 200 | D27: TUBOS PVC ESGOTO
B28: 106 | C28: TUBO PVC LEVE - 6M - DN 250 | D28: TUBOS PVC ESGOTO
B29: 110 | C29: TUBO PVC ESGOTO SEC. - 3M- DN 40 | D29: TUBOS PVC ESGOTO
B30: 111 | C30: TUBO PVC ESGOTO PRIM. - 3M- DN 50 | D30: TUBOS PVC ESGOTO
B31: 112 | C31: TUBO PVC ESGOTO PRIM. - 3M- DN 75 | D31: TUBOS PVC ESGOTO
B32: 113 | C32: TUBO PVC ESGOTO PRIM. - 3M- DN 100 | D32: TUBOS PVC ESGOTO
B33: 114 | C33: TUBO PVC ESGOTO PRIM. - 3M- DN 150 | D33: TUBOS PVC ESGOTO
... B41: 122 | C41: TUBO PVC ROSC 2 | D41: TUBOS PVC BRANCO
B42: 136 | C42: TUBO PVC ESG SR 6M DN50X6M | D42: TUBOS PVC ESGOTO | E42: Instalações prediais industriais, comerciais e residenciais, principalmente quando se exige maiores esforços. | F42: A linha de Esgoto Série Reforçada é utilizada em instalações prediais de esgoto sanitário, água pluvial e ventilação na qual se necessita de uma maior classe de rigidez. Geralmente utilizada em obras verticais com mais de três pavimentos, como: tubos de queda e subcoletores. | G42: *Matéria Prima PVC (Policloreto de Vinila) *Cor: Cinza Claro *Processo: Extrusão *Temperatura Nominal: 75 ͦC (regime não contínuo) *Escoamento por gravidade, não submetida a pressão e ventilação. *Resistência a classe de rigidez de 3.200Pa para os tubos esgoto DN 100 e 150 mm. | H42: *ABNT NBR 5688 *ABNT NBR 8160 | I42: *Resistente a esforços mecânicos e a temperatura. *Fácil instalação. *Simples execução das juntas, leveza dos materiais. *Estanqueidade em junta elástica. *Bolsa com dupla ação: junta elástica e soldável.
B43: 137 | C43: TUBO PVC ESG SR 6M DN75X6M | D43: TUBOS PVC ESGOTO | E43: Instalações prediais industriais, comerciais e residenciais, principalmente quando se exige maiores esforços. | F43: A linha de Esgoto Série Reforçada é utilizada em instalações prediais de esgoto sanitário, água pluvial e ventilação na qual se necessita de uma maior classe de rigidez. Geralmente utilizada em obras verticais com mais de três pavimentos, como: tubos de queda e subcoletores. | G43: *Matéria Prima PVC (Policloreto de Vinila) *Cor: Cinza Claro *Processo: Extrusão *Temperatura Nominal: 75 ͦC (regime não contínuo) *Escoamento por gravidade, não submetida a pressão e ventilação. *Resistência a classe de rigidez de 3.200Pa para os tubos esgoto DN 100 e 150 mm. | H43: *ABNT NBR 5688 *ABNT NBR 8160 | I43: *Resistente a esforços mecânicos e a temperatura. *Fácil instalação. *Simples execução das juntas, leveza dos materiais. *Estanqueidade em junta elástica. *Bolsa com dupla ação: junta elástica e soldável.
B44: 138 | C44: TUBO PVC ESG SR 6M DN100X6M | D44: TUBOS PVC ESGOTO | E44: Instalações prediais industriais, comerciais e residenciais, principalmente quando se exige maiores esforços. | F44: A linha de Esgoto Série Reforçada é utilizada em instalações prediais de esgoto sanitário, água pluvial e ventilação na qual se necessita de uma maior classe de rigidez. Geralmente utilizada em obras verticais com mais de três pavimentos, como: tubos de queda e subcoletores. | G44: *Matéria Prima PVC (Policloreto de Vinila) *Cor: Cinza Claro *Processo: Extrusão *Temperatura Nominal: 75 ͦC (regime não contínuo) *Escoamento por gravidade, não submetida a pressão e ventilação. *Resistência a classe de rigidez de 3.200Pa para os tubos esgoto DN 100 e 150 mm. | H44: *ABNT NBR 5688 *ABNT NBR 8160 | I44: *Resistente a esforços mecânicos e a temperatura. *Fácil instalação. *Simples execução das juntas, leveza dos materiais. *Estanqueidade em junta elástica. *Bolsa com dupla ação: junta elástica e soldável.
B45: 139 | C45: TUBO PVC ESG SR 6M DN150X6M | D45: TUBOS PVC ESGOTO | E45: Instalações prediais industriais, comerciais e residenciais, principalmente quando se exige maiores esforços. | F45: A linha de Esgoto Série Reforçada é utilizada em instalações prediais de esgoto sanitário, água pluvial e ventilação na qual se necessita de uma maior classe de rigidez. Geralmente utilizada em obras verticais com mais de três pavimentos, como: tubos de queda e subcoletores. | G45: *Matéria Prima PVC (Policloreto de Vinila) *Cor: Cinza Claro *Processo: Extrusão *Temperatura Nominal: 75 ͦC (regime não contínuo) *Escoamento por gravidade, não submetida a pressão e ventilação. *Resistência a classe de rigidez de 3.200Pa para os tubos esgoto DN 100 e 150 mm. | H45: *ABNT NBR 5688 *ABNT NBR 8160 | I45: *Resistente a esforços mecânicos e a temperatura. *Fácil instalação. *Simples execução das juntas, leveza dos materiais. *Estanqueidade em junta elástica. *Bolsa com dupla ação: junta elástica e soldável.
B46: 147 | C46: TUBO PPR PN20 20MMX3M | D46: TUBOS PPR | E46: Os Tubos PN20 e PN25 são produzidos em PPR e sua instalação permite encaminhar água quente ou fria aos pontos de consumo | F46: Utilizado em instalação de água quente residencial, comercial, industrial e pode ser embutida em parede de alvenaria, enterrada, parede oca (drywall) e instalações aparentes. | G46: *Material: Polipropileno Copolímero Random PPR. *Material: Polipropileno Copolímero Random PPR. | H46: *ABNT NBR 15813 ○ Parte 1 ○ Parte 2 ○ Parte 3 *ABNT NBR 7198 * DIN 8077 *DIN 8078 *DIN 16962 | I46: *Consulte a tabela de resistência química do PPR disponível no catálogo técnico da linha. *Fácil instalação. * Baixa condutividade térmica. *Economia de energia.
B47: 148 | C47: TUBO PPR PN20 25MMX3M | D47: TUBOS PPR | E47: Os Tubos PN20 e PN25 são produzidos em PPR e sua instalação permite encaminhar água quente ou fria aos pontos de consumo | F47: Utilizado em instalação de água quente residencial, comercial, industrial e pode ser embutida em parede de alvenaria, enterrada, parede oca (drywall) e instalações aparentes. | G47: *Material: Polipropileno Copolímero Random PPR. *Material: Polipropileno Copolímero Random PPR. | H47: *ABNT NBR 15813 ○ Parte 1 ○ Parte 2 ○ Parte 3 *ABNT NBR 7198 * DIN 8077 *DIN 8078 *DIN 16962 | I47: *Consulte a tabela de resistência química do PPR disponível no catálogo técnico da linha. *Fácil instalação. * Baixa condutividade térmica. *Economia de energia.
B48: 149 | C48: TUBO PPR PN20 32MMX3M | D48: TUBOS PPR | E48: Os Tubos PN20 e PN25 são produzidos em PPR e sua instalação permite encaminhar água quente ou fria aos pontos de consumo | F48: Utilizado em instalação de água quente residencial, comercial, industrial e pode ser embutida em parede de alvenaria, enterrada, parede oca (drywall) e instalações aparentes. | G48: *Material: Polipropileno Copolímero Random PPR. *Material: Polipropileno Copolímero Random PPR. | H48: *ABNT NBR 15813 ○ Parte 1 ○ Parte 2 ○ Parte 3 *ABNT NBR 7198 * DIN 8077 *DIN 8078 *DIN 16962 | I48: *Consulte a tabela de resistência química do PPR disponível no catálogo técnico da linha. *Fácil instalação. * Baixa condutividade térmica. *Economia de energia.
B49: 150 | C49: TUBO PPR PN20 40MMX3M | D49: TUBOS PPR | E49: Os Tubos PN20 e PN25 são produzidos em PPR e sua instalação permite encaminhar água quente ou fria aos pontos de consumo | F49: Utilizado em instalação de água quente residencial, comercial, industrial e pode ser embutida em parede de alvenaria, enterrada, parede oca (drywall) e instalações aparentes. | G49: *Material: Polipropileno Copolímero Random PPR. *Material: Polipropileno Copolímero Random PPR. | H49: *ABNT NBR 15813 ○ Parte 1 ○ Parte 2 ○ Parte 3 *ABNT NBR 7198 * DIN 8077 *DIN 8078 *DIN 16962 | I49: *Consulte a tabela de resistência química do PPR disponível no catálogo técnico da linha. *Fácil instalação. * Baixa condutividade térmica. *Economia de energia.
B50: 151 | C50: TUBO PPR PN20 50MMX3M | D50: TUBOS PPR | E50: Os Tubos PN20 e PN25 são produzidos em PPR e sua instalação permite encaminhar água quente ou fria aos pontos de consumo | F50: Utilizado em instalação de água quente residencial, comercial, industrial e pode ser embutida em parede de alvenaria, enterrada, parede oca (drywall) e instalações aparentes. | G50: *Material: Polipropileno Copolímero Random PPR. *Material: Polipropileno Copolímero Random PPR. | H50: *ABNT NBR 15813 ○ Parte 1 ○ Parte 2 ○ Parte 3 *ABNT NBR 7198 * DIN 8077 *DIN 8078 *DIN 16962 | I50: *Consulte a tabela de resistência química do PPR disponível no catálogo técnico da linha. *Fácil instalação. * Baixa condutividade térmica. *Economia de energia.
B51: 152 | C51: TUBO PPR PN20 63MMX3M | D51: TUBOS PPR | E51: Os Tubos PN20 e PN25 são produzidos em PPR e sua instalação permite encaminhar água quente ou fria aos pontos de consumo | F51: Utilizado em instalação de água quente residencial, comercial, industrial e pode ser embutida em parede de alvenaria, enterrada, parede oca (drywall) e instalações aparentes. | G51: *Material: Polipropileno Copolímero Random PPR. *Material: Polipropileno Copolímero Random PPR. | H51: *ABNT NBR 15813 ○ Parte 1 ○ Parte 2 ○ Parte 3 *ABNT NBR 7198 * DIN 8077 *DIN 8078 *DIN 16962 | I51: *Consulte a tabela de resistência química do PPR disponível no catálogo técnico da linha. *Fácil instalação. * Baixa condutividade térmica. *Economia de energia.
B52: 153 | C52: TUBO PPR PN20 75MMX3M | D52: TUBOS PPR | E52: Os Tubos PN20 e PN25 são produzidos em PPR e sua instalação permite encaminhar água quente ou fria aos pontos de consumo | F52: Utilizado em instalação de água quente residencial, comercial, industrial e pode ser embutida em parede de alvenaria, enterrada, parede oca (drywall) e instalações aparentes. | G52: *Material: Polipropileno Copolímero Random PPR. *Material: Polipropileno Copolímero Random PPR. | H52: *ABNT NBR 15813 ○ Parte 1 ○ Parte 2 ○ Parte 3 *ABNT NBR 7198 * DIN 8077 *DIN 8078 *DIN 16962 | I52: *Consulte a tabela de resistência química do PPR disponível no catálogo técnico da linha. *Fácil instalação. * Baixa condutividade térmica. *Economia de energia.
B53: 154 | C53: TUBO PPR PN20 90MMX3M | D53: TUBOS PPR | E53: Os Tubos PN20 e PN25 são produzidos em PPR e sua instalação permite encaminhar água quente ou fria aos pontos de consumo | F53: Utilizado em instalação de água quente residencial, comercial, industrial e pode ser embutida em parede de alvenaria, enterrada, parede oca (drywall) e instalações aparentes. | G53: *Material: Polipropileno Copolímero Random PPR. *Material: Polipropileno Copolímero Random PPR. | H53: *ABNT NBR 15813 ○ Parte 1 ○ Parte 2 ○ Parte 3 *ABNT NBR 7198 * DIN 8077 *DIN 8078 *DIN 16962 | I53: *Consulte a tabela de resistência química do PPR disponível no catálogo técnico da linha. *Fácil instalação. * Baixa condutividade térmica. *Economia de energia.
... B63: 164 | C63: TUBO PPR PN25 110MMX3M | D63: TUBOS PPR | E63: Os Tubos PN20 e PN25 são produzidos em PPR e sua instalação permite encaminhar água quente ou fria aos pontos de consumo | F63: Utilizado em instalação de água quente residencial, comercial, industrial e pode ser embutida em parede de alvenaria, enterrada, parede oca (drywall) e instalações aparentes. | G63: *Material: Polipropileno Copolímero Random PPR. *Material: Polipropileno Copolímero Random PPR. | H63: *ABNT NBR 15813 ○ Parte 1 ○ Parte 2 ○ Parte 3 *ABNT NBR 7198 * DIN 8077 *DIN 8078 *DIN 16962 | I63: *Consulte a tabela de resistência química do PPR disponível no catálogo técnico da linha. *Fácil instalação. * Baixa condutividade térmica. *Economia de energia.
B64: 180 | C64: TUBO PVC BRANCO - 6M - 25MM | D64: TUBOS PVC BRANCO
B65: 181 | C65: TUBO PVC BRANCO - 6M - 40MM | D65: TUBOS PVC BRANCO
B66: 182 | C66: TUBO PVC BRANCO - 6M - 50MM | D66: TUBOS PVC BRANCO
B67: 183 | C67: TUBO PVC BRANCO - 6M - 75MM | D67: TUBOS PVC BRANCO
B68: 184 | C68: TUBO PVC BRANCO - 6M - 100MM | D68: TUBOS PVC BRANCO
B69: 185 | C69: TUBO PVC BRANCO - 6M - 150MM | D69: TUBOS PVC BRANCO
B70: 200 | C70: ADAPTADOR ROSC. P/CX.DAGUA 1/2 | D70: ADAP.P/CX.D AGUA ROSC.
B71: 201 | C71: ADAPTADOR ROSC. P/CX.DAGUA 3/4 | D71: ADAP.P/CX.D AGUA ROSC.
B72: 202 | C72: ADAPTADOR ROSC. P/CX.DAGUA 1 | D72: ADAP.P/CX.D AGUA ROSC.
B73: 203 | C73: ADAPTADOR ROSC. P/CX.DAGUA 1.1/4 | D73: ADAP.P/CX.D AGUA ROSC.
B74: 204 | C74: ADAPTADOR ROSC. P/CX.DAGUA 1.1/2 | D74: ADAP.P/CX.D AGUA ROSC.
B75: 205 | C75: ADAPTADOR ROSC. P/CX.DAGUA 2 | D75: ADAP.P/CX.D AGUA ROSC.
... B156: 329 | C156: LUVA DE CORRER ROSCAVEL 2 | D156: CONEXOES ROSCAVEIS
B157: 330 | C157: ADAPTADOR SOLD CURTO 20MM X 1/2 | D157: CONEXOES SOLDAVEIS | E157: Efetuar a adaptação entre a linha soldável e roscável, adaptando a ponta do tubo para receber uma ligação ou conexão roscável. | F157: Utilizada em instalação hidráulica residencial, comercial e industrial nas tubulações de água fria, Por exemplo: em ligações que tenham a necessidade de conectar uma peça com rosca fêmea. | G157: *Material: PVC (Policloreto de Vinila). *Processo: Injeção * Cor: Marrom *Conexão: Ponta Rosca / Bolsa Solda *Temperatura x Pressão *45 ͦC x 7,5 kgf/cm² | H157: *ABNT NBR 5648 *ABNT NBR 5626 | I157: *Sem efeito nocivo ao organismo, atóxico. *Resistente a corrosão, não enferruja. * Superfície interna lisa, não incrusta.
B158: 331 | C158: ADAPTADOR SOLD CURTO 25MM X 3/4 | D158: CONEXOES SOLDAVEIS | E158: Efetuar a adaptação entre a linha soldável e roscável, adaptando a ponta do tubo para receber uma ligação ou conexão roscável. | F158: Utilizada em instalação hidráulica residencial, comercial e industrial nas tubulações de água fria, Por exemplo: em ligações que tenham a necessidade de conectar uma peça com rosca fêmea. | G158: *Material: PVC (Policloreto de Vinila). *Processo: Injeção * Cor: Marrom *Conexão: Ponta Rosca / Bolsa Solda *Temperatura x Pressão *45 ͦC x 7,5 kgf/cm² | H158: *ABNT NBR 5648 *ABNT NBR 5626 | I158: *Sem efeito nocivo ao organismo, atóxico. *Resistente a corrosão, não enferruja. * Superfície interna lisa, não incrusta.
B159: 332 | C159: ADAPTADOR SOLD CURTO 32MM X 1 | D159: CONEXOES SOLDAVEIS | E159: Efetuar a adaptação entre a linha soldável e roscável, adaptando a ponta do tubo para receber uma ligação ou conexão roscável. | F159: Utilizada em instalação hidráulica residencial, comercial e industrial nas tubulações de água fria, Por exemplo: em ligações que tenham a necessidade de conectar uma peça com rosca fêmea. | G159: *Material: PVC (Policloreto de Vinila). *Processo: Injeção * Cor: Marrom *Conexão: Ponta Rosca / Bolsa Solda *Temperatura x Pressão *45 ͦC x 7,5 kgf/cm² | H159: *ABNT NBR 5648 *ABNT NBR 5626 | I159: *Sem efeito nocivo ao organismo, atóxico. *Resistente a corrosão, não enferruja. * Superfície interna lisa, não incrusta.
B160: 333 | C160: ADAPTADOR SOLD CURTO 40MM X 1.1/4 | D160: CONEXOES SOLDAVEIS | E160: Efetuar a adaptação entre a linha soldável e roscável, adaptando a ponta do tubo para receber uma ligação ou conexão roscável. | F160: Utilizada em instalação hidráulica residencial, comercial e industrial nas tubulações de água fria, Por exemplo: em ligações que tenham a necessidade de conectar uma peça com rosca fêmea. | G160: *Material: PVC (Policloreto de Vinila). *Processo: Injeção * Cor: Marrom *Conexão: Ponta Rosca / Bolsa Solda *Temperatura x Pressão *45 ͦC x 7,5 kgf/cm² | H160: *ABNT NBR 5648 *ABNT NBR 5626 | I160: *Sem efeito nocivo ao organismo, atóxico. *Resistente a corrosão, não enferruja. * Superfície interna lisa, não incrusta.
B161: 336 | C161: ADAPTADOR SOLD CURTO 50MM X 1.1/2 | D161: CONEXOES SOLDAVEIS | E161: Efetuar a adaptação entre a linha soldável e roscável, adaptando a ponta do tubo para receber uma ligação ou conexão roscável. | F161: Utilizada em instalação hidráulica residencial, comercial e industrial nas tubulações de água fria, Por exemplo: em ligações que tenham a necessidade de conectar uma peça com rosca fêmea. | G161: *Material: PVC (Policloreto de Vinila). *Processo: Injeção * Cor: Marrom *Conexão: Ponta Rosca / Bolsa Solda *Temperatura x Pressão *45 ͦC x 7,5 kgf/cm² | H161: *ABNT NBR 5648 *ABNT NBR 5626 | I161: *Sem efeito nocivo ao organismo, atóxico. *Resistente a corrosão, não enferruja. * Superfície interna lisa, não incrusta.
B162: 337 | C162: ADAPTADOR SOLD CURTO 60MM X 2 | D162: CONEXOES SOLDAVEIS | E162: Efetuar a adaptação entre a linha soldável e roscável, adaptando a ponta do tubo para receber uma ligação ou conexão roscável. | F162: Utilizada em instalação hidráulica residencial, comercial e industrial nas tubulações de água fria, Por exemplo: em ligações que tenham a necessidade de conectar uma peça com rosca fêmea. | G162: *Material: PVC (Policloreto de Vinila). *Processo: Injeção * Cor: Marrom *Conexão: Ponta Rosca / Bolsa Solda *Temperatura x Pressão *45 ͦC x 7,5 kgf/cm² | H162: *ABNT NBR 5648 *ABNT NBR 5626 | I162: *Sem efeito nocivo ao organismo, atóxico. *Resistente a corrosão, não enferruja. * Superfície interna lisa, não incrusta.
B163: 338 | C163: ADAPTADOR SOLD CURTO 75MM X 2.1/2 | D163: CONEXOES SOLDAVEIS | E163: Efetuar a adaptação entre a linha soldável e roscável, adaptando a ponta do tubo para receber uma ligação ou conexão roscável. | F163: Utilizada em instalação hidráulica residencial, comercial e industrial nas tubulações de água fria, Por exemplo: em ligações que tenham a necessidade de conectar uma peça com rosca fêmea. | G163: *Material: PVC (Policloreto de Vinila). *Processo: Injeção * Cor: Marrom *Conexão: Ponta Rosca / Bolsa Solda *Temperatura x Pressão *45 ͦC x 7,5 kgf/cm² | H163: *ABNT NBR 5648 *ABNT NBR 5626 | I163: *Sem efeito nocivo ao organismo, atóxico. *Resistente a corrosão, não enferruja. * Superfície interna lisa, não incrusta.
B164: 339 | C164: ADAPTADOR SOLD CURTO 85MM X 3 | D164: CONEXOES SOLDAVEIS | E164: Efetuar a adaptação entre a linha soldável e roscável, adaptando a ponta do tubo para receber uma ligação ou conexão roscável. | F164: Utilizada em instalação hidráulica residencial, comercial e industrial nas tubulações de água fria, Por exemplo: em ligações que tenham a necessidade de conectar uma peça com rosca fêmea. | G164: *Material: PVC (Policloreto de Vinila). *Processo: Injeção * Cor: Marrom *Conexão: Ponta Rosca / Bolsa Solda *Temperatura x Pressão *45 ͦC x 7,5 kgf/cm² | H164: *ABNT NBR 5648 *ABNT NBR 5626 | I164: *Sem efeito nocivo ao organismo, atóxico. *Resistente a corrosão, não enferruja. * Superfície interna lisa, não incrusta.
B165: 340 | C165: ADAPTADOR SOLD CURTO 110MM X 4 | D165: CONEXOES SOLDAVEIS | E165: Efetuar a adaptação entre a linha soldável e roscável, adaptando a ponta do tubo para receber uma ligação ou conexão roscável. | F165: Utilizada em instalação hidráulica residencial, comercial e industrial nas tubulações de água fria, Por exemplo: em ligações que tenham a necessidade de conectar uma peça com rosca fêmea. | G165: *Material: PVC (Policloreto de Vinila). *Processo: Injeção * Cor: Marrom *Conexão: Ponta Rosca / Bolsa Solda *Temperatura x Pressão *45 ͦC x 7,5 kgf/cm² | H165: *ABNT NBR 5648 *ABNT NBR 5626 | I165: *Sem efeito nocivo ao organismo, atóxico. *Resistente a corrosão, não enferruja. * Superfície interna lisa, não incrusta.
B166: 341 | C166: ADAPTADOR SOLD. P/CX.DAGUA 20MM X 1/2 | D166: ADAP.P/CX.D AGUA SOLD. | E166: Efetua a adaptação na entrada e saída de caixa d’água, possuí gabarito, fundo fixo, móvel e vedação. | F166: Utilizada em instalação hidráulica residencial, comercial e industrial nas tubulações de água fria, indicado para utilização em entrada e saída de caixa d’água. | G166: *Material: PVC (Policloreto de Vinila). *Processo: Injeção * Cor: Marrom *Conexão: Bolsa Roscável BSP para a boia / Bolsa Soldável *Temperatura x Pressão *45 ͦC x 7,5 kgf/cm | H166: *ABNT NBR 5648 *ABNT NBR 5626 | I166: *Sem efeito nocivo ao organismo, atóxico. * Resistente a corrosão, não enferruja. * Juntas soldáveis a frio. *Longa vida útil. *Dispensa o uso de ferramentas.
B167: 342 | C167: ADAPTADOR SOLD. P/CX.DAGUA 25MM X 3/4 | D167: ADAP.P/CX.D AGUA SOLD. | E167: Efetua a adaptação na entrada e saída de caixa d’água, possuí gabarito, fundo fixo, móvel e vedação. | F167: Utilizada em instalação hidráulica residencial, comercial e industrial nas tubulações de água fria, indicado para utilização em entrada e saída de caixa d’água. | G167: *Material: PVC (Policloreto de Vinila). *Processo: Injeção * Cor: Marrom *Conexão: Bolsa Roscável BSP para a boia / Bolsa Soldável *Temperatura x Pressão *45 ͦC x 7,5 kgf/cm | H167: *ABNT NBR 5648 *ABNT NBR 5626 | I167: *Sem efeito nocivo ao organismo, atóxico. * Resistente a corrosão, não enferruja. * Juntas soldáveis a frio. *Longa vida útil. *Dispensa o uso de ferramentas.
B168: 343 | C168: ADAPTADOR SOLD. P/CX.DAGUA 32MM X 1 | D168: ADAP.P/CX.D AGUA SOLD. | E168: Efetua a adaptação na entrada e saída de caixa d’água, possuí gabarito, fundo fixo, móvel e vedação. | F168: Utilizada em instalação hidráulica residencial, comercial e industrial nas tubulações de água fria, indicado para utilização em entrada e saída de caixa d’água. | G168: *Material: PVC (Policloreto de Vinila). *Processo: Injeção * Cor: Marrom *Conexão: Bolsa Roscável BSP para a boia / Bolsa Soldável *Temperatura x Pressão *45 ͦC x 7,5 kgf/cm | H168: *ABNT NBR 5648 *ABNT NBR 5626 | I168: *Sem efeito nocivo ao organismo, atóxico. * Resistente a corrosão, não enferruja. * Juntas soldáveis a frio. *Longa vida útil. *Dispensa o uso de ferramentas.
... B174: 349 | C174: ADAPTADOR SOLD. P/CX.DAGUA 110MM X 4 | D174: ADAP.P/CX.D AGUA SOLD. | E174: Efetua a adaptação na entrada e saída de caixa d’água, possuí gabarito, fundo fixo, móvel e vedação. | F174: Utilizada em instalação hidráulica residencial, comercial e industrial nas tubulações de água fria, indicado para utilização em entrada e saída de caixa d’água. | G174: *Material: PVC (Policloreto de Vinila). *Processo: Injeção * Cor: Marrom *Conexão: Bolsa Roscável BSP para a boia / Bolsa Soldável *Temperatura x Pressão *45 ͦC x 7,5 kgf/cm | H174: *ABNT NBR 5648 *ABNT NBR 5626 | I174: *Sem efeito nocivo ao organismo, atóxico. * Resistente a corrosão, não enferruja. * Juntas soldáveis a frio. *Longa vida útil. *Dispensa o uso de ferramentas.
B175: 359 | C175: BUCHA RED.SOLD.CURTA 110 X 85MM | D175: CONEXOES SOLDAVEIS
B176: 360 | C176: BUCHA RED.SOLD.CURTA 25 X 20MM | D176: CONEXOES SOLDAVEIS
B177: 361 | C177: BUCHA RED.SOLD.CURTA 32 X 25MM | D177: CONEXOES SOLDAVEIS
B178: 362 | C178: BUCHA RED.SOLD.CURTA 40 X 32MM | D178: CONEXOES SOLDAVEIS
B179: 363 | C179: BUCHA RED.SOLD.CURTA 50 X 40MM | D179: CONEXOES SOLDAVEIS
B180: 364 | C180: BUCHA RED.SOLD.CURTA 60 X 50MM | D180: CONEXOES SOLDAVEIS
B181: 365 | C181: BUCHA RED.SOLD.CURTA 75 X 60MM | D181: CONEXOES SOLDAVEIS
B182: 366 | C182: BUCHA RED.SOLD.CURTA 85 X 75MM | D182: CONEXOES SOLDAVEIS
B183: 367 | C183: BUCHA RED.SOLD.LONGA 32 X 20MM | D183: CONEXOES SOLDAVEIS
B184: 368 | C184: BUCHA RED.SOLD.LONGA 40 X 20MM | D184: CONEXOES SOLDAVEIS
B185: 369 | C185: BUCHA RED.SOLD.LONGA 40 X 25MM | D185: CONEXOES SOLDAVEIS
B186: 370 | C186: BUCHA RED.SOLD.LONGA 50 X 20MM | D186: CONEXOES SOLDAVEIS
... B214: 401 | C214: CURVA 45 SOLD - 110MM | D214: CONEXOES SOLDAVEIS
B215: 402 | C215: CURVA DE TRANSPOSICAO SOLD - 20MM | D215: CONEXOES SOLDAVEIS | E215: Efetuar sobreposição de tubulações, através de seu desenho exclusivo, reduzindo emendas e garantindo a estanqueidade. | F215: Utilizada em instalação hidráulica residencial, comercial e industrial nas tubulações de água fria, indicado para utilização em instalações sobrepostas. | G215: *Material: PVC (Policloreto de Vinila). *Processo: Injeção * Cor: Marrom *Conexão: Bolsas Soldáveis *Temperatura x Pressão *45 ͦC x 7,5 kgf/cm² | H215: *ABNT NBR 5648 *ABNT NBR 5626 | I215: *Sem efeito nocivo ao organismo, atóxico. *Resistente a corrosão, não enferruja. *Juntas soldáveis a frio. *Longa vida útil.
B216: 403 | C216: CURVA DE TRANSPOSICAO SOLD - 25MM | D216: CONEXOES SOLDAVEIS | E216: Efetuar sobreposição de tubulações, através de seu desenho exclusivo, reduzindo emendas e garantindo a estanqueidade. | F216: Utilizada em instalação hidráulica residencial, comercial e industrial nas tubulações de água fria, indicado para utilização em instalações sobrepostas. | G216: *Material: PVC (Policloreto de Vinila). *Processo: Injeção * Cor: Marrom *Conexão: Bolsas Soldáveis *Temperatura x Pressão *45 ͦC x 7,5 kgf/cm² | H216: *ABNT NBR 5648 *ABNT NBR 5626 | I216: *Sem efeito nocivo ao organismo, atóxico. *Resistente a corrosão, não enferruja. *Juntas soldáveis a frio. *Longa vida útil.
B217: 404 | C217: CURVA DE TRANSPOSICAO SOLD - 32MM | D217: CONEXOES SOLDAVEIS | E217: Efetuar sobreposição de tubulações, através de seu desenho exclusivo, reduzindo emendas e garantindo a estanqueidade. | F217: Utilizada em instalação hidráulica residencial, comercial e industrial nas tubulações de água fria, indicado para utilização em instalações sobrepostas. | G217: *Material: PVC (Policloreto de Vinila). *Processo: Injeção * Cor: Marrom *Conexão: Bolsas Soldáveis *Temperatura x Pressão *45 ͦC x 7,5 kgf/cm² | H217: *ABNT NBR 5648 *ABNT NBR 5626 | I217: *Sem efeito nocivo ao organismo, atóxico. *Resistente a corrosão, não enferruja. *Juntas soldáveis a frio. *Longa vida útil.
B219: 406 | C219: CURVA 90 SOLD - 20MM | D219: CONEXOES SOLDAVEIS
B220: 407 | C220: CURVA 90 SOLD - 25MM | D220: CONEXOES SOLDAVEIS
B221: 408 | C221: CURVA 90 SOLD - 32MM | D221: CONEXOES SOLDAVEIS
B222: 409 | C222: CURVA 90 SOLD - 40MM | D222: CONEXOES SOLDAVEIS
B223: 410 | C223: CURVA 90 SOLD - 50MM | D223: CONEXOES SOLDAVEIS
B224: 411 | C224: CURVA 90 SOLD - 60MM | D224: CONEXOES SOLDAVEIS
B225: 412 | C225: CURVA 90 SOLD - 75MM | D225: CONEXOES SOLDAVEIS
B226: 413 | C226: CURVA 90 SOLD - 85MM | D226: CONEXOES SOLDAVEIS
B227: 414 | C227: CURVA 90 SOLD - 110MM | D227: CONEXOES SOLDAVEIS
B228: 415 | C228: JOELHO 45 SOLD - 20MM | D228: CONEXOES SOLDAVEIS
B229: 416 | C229: JOELHO 45 SOLD - 25MM | D229: CONEXOES SOLDAVEIS
B230: 417 | C230: JOELHO 45 SOLD - 32MM | D230: CONEXOES SOLDAVEIS
... B256: 443 | C256: LUVA SOLD - 110MM | D256: CONEXOES SOLDAVEIS
B257: 444 | C257: LUVA DE CORRER P/TUBO SOLD.20MM | D257: CONEXOES SOLDAVEIS | E257: Reparar ramais e sub-ramais de PVC, instalados de forma embutida. A Estanqueidade é garantida pelos anéis deslizantes. | F257: Utilizada em instalação hidráulica residencial, comercial e industrial nas tubulações de água fria, Por exemplo: em reparos provenientes de perfuração ou rupturas. | G257: *Material: PVC (Policloreto de Vinila). *Processo: Injeção *Cor: Marrom *Conexão: Ponta Rosca / Bolsa Solda *Temperatura x Pressão *45 ͦC x 7,5 kgf/cm² | H257: *ABNT NBR 5648 *ABNT NBR 5626 | I257: *Sem efeito nocivo ao organismo, atóxico. *Resistente a corrosão, não enferruja. *Juntas soldáveis a frio. *Longa vida útil.
B258: 445 | C258: LUVA DE CORRER P/TUBO SOLD.25MM | D258: CONEXOES SOLDAVEIS | E258: Reparar ramais e sub-ramais de PVC, instalados de forma embutida. A Estanqueidade é garantida pelos anéis deslizantes. | F258: Utilizada em instalação hidráulica residencial, comercial e industrial nas tubulações de água fria, Por exemplo: em reparos provenientes de perfuração ou rupturas. | G258: *Material: PVC (Policloreto de Vinila). *Processo: Injeção *Cor: Marrom *Conexão: Ponta Rosca / Bolsa Solda *Temperatura x Pressão *45 ͦC x 7,5 kgf/cm² | H258: *ABNT NBR 5648 *ABNT NBR 5626 | I258: *Sem efeito nocivo ao organismo, atóxico. *Resistente a corrosão, não enferruja. *Juntas soldáveis a frio. *Longa vida útil.
...

Sheet Resumo
A1: Família | B1: N° SKUS
A2: ACESSÓRIOS | B2: 53
A3: AF | B3: 395
A4: AQ | B4: 239
A5: ELETRICA | B5: 121
A6: ESGOTO | B6: 239
B7: =SUM(B2:B6) -> 1047

Sheet SB1
A1: SB1
B2: 1 | C2: 2 | D2: 3 | E2: 4 | F2: 5 | G2: 6 | H2: 7 | I2: 8 | J2: 9 | K2: 10 | L2: 11 | M2: 12 | N2: 13 | O2: 14 | P2: 15 | Q2: 16 | R2: 17 | S2: 18 | T2: 19 | U2: 20 | V2: 21 | W2: 22 | X2: 23 | Y2: 24 | Z2: 25 | AA2: 26 | AB2: 27 | AC2: 28 | AD2: 29 | AE2: 30 | AF2: 31 | AG2: 32 | AH2: 33 | AI2: 34 | AJ2: 35 | AK2: 36 | AL2: 37 | AM2: 38 | AN2: 39 | AO2: 40 | AP2: 41 | AQ2: 42 | AR2: 43 | AS2: 44 | AT2: 45 | AU2: 46 | AV2: 47 | AW2: 48 | AX2: 49 | AY2: 50 | AZ2: 51 | BA2: 52 | BB2: 53 | BC2: 54 | BD2: 55 | BE2: 56 | BF2: 57 | BG2: 58 | BH2: 59 | BI2: 60 | BJ2: 61 | BK2: 62 | BL2: 63 | BM2: 64 | BN2: 65 | BO2: 66 | BP2: 67 | BQ2: 68 | BR2: 69 | BS2: 70 | BT2: 71 | BU2: 72 | BV2: 73 | BW2: 74 | BX2: 75 | BY2: 76 | BZ2: 77 | CA2: 78 | CB2: 79 | CC2: 80 | CD2: 81 | CE2: 82 | CF2: 83 | CG2: 84 | CH2: 85 | CI2: 86 | CJ2: 87 | CK2: 88 | CL2: 89 | CM2: 90 | CN2: 91 | CO2: 92 | CP2: 93 | CQ2: 94 | CR2: 95 | CS2: 96 | CT2: 97 | CU2: 98 | CV2: 99 | CW2: 100 | CX2: 101 | CY2: 102 | CZ2: 103 | DA2: 104 | DB2: 105 | DC2: 106 | DD2: 107 | DE2: 108 | DF2: 109 | DG2: 110 | DH2: 111 | DI2: 112 | DJ2: 113 | DK2: 114 | DL2: 115 | DM2: 116 | DN2: 117 | DO2: 118 | DP2: 119 | DQ2: 120 | DR2: 121 | DS2: 122 | DT2: 123 | DU2: 124 | DV2: 125 | DW2: 126 | DX2: 127 | DY2: 128 | DZ2: 129 | EA2: 130 | EB2: 131 | EC2: 132 | ED2: 133 | EE2: 134 | EF2: 135 | EG2: 136 | EH2: 137 | EI2: 138 | EJ2: 139 | EK2: 140 | EL2: 141 | EM2: 142 | EN2: 143 | EO2: 144 | EP2: 145 | EQ2: 146 | ER2: 147 | ES2: 148 | ET2: 149 | EU2: 150 | EV2: 151 | EW2: 152 | EX2: 153 | EY2: 154 | EZ2: 155 | FA2: 156 | FB2: 157 | FC2: 158 | FD2: 159 | FE2: 160 | FF2: 161 | FG2: 162 | FH2: 163 | FI2: 164 | FJ2: 165 | FK2: 166 | FL2: 167 | FM2: 168 | FN2: 169 | FO2: 170 | FP2: 171 | FQ2: 172 | FR2: 173 | FS2: 174 | FT2: 175 | FU2: 176 | FV2: 177 | FW2: 178 | FX2: 179 | FY2: 180 | FZ2: 181 | GA2: 182 | GB2: 183 | GC2: 184 | GD2: 185 | GE2: 186 | GF2: 187 | GG2: 188 | GH2: 189 | GI2: 190 | GJ2: 191 | GK2: 192 | GL2: 193 | GM2: 194 | GN2: 195 | GO2: 196 | GP2: 197 | GQ2: 198 | GR2: 199 | GS2: 200 | GT2: 201 | GU2: 202 | GV2: 203 | GW2: 204 | GX2: 205 | GY2: 206 | GZ2: 207 | HA2: 208 | HB2: 209 | HC2: 210 | HD2: 211 | HE2: 212 | HF2: 213 | HG2: 214 | HH2: 215 | HI2: 216 | HJ2: 217 | HK2: 218 | HL2: 219 | HM2: 220 | HN2: 221 | HO2: 222 | HP2: 223 | HQ2: 224 | HR2: 225 | HS2: 226 | HT2: 227 | HU2: 228 | HV2: 229 | HW2: 230 | HX2: 231 | HY2: 232 | HZ2: 233 | IA2: 234 | IB2: 235 | IC2: 236 | ID2: 237 | IE2: 238 | IF2: 239 | IG2: 240 | IH2: 241 | II2: 242 | IJ2: 243 | IK2: 244 | IL2: 245 | IM2: 246 | IN2: 247 | IO2: 248 | IP2: 249 | IQ2: 250 | IR2: 251 | IS2: 252 | IT2: 253 | IU2: 254 | IV2: 255 | IW2: 256 | IX2: 257 | IY2: 258 | IZ2: 259 | JA2: 260 | JB2: 261 | JC2: 262 | JD2: 263 | JE2: 264 | JF2: 265 | JG2: 266 | JH2: 267 | JI2: 268 | JJ2: 269 | JK2: 270 | JL2: 271 | JM2: 272 | JN2: 273 | JO2: 274 | JP2: 275 | JQ2: 276 | JR2: 277 | JS2: 278 | JT2: 279 | JU2: 280 | JV2: 281 | JW2: 282 | JX2: 283 | JY2: 284 | JZ2: 285 | KA2: 286 | KB2: 287 | KC2: 288 | KD2: 289 | KE2: 290 | KF2: 291 | KG2: 292 | KH2: 293 | KI2: 294 | KJ2: 295 | KK2: 296 | KL2: 297 | KM2: 298 | KN2: 299 | KO2: 300 | KP2: 301 | KQ2: 302 | KR2: 303 | KS2: 304 | KT2: 305 | KU2: 306 | KV2: 307 | KW2: 308 | KX2: 309 | KY2: 310 | KZ2: 311 | LA2: 312 | LB2: 313 | LC2: 314 | LD2: 315 | LE2: 316 | LF2: 317 | LG2: 318 | LH2: 319 | LI2: 320
A3: Filial | B3: Codigo | C3: Descricao | D3: Tipo | E3: Unidade | F3: Local Padrao | G3: Grupo | H3: Aliq. ICMS | I3: Pos.IPI/NCM | J3: Ex-NCM | K3: Ex-NBM | L3: Especie TIPI | M3: Aliq. IPI | N3: Aliq. ISS | O3: Cod.Serv.ISS | P3: TE Padrao | Q3: TS Padrao | R3: Solid. Saida | S3: Solid. Entr. | T3: Foto | U3: Seg.Un.Medi. | V3: Imp.Z.Franca | W3: Tipo de Conv | X3: Fator Conv. | Y3: Alternativo | Z3: Qtd.Embalag. | AA3: Preco Venda | AB3: Ponto Pedido | AC3: Custo Stand. | AD3: Ult. Compra | AE3: Ult. Preco | AF3: Peso Liquido | AG3: Form.Est.Seg | AH3: Seguranca | AI3: Form. Prazo | AJ3: Entrega | AK3: Tipo Prazo | AL3: Lote Econom. | AM3: Lote Minimo | AN3: Cta Contabil | AO3: Tolerancia | AP3: C Custo | AQ3: Familia | AR3: Loja Padrao | AS3: Forn. Padrao | AT3: Base Estrut. | AU3: Apropriacao | AV3: Fantasma | AW3: Tipo Dec. OP | AX3: Origem | AY3: DT Referenc. | AZ3: Class.Fiscal | BA3: Ult. Revisao | BB3: Rastro | BC3: Fora estado | BD3: % Comissao | BE3: Forn. Canal | BF3: Entra MRP | BG3: Dt.Ref.Prc 1 | BH3: Per.Invent. | BI3: Grupo Trib. | BJ3: Nota Minima | BK3: Prazo Valid. | BL3: Cont.Seg.Soc | BM3: Cons.Inicial | BN3: Qtde. Copias | BO3: Cod Barras | BP3: Grade | BQ3: Cod Form Lot | BR3: Impos.Renda | BS3: Contr.Locali | BT3: Contrato | BU3: Desc. Portug | BV3: Rt.Op Padrao | BW3: Cod.Familia | BX3: Desc. Ingles | BY3: Linha | BZ3: Desc. L.I. | CA3: Val.Ref.US$ | CB3: Anuente ? | CC3: Opc. Default | CD3: Cod. Obs. | CE3: Prod. Import | CF3: Situacao | CG3: Fabricante | CH3: Gera OP Auto | CI3: Modelo | CJ3: Setor | CK3: Balanca | CL3: Produto Pai | CM3: Tecla | CN3: Tipo de C.Q. | CO3: Restricao | CP3: Gr. Compras | CQ3: Desv Padrao | CR3: Calc. FETHAB | CS3: Pauta FETHAB | CT3: PIS Pauta | CU3: COFINS Pauta | CV3: Ret.Operacao | CW3: Produ‡”es CQ | CX3: Pr.Fundersul | CY3: Cont.Prod.CQ | CZ3: P.M.kg/Prev. | DA3: Rev.Estrutur | DB3: Dem.Prevista | DC3: Calcula INSS | DD3: Classe Repos | DE3: Espec.Mater. | DF3: Custeio OP | DG3: Materia Pri. | DH3: % Red.PIS | DI3: ALADI | DJ3: Frac Permit | DK3: Status Venda | DL3: % Red.COFINS | DM3: Cod Item | DN3: MTTR em Hr. | DO3: Data Substit | DP3: P.ICMS Prop. | DQ3: Perc. COFINS | DR3: Gr Cnt Custo | DS3: Perc. CSLL | DT3: CC p/ Custo | DU3: Perc. PIS | DV3: Cód. ant. | DW3: Qtde. Midia | DX3: Inc.FETHAB | DY3: % Red. INSS | DZ3: Crd Estímulo | EA3: % Red. IRRF | EB3: C.Bar.Embal. | EC3: IPI de Pauta | ED3: Base ST R.SC | EE3: Aliq FECP | EF3: Est.Limite | EG3: Nova Emb | EH3: Cal. IVA Aju | EI3: Fust/Funttel | EJ3: Regra ISS Pg | EK3: Tp Pad.Reemb | EL3: C.B.Unitiz | EM3: C. Trib. Mun | EN3: Emb.Padrao | EO3: Imp.Direta | EP3: Embalagem | EQ3: Env. Obrigat | ER3: Parceiro | ES3: Tip Sugestao | ET3: % Macronutr. | EU3: Grupo Descon | EV3: % Micronutr. | EW3: Item Conta | EX3: Dep Correcao | EY3: Moeda C.Std | EZ3: Base Pre-Es. | FA3: Calc.Midia | FB3: IPI de Pauta | FC3: MTBF em Hr. | FD3: Reembalagem | FE3: NALADI NCCA | FF3: Qt. Reemb. | FG3: NALADI SH | FH3: Cd.Bar.Reemb | FI3: Serie/Colec. | FJ3: Nr.faixas CD | FK3: Nro. Paginas | FL3: Codigo ISBN | FM3: Rel. Prodepe | FN3: Tit.Original | FO3: Tipo Medic. | FP3: Alq. FUMACOP | FQ3: Prod. RN 944 | FR3: % Markup | FS3: Insp.Normal? | FT3: Grp.Nat.Rec. | FU3: Lingua Orig. | FV3: Nro.Edicao | FW3: Obs ISBN | FX3: Dt.Fim N. R. | FY3: Cod Cl Val | FZ3: Ativo | GA3: Peso Bruto | GB3: Fora PP ate? | GC3: Tipo Carga | GD3: Alm.Entr | GE3: Icms Pauta | GF3: Des SubFam | GG3: Valor Selo | GH3: SFamilia | GI3: Trunc ou Arr | GJ3: Prop ou Terc | GK3: Tamanho | GL3: Cód.Desc.Pro | GM3: Grau Dificul | GN3: Valor CIF | GO3: Atende Nec? | GP3: Vale Present | GQ3: Lote SBP | GR3: Tipo BN | GS3: Des SubFam | GT3: Admin. | GU3: Qt.Lim.Etiq. | GV3: Loc. Fisica | GW3: Perda Confor | GX3: SubSubFamil | GY3: Garantia? | GZ3: Tipo Vetor | HA3: Cod Familia | HB3: % Garantia | HC3: Estr. Origem | HD3: Cod. Norma | HE3: % Promocao | HF3: Descto Ger. | HG3: Cubagem | HH3: Cor | HI3: Integracao | HJ3: Cod. GTIN | HK3: Integ.Portal | HL3: Exp. Alcis | HM3: Vld Num Seri | HN3: Est.Min.Inve | HO3: Grp Mix Alvo | HP3: Peso MCP | HQ3: Desconto Rep | HR3: Ult. Calculo | HS3: Contr. Poten | HT3: Potencia Pad | HU3: Qtde. Acum. | HV3: Class. Produ | HW3: Qtd Inic Mes | HX3: Estoq Maximo | HY3: Ult Moe Comp | HZ3: Calcula PIS | IA3: Ult Vlr Comp | IB3: Calc. COFINS | IC3: Nivel Tabela | ID3: Calcula CSLL | IE3: C. Atividade | IF3: Qt. Unitizad | IG3: Dt.Lancament | IH3: Tipo Etiquet | II3: Dt.Descontin | IJ3: Cor Princip. | IK3: Cor Secund. | IL3: Icone APS | IM3: Atributo 1 | IN3: Atributo 2 | IO3: Atributo 3 | IP3: Regra Sequ. | IQ3: Requisitado | IR3: Bloqueado | IS3: Utiliza Selo | IT3: Qtde Venda | IU3: OK | IV3: Classe Selo | IW3: Tp. Reg | IX3: F.Ret.ISS | IY3: FEFO | IZ3: Est Cred IPI | JA3: Cred. ICMS | JB3: Código EAN | JC3: Desp.Import. | JD3: Enq. Selo | JE3: Aliq. FECOP | JF3: Al. FECOP ST | JG3: Calc. FECOP | JH3: Material Rec | JI3: Data Vigenc | JJ3: %Crd. Pres. | JK3: Aliq. FETHAB | JL3: Aliq. FACS | JM3: Aliq. FABOV | JN3: Tipo FETHAB | JO3: Ref. Base | JP3: Cod.Orig. | JQ3: Art65 RICMPR | JR3: Cal. CFEM | JS3: Sit. CFEM | JT3: Aliq. CFEMA | JU3: Mud.Reg.Trib | JV3: Cod.Cat83 | JW3: %Red.43080 | JX3: Tab. Nat. Re | JY3: Cod Nat Rece | JZ3: Chassi | KA3: Aliq FECP BA | KB3: Dif. CNAE | KC3: Prod. DCI | KD3: Nr. DCRE | KE3: Nr. DCR | KF3: Vl. DCRII | KG3: Coef. DCR | KH3: Pr.Inc.Leite | KI3: Ali.FECOP-RN | KJ3: Rg. Simp. MT | KK3: Cont ICMS-ST | KL3: Rastro Ativo | KM3: Ajust/Difer | KN3: Exe. Servico | KO3: Sit Trib | KP3: Carga Esp? | KQ3: Grupo - TI | KR3: Enq. IPI | KS3: CEST | KT3: Alq.FUNDESA | KU3: Alíq. IMA-MT | KV3: Alíq.FASE-MT | KW3: Porc. PRL | KX3: Aliq. FAMAD | KY3: Calc. TPDP | KZ3: Aliq. de Imp | LA3: Terc Un Med | LB3: Hr. Ult. Exp | LC3: ID.Hist. | LD3: Ident.Export | LE3: MD5 | LF3: Peso Uni Emb | LG3: Ap. p/ Prod. | LH3: Lote Maximo | LI3: Perc. Aponta
A4: 1 | B4: 1225 | C4: ELETROD. PVC FLEX CORRUGADO 20MM - 10 METROS | D4: PA | E4: MT | F4: 1 | G4: 160 | H4: 0 | I4: 3917.23.00 | L4: 0 | M4: 0 | N4: 0 | Q4: 516 | R4: 0 | S4: 0 | W4: Multiplicador | X4: 0 | Z4: 10 | AA4: 16.8993 | AB4: 3178 | AC4: 0.8119 | AD4: 44614 | AE4: 1.031 | AF4: 0.051 | AH4: 495 | AJ4: 1 | AK4: Dias | AL4: 15710 | AM4: 90 | AN4: 11501001 | AO4: 0 | AP4: 1001 | AT4: 1 | AU4: Direto | AV4: Nao | AW4: Normal | AX4: 0 | AY4: 43274 | BA4: 44638 | BB4: Nao utiliza | BD4: 0 | BF4: Sim | BG4: 42705 | BH4: 0 | BI4: 33 | BJ4: 0 | BK4: 0 | BM4: 42717 | BN4: 0 | BO4: 7897801317092 | BR4: Nao | BS4: Nao | BT4: Nao | BV4: 1 | BW4: 30 | BY4: 66 | CA4: 0 | CB4: Nao | CE4: Nao | CH4: Nao | CI4: KRONA | CK4: NÒo usa | CN4: SigaQuality | CP4: 1 | CQ4: 0 | CS4: 0 | CT4: 0 | CU4: 0 | CV4: Não | CW4: 0 | CX4: 0 | CY4: 0 | CZ4: 0 | DA4: 106 | DB4: 0 | DH4: 0 | DJ4: 0 | DL4: 0 | DN4: 0 | DO4: / / | DP4: 0 | DQ4: 7.6 | DS4: 0 | DU4: 1.65 | DW4: 0 | DY4: 0 | DZ4: 0 | EA4: 0 | EB4: 17897801317099 | EE4: 0 | EF4: 0 | EL4: 57897801317097 | EN4: Rolos | EO4: Sim | ET4: 0 | EV4: 0 | EY4: Moeda1 | EZ4: 0 | FA4: Nao | FB4: 0 | FC4: 0 | FD4: T | FE4: . . | FF4: 0 | FG4: . . | FH4: 27897801317096 | FJ4: 0 | FK4: 0 | FP4: 0 | FR4: 0 | FS4: Nao | FX4: / / | GA4: 0 | GB4: / / | GD4: 16 | GE4: 0 | GG4: 0 | GN4: 0 | GO4: Produzindo | GQ4: 0 | GU4: 4 | GY4: Não | HB4: 0 | HE4: 0 | HF4: 0 | HG4: 0.00802 | HK4: / / | HL4: S | HM4: 0 | HN4: 0 | HO4: 24 | HP4: 0.0497 | HQ4: 0 | HR4: / / | HT4: 0 | HU4: 0 | HW4: 0 | HX4: 9502 | HY4: 1 | IA4: 1.03 | IF4: 1600 | IG4: 42709 | IH4: Embalagem | II4: / / | IR4: Não | IT4: 0 | JE4: 0 | JF4: 0 | JI4: / / | JJ4: 0 | JK4: 0 | JL4: 0 | JM4: 0 | JT4: 0 | JU4: / / | JW4: 0 | KA4: 0 | KF4: 0 | KG4: 0 | KH4: 0 | KI4: 0 | KS4: 10.006.00 | KT4: 0 | KU4: 0 | KV4: 0 | KX4: 0 | KZ4: 0 | LF4: 0 | LH4: 42840 | LI4: 0
A5: 1 | B5: 12250 | C5: ADESIVO AQUATHERM 850G TIGRE | D5: AI | E5: UN | F5: 80 | G5: 46 | H5: 0 | I5: 3506.10.90 | L5: 0 | M5: 0 | N5: 0 | R5: 0 | S5: 0 | W5: Multiplicador | X5: 0 | Z5: 1 | AA5: 0 | AB5: 0 | AC5: 103.32 | AD5: 44635 | AE5: 113.85 | AF5: 0 | AH5: 0 | AJ5: 0 | AL5: 1 | AM5: 0 | AN5: 16601003 | AO5: 0 | AP5: 1000 | AT5: 0 | AU5: Direto | AW5: Normal | AX5: 0 | AY5: 40777 | BA5: 40777 | BB5: Nao utiliza | BD5: 0 | BF5: Nao | BG5: / / | BH5: 0 | BI5: 1 | BJ5: 0 | BK5: 0 | BM5: / / | BN5: 0 | BO5: 3457801100052 | BR5: Nao | BS5: Nao | BT5: Nao | BW5: 83 | CA5: 0 | CB5: N | CE5: Nao | CH5: Nao | CN5: SigaQuality | CO5: Nao | CP5: 1 | CQ5: 0 | CS5: 0 | CT5: 0 | CU5: 0 | CV5: Não | CW5: 0 | CX5: 0 | CY5: 0 | CZ5: 0 | DB5: 0 | DC5: Nao | DF5: Nao permite | DH5: 0 | DJ5: 0 | DK5: Normal | DL5: 0 | DN5: 0 | DO5: / / | DP5: 0 | DQ5: 0 | DS5: 0 | DU5: 0 | DW5: 0 | DX5: Nao | DY5: 0 | DZ5: 0 | EA5: 0 | ED5: Não | EE5: 0 | EF5: 0 | EQ5: Sim | ES5: Normal | ET5: 0 | EV5: 0 | EY5: Moeda1 | EZ5: 0 | FA5: Nao | FB5: 0 | FC5: 0 | FE5: . . | FF5: 0 | FG5: . . | FJ5: 0 | FK5: 0 | FP5: 0 | FR5: 0 | FS5: Nao | FX5: / / | FZ5: S | GA5: 0 | GB5: / / | GE5: 0 | GG5: 0 | GN5: 0 | GO5: Comprando | GQ5: 0 | GU5: 0 | GY5: Não | HB5: 0 | HE5: 0 | HF5: 0 | HG5: 0 | HK5: 44627 | HM5: 1a Unidade de Medida | HN5: 0 | HP5: 0 | HQ5: 0 | HR5: / / | HS5: Nao | HT5: 0 | HU5: 0 | HW5: 0 | HX5: 0 | HY5: 1 | HZ5: Não | IA5: 113.85 | IB5: Não | ID5: Não | IF5: 0 | IG5: / / | II5: / / | IR5: Não | IT5: 0 | IY5: Sim | IZ5: Nao | JC5: Nao | JE5: 0 | JF5: 0 | JI5: / / | JJ5: 0 | JK5: 0 | JL5: 0 | JM5: 0 | JQ5: Nao | JT5: 0 | JU5: / / | JW5: 0 | KA5: 0 | KF5: 0 | KG5: 0 | KH5: 0 | KI5: 0 | KS5: . . | KT5: 0 | KU5: 0 | KV5: 0 | KX5: 0 | KZ5: 0 | LF5: 0 | LH5: 0 | LI5: 0
A6: 1 | B6: 12251 | C6: ESQUADRIA EM ALUMINIO E VIDRO | D6: AI | E6: UN | F6: 80 | G6: 9000 | H6: 0 | I6: . . | L6: 0 | M6: 0 | N6: 0 | R6: 0 | S6: 0 | W6: Multiplicador | X6: 0 | Z6: 1 | AA6: 0 | AB6: 0 | AC6: 146.4074 | AD6: 40777 | AE6: 102.04 | AF6: 0 | AH6: 0 | AJ6: 0 | AL6: 0 | AM6: 0 | AN6: 16301003 | AO6: 0 | AP6: 1001 | AT6: 0 | AU6: Direto | AW6: Normal | AX6: 0 | AY6: 40777 | BA6: 40777 | BB6: Nao utiliza | BD6: 0 | BF6: Nao | BG6: / / | BH6: 0 | BI6: 1 | BJ6: 0 | BK6: 0 | BM6: / / | BN6: 0 | BR6: Nao | BS6: Nao | BT6: Nao | BW6: 83 | CA6: 0 | CB6: N | CE6: Nao | CH6: Nao | CN6: SigaQuality | CO6: Nao | CP6: 1 | CQ6: 0 | CS6: 0 | CT6: 0 | CU6: 0 | CV6: Não | CW6: 0 | CX6: 0 | CY6: 0 | CZ6: 0 | DB6: 0 | DC6: Nao | DF6: Nao permite | DH6: 0 | DJ6: 0 | DK6: Normal | DL6: 0 | DN6: 0 | DO6: / / | DP6: 0 | DQ6: 0 | DS6: 0 | DU6: 0 | DW6: 0 | DX6: Nao | DY6: 0 | DZ6: 0 | EA6: 0 | ED6: Não | EE6: 0 | EF6: 0 | EQ6: Sim | ES6: Normal | ET6: 0 | EV6: 0 | EY6: Moeda1 | EZ6: 0 | FA6: Nao | FB6: 0 | FC6: 0 | FE6: . . | FF6: 0 | FG6: . . | FJ6: 0 | FK6: 0 | FP6: 0 | FR6: 0 | FS6: Nao | FX6: / / | FZ6: S | GA6: 0 | GB6: / / | GE6: 0 | GG6: 0 | GN6: 0 | GO6: Comprando | GQ6: 0 | GU6: 0 | GY6: Não | HB6: 0 | HE6: 0 | HF6: 0 | HG6: 0 | HK6: / / | HM6: 1a Unidade de Medida | HN6: 0 | HP6: 0 | HQ6: 0 | HR6: / / | HS6: Nao | HT6: 0 | HU6: 0 | HW6: 0 | HX6: 0 | HY6: 0 | HZ6: Não | IA6: 0 | IB6: Não | ID6: Não | IF6: 0 | IG6: / / | II6: / / | IR6: Não | IT6: 0 | IY6: Sim | IZ6: Nao | JC6: Nao | JE6: 0 | JF6: 0 | JI6: / / | JJ6: 0 | JK6: 0 | JL6: 0 | JM6: 0 | JQ6: Nao | JT6: 0 | JU6: / / | JW6: 0 | KA6: 0 | KF6: 0 | KG6: 0 | KH6: 0 | KI6: 0 | KS6: . . | KT6: 0 | KU6: 0 | KV6: 0 | KX6: 0 | KZ6: 0 | LF6: 0 | LH6: 0 | LI6: 0
A7: 1 | B7: 12252 | C7: DISMA LONA POLIETILENO LARANJA 12X10M | D7: AI | E7: PC | F7: 80 | G7: 9000 | H7: 0 | I7: 6306.12.00 | L7: 0 | M7: 0 | N7: 0 | R7: 0 | S7: 0 | W7: Multiplicador | X7: 0 | Z7: 1 | AA7: 0 | AB7: 0 | AC7: 275 | AD7: 40778 | AE7: 293.65 | AF7: 0 | AH7: 0 | AJ7: 0 | AL7: 0 | AM7: 0 | AN7: 16601003 | AO7: 0 | AP7: 1000 | AT7: 0 | AU7: Direto | AW7: Normal | AX7: 0 | AY7: 40778 | BA7: 40778 | BB7: Nao utiliza | BD7: 0 | BF7: Nao | BG7: / / | BH7: 0 | BI7: 1 | BJ7: 0 | BK7: 0 | BM7: / / | BN7: 0 | BR7: Nao | BS7: Nao | BT7: Nao | BW7: 83 | CA7: 0 | CB7: N | CE7: Nao | CH7: Nao | CN7: SigaQuality | CO7: Nao | CP7: 1 | CQ7: 0 | CS7: 0 | CT7: 0 | CU7: 0 | CV7: Não | CW7: 0 | CX7: 0 | CY7: 0 | CZ7: 0 | DB7: 0 | DC7: Nao | DF7: Nao permite | DH7: 0 | DJ7: 0 | DK7: Normal | DL7: 0 | DN7: 0 | DO7: / / | DP7: 0 | DQ7: 0 | DS7: 0 | DU7: 0 | DW7: 0 | DX7: Nao | DY7: 0 | DZ7: 0 | EA7: 0 | ED7: Não | EE7: 0 | EF7: 0 | EQ7: Sim | ES7: Normal | ET7: 0 | EV7: 0 | EY7: Moeda1 | EZ7: 0 | FA7: Nao | FB7: 0 | FC7: 0 | FE7: . . | FF7: 0 | FG7: . . | FJ7: 0 | FK7: 0 | FP7: 0 | FR7: 0 | FS7: Nao | FX7: / / | FZ7: S | GA7: 0 | GB7: / / | GE7: 0 | GG7: 0 | GN7: 0 | GO7: Comprando | GQ7: 0 | GU7: 0 | GY7: Não | HB7: 0 | HE7: 0 | HF7: 0 | HG7: 0 | HK7: / / | HM7: 1a Unidade de Medida | HN7: 0 | HP7: 0 | HQ7: 0 | HR7: / / | HS7: Nao | HT7: 0 | HU7: 0 | HW7: 0 | HX7: 0 | HY7: 0 | HZ7: Não | IA7: 0 | IB7: Não | ID7: Não | IF7: 0 | IG7: / / | II7: / / | IR7: Não | IT7: 0 | IY7: Sim | IZ7: Nao | JC7: Nao | JE7: 0 | JF7: 0 | JI7: / / | JJ7: 0 | JK7: 0 | JL7: 0 | JM7: 0 | JQ7: Nao | JT7: 0 | JU7: / / | JW7: 0 | KA7: 0 | KF7: 0 | KG7: 0 | KH7: 0 | KI7: 0 | KS7: . . | KT7: 0 | KU7: 0 | KV7: 0 | KX7: 0 | KZ7: 0 | LF7: 0 | LH7: 0 | LI7: 0
A8: 1 | B8: 12253 | C8: FELTRO FACEFELT BR 1.4 2300X120X6,35 | D8: AI | E8: PC | F8: 80 | G8: 9000 | H8: 0 | I8: . . | L8: 0 | M8: 0 | N8: 0 | R8: 0 | S8: 0 | W8: Multiplicador | X8: 0 | Z8: 1 | AA8: 0 | AB8: 0 | AC8: 0 | AD8: 40778 | AE8: 1 | AF8: 0 | AH8: 0 | AJ8: 0 | AL8: 0 | AM8: 0 | AN8: 16601001 | AO8: 0 | AP8: 1000 | AT8: 0 | AU8: Direto | AW8: Normal | AX8: 0 | AY8: 40778 | BA8: 40778 | BB8: Nao utiliza | BD8: 0 | BF8: Nao | BG8: / / | BH8: 0 | BI8: 1 | BJ8: 0 | BK8: 0 | BM8: / / | BN8: 0 | BR8: Nao | BS8: Nao | BT8: Nao | BW8: 83 | CA8: 0 | CB8: N | CE8: Nao | CH8: Nao | CN8: SigaQuality | CO8: Nao | CP8: 1 | CQ8: 0 | CS8: 0 | CT8: 0 | CU8: 0 | CV8: Não | CW8: 0 | CX8: 0 | CY8: 0 | CZ8: 0 | DB8: 0 | DC8: Nao | DF8: Nao permite | DH8: 0 | DJ8: 0 | DK8: Normal | DL8: 0 | DN8: 0 | DO8: / / | DP8: 0 | DQ8: 0 | DS8: 0 | DU8: 0 | DW8: 0 | DX8: Nao | DY8: 0 | DZ8: 0 | EA8: 0 | ED8: Não | EE8: 0 | EF8: 0 | EQ8: Sim | ES8: Normal | ET8: 0 | EV8: 0 | EY8: Moeda1 | EZ8: 0 | FA8: Nao | FB8: 0 | FC8: 0 | FE8: . . | FF8: 0 | FG8: . . | FJ8: 0 | FK8: 0 | FP8: 0 | FR8: 0 | FS8: Nao | FX8: / / | FZ8: S | GA8: 0 | GB8: / / | GE8: 0 | GG8: 0 | GN8: 0 | GO8: Comprando | GQ8: 0 | GU8: 0 | GY8: Não | HB8: 0 | HE8: 0 | HF8: 0 | HG8: 0 | HK8: / / | HM8: 1a Unidade de Medida | HN8: 0 | HP8: 0 | HQ8: 0 | HR8: / / | HS8: Nao | HT8: 0 | HU8: 0 | HW8: 0 | HX8: 0 | HY8: 0 | HZ8: Não | IA8: 0 | IB8: Não | ID8: Não | IF8: 0 | IG8: / / | II8: / / | IR8: Não | IT8: 0 | IY8: Sim | IZ8: Nao | JC8: Nao | JE8: 0 | JF8: 0 | JI8: / / | JJ8: 0 | JK8: 0 | JL8: 0 | JM8: 0 | JQ8: Nao | JT8: 0 | JU8: / / | JW8: 0 | KA8: 0 | KF8: 0 | KG8: 0 | KH8: 0 | KI8: 0 | KS8: . . | KT8: 0 | KU8: 0 | KV8: 0 | KX8: 0 | KZ8: 0 | LF8: 0 | LH8: 0 | LI8: 0
A9: 1 | B9: 12254 | C9: FELTRO FACEFELT BR 1,4 19500X1200X63,5 | D9: AI | E9: PC | F9: 80 | G9: 9000 | H9: 0 | I9: . . | L9: 0 | M9: 0 | N9: 0 | R9: 0 | S9: 0 | W9: Multiplicador | X9: 0 | Z9: 1 | AA9: 0 | AB9: 0 | AC9: 0 | AD9: 40778 | AE9: 1 | AF9: 0 | AH9: 0 | AJ9: 0 | AL9: 0 | AM9: 0 | AN9: 16601001 | AO9: 0 | AP9: 1000 | AT9: 0 | AU9: Direto | AW9: Normal | AX9: 0 | AY9: 40778 | BA9: 40778 | BB9: Nao utiliza | BD9: 0 | BF9: Nao | BG9: / / | BH9: 0 | BI9: 1 | BJ9: 0 | BK9: 0 | BM9: / / | BN9: 0 | BR9: Nao | BS9: Nao | BT9: Nao | BW9: 83 | CA9: 0 | CB9: N | CE9: Nao | CH9: Nao | CN9: SigaQuality | CO9: Nao | CP9: 1 | CQ9: 0 | CS9: 0 | CT9: 0 | CU9: 0 | CV9: Não | CW9: 0 | CX9: 0 | CY9: 0 | CZ9: 0 | DB9: 0 | DC9: Nao | DF9: Nao permite | DH9: 0 | DJ9: 0 | DK9: Normal | DL9: 0 | DN9: 0 | DO9: / / | DP9: 0 | DQ9: 0 | DS9: 0 | DU9: 0 | DW9: 0 | DX9: Nao | DY9: 0 | DZ9: 0 | EA9: 0 | ED9: Não | EE9: 0 | EF9: 0 | EQ9: Sim | ES9: Normal | ET9: 0 | EV9: 0 | EY9: Moeda1 | EZ9: 0 | FA9: Nao | FB9: 0 | FC9: 0 | FE9: . . | FF9: 0 | FG9: . . | FJ9: 0 | FK9: 0 | FP9: 0 | FR9: 0 | FS9: Nao | FX9: / / | FZ9: S | GA9: 0 | GB9: / / | GE9: 0 | GG9: 0 | GN9: 0 | GO9: Comprando | GQ9: 0 | GU9: 0 | GY9: Não | HB9: 0 | HE9: 0 | HF9: 0 | HG9: 0 | HK9: / / | HM9: 1a Unidade de Medida | HN9: 0 | HP9: 0 | HQ9: 0 | HR9: / / | HS9: Nao | HT9: 0 | HU9: 0 | HW9: 0 | HX9: 0 | HY9: 0 | HZ9: Não | IA9: 0 | IB9: Não | ID9: Não | IF9: 0 | IG9: / / | II9: / / | IR9: Não | IT9: 0 | IY9: Sim | IZ9: Nao | JC9: Nao | JE9: 0 | JF9: 0 | JI9: / / | JJ9: 0 | JK9: 0 | JL9: 0 | JM9: 0 | JQ9: Nao | JT9: 0 | JU9: / / | JW9: 0 | KA9: 0 | KF9: 0 | KG9: 0 | KH9: 0 | KI9: 0 | KS9: . . | KT9: 0 | KU9: 0 | KV9: 0 | KX9: 0 | KZ9: 0 | LF9: 0 | LH9: 0 | LI9: 0
A10: 1 | B10: 12255 | C10: CR 80.000MM KRONA | D10: AI | E10: PC | F10: 80 | G10: 9000 | H10: 0 | I10: . . | L10: 0 | M10: 0 | N10: 0 | R10: 0 | S10: 0 | W10: Multiplicador | X10: 0 | Z10: 1 | AA10: 0 | AB10: 0 | AC10: 58600 | AD10: 40778 | AE10: 1 | AF10: 0 | AH10: 0 | AJ10: 0 | AL10: 0 | AM10: 0 | AN10: 16601001 | AO10: 0 | AP10: 1000 | AT10: 0 | AU10: Direto | AW10: Normal | AX10: 0 | AY10: 40778 | BA10: 40778 | BB10: Nao utiliza | BD10: 0 | BF10: Nao | BG10: / / | BH10: 0 | BI10: 1 | BJ10: 0 | BK10: 0 | BM10: / / | BN10: 0 | BR10: Nao | BS10: Nao | BT10: Nao | BW10: 83 | CA10: 0 | CB10: N | CE10: Nao | CH10: Nao | CN10: SigaQuality | CO10: Nao | CP10: 1 | CQ10: 0 | CS10: 0 | CT10: 0 | CU10: 0 | CV10: Não | CW10: 0 | CX10: 0 | CY10: 0 | CZ10: 0 | DB10: 0 | DC10: Nao | DF10: Nao permite | DH10: 0 | DJ10: 0 | DK10: Normal | DL10: 0 | DN10: 0 | DO10: / / | DP10: 0 | DQ10: 0 | DS10: 0 | DU10: 0 | DW10: 0 | DX10: Nao | DY10: 0 | DZ10: 0 | EA10: 0 | ED10: Não | EE10: 0 | EF10: 0 | EQ10: Sim | ES10: Normal | ET10: 0 | EV10: 0 | EY10: Moeda1 | EZ10: 0 | FA10: Nao | FB10: 0 | FC10: 0 | FE10: . . | FF10: 0 | FG10: . . | FJ10: 0 | FK10: 0 | FP10: 0 | FR10: 0 | FS10: Nao | FX10: / / | FZ10: S | GA10: 0 | GB10: / / | GE10: 0 | GG10: 0 | GN10: 0 | GO10: Comprando | GQ10: 0 | GU10: 0 | GY10: Não | HB10: 0 | HE10: 0 | HF10: 0 | HG10: 0 | HK10: / / | HM10: 1a Unidade de Medida | HN10: 0 | HP10: 0 | HQ10: 0 | HR10: / / | HS10: Nao | HT10: 0 | HU10: 0 | HW10: 0 | HX10: 0 | HY10: 0 | HZ10: Não | IA10: 0 | IB10: Não | ID10: Não | IF10: 0 | IG10: / / | II10: / / | IR10: Não | IT10: 0 | IY10: Sim | IZ10: Nao | JC10: Nao | JE10: 0 | JF10: 0 | JI10: / / | JJ10: 0 | JK10: 0 | JL10: 0 | JM10: 0 | JQ10: Nao | JT10: 0 | JU10: / / | JW10: 0 | KA10: 0 | KF10: 0 | KG10: 0 | KH10: 0 | KI10: 0 | KS10: . . | KT10: 0 | KU10: 0 | KV10: 0 | KX10: 0 | KZ10: 0 | LF10: 0 | LH10: 0 | LI10: 0
A11: 1 | B11: 12256 | C11: BOMBA MULTIEST MONOBL 03,00 CV | D11: AI | E11: PC | F11: 80 | G11: 9000 | H11: 0 | I11: 8413.70.80 | L11: 0 | M11: 0 | N11: 0 | R11: 0 | S11: 0 | W11: Multiplicador | X11: 0 | Z11: 1 | AA11: 0 | AB11: 0 | AC11: 0 | AD11: 40779 | AE11: 1599.4677 | AF11: 0 | AH11: 0 | AJ11: 0 | AL11: 0 | AM11: 0 | AN11: 16601001 | AO11: 0 | AP11: 1000 | AT11: 0 | AU11: Direto | AW11: Normal | AX11: 0 | AY11: 40778 | BA11: 40778 | BB11: Nao utiliza | BD11: 0 | BF11: Nao | BG11: / / | BH11: 0 | BI11: 1 | BJ11: 0 | BK11: 0 | BM11: 43635 | BN11: 0 | BR11: Nao | BS11: Nao | BT11: Nao | BW11: 83 | CA11: 0 | CB11: N | CE11: Nao | CH11: Nao | CN11: SigaQuality | CO11: Nao | CP11: 1 | CQ11: 0 | CS11: 0 | CT11: 0 | CU11: 0 | CV11: Não | CW11: 0 | CX11: 0 | CY11: 0 | CZ11: 0 | DB11: 0 | DC11: Nao | DF11: Nao permite | DH11: 0 | DJ11: 0 | DK11: Normal | DL11: 0 | DN11: 0 | DO11: / / | DP11: 0 | DQ11: 0 | DS11: 0 | DU11: 0 | DW11: 0 | DX11: Nao | DY11: 0 | DZ11: 0 | EA11: 0 | ED11: Não | EE11: 0 | EF11: 0 | EQ11: Sim | ES11: Normal | ET11: 0 | EV11: 0 | EY11: Moeda1 | EZ11: 0 | FA11: Nao | FB11: 0 | FC11: 0 | FE11: . . | FF11: 0 | FG11: . . | FJ11: 0 | FK11: 0 | FP11: 0 | FR11: 0 | FS11: Nao | FX11: / / | FZ11: S | GA11: 0 | GB11: / / | GE11: 0 | GG11: 0 | GN11: 0 | GO11: Comprando | GQ11: 0 | GU11: 0 | GY11: Não | HB11: 0 | HE11: 0 | HF11: 0 | HG11: 0 | HK11: / / | HM11: 1a Unidade de Medida | HN11: 0 | HP11: 0 | HQ11: 0 | HR11: / / | HS11: Nao | HT11: 0 | HU11: 0 | HW11: 0 | HX11: 0 | HY11: 0 | HZ11: Não | IA11: 0 | IB11: Não | ID11: Não | IF11: 0 | IG11: / / | II11: / / | IR11: Não | IT11: 0 | IY11: Sim | IZ11: Nao | JC11: Nao | JE11: 0 | JF11: 0 | JI11: / / | JJ11: 0 | JK11: 0 | JL11: 0 | JM11: 0 | JQ11: Nao | JT11: 0 | JU11: / / | JW11: 0 | KA11: 0 | KF11: 0 | KG11: 0 | KH11: 0 | KI11: 0 | KS11: . . | KT11: 0 | KU11: 0 | KV11: 0 | KX11: 0 | KZ11: 0 | LF11: 0 | LH11: 0 | LI11: 0
A12: 1 | B12: 12257 | C12: BOMBA MULTIEST MONOBL 02,00 CV | D12: AI | E12: PC | F12: 80 | G12: 9000 | H12: 0 | I12: 8413.70.80 | L12: 0 | M12: 0 | N12: 0 | R12: 0 | S12: 0 | W12: Multiplicador | X12: 0 | Z12: 1 | AA12: 0 | AB12: 0 | AC12: 1084.975 | AD12: 40779 | AE12: 1189.6584 | AF12: 0 | AH12: 0 | AJ12: 0 | AL12: 0 | AM12: 0 | AN12: 16601001 | AO12: 0 | AP12: 1000 | AT12: 0 | AU12: Direto | AW12: Normal | AX12: 0 | AY12: 40778 | BA12: 40778 | BB12: Nao utiliza | BD12: 0 | BF12: Nao | BG12: / / | BH12: 0 | BI12: 1 | BJ12: 0 | BK12: 0 | BM12: / / | BN12: 0 | BR12: Nao | BS12: Nao | BT12: Nao | BW12: 83 | CA12: 0 | CB12: N | CE12: Nao | CH12: Nao | CN12: SigaQuality | CO12: Nao | CP12: 1 | CQ12: 0 | CS12: 0 | CT12: 0 | CU12: 0 | CV12: Não | CW12: 0 | CX12: 0 | CY12: 0 | CZ12: 0 | DB12: 0 | DC12: Nao | DF12: Nao permite | DH12: 0 | DJ12: 0 | DK12: Normal | DL12: 0 | DN12: 0 | DO12: / / | DP12: 0 | DQ12: 0 | DS12: 0 | DU12: 0 | DW12: 0 | DX12: Nao | DY12: 0 | DZ12: 0 | EA12: 0 | ED12: Não | EE12: 0 | EF12: 0 | EQ12: Sim | ES12: Normal | ET12: 0 | EV12: 0 | EY12: Moeda1 | EZ12: 0 | FA12: Nao | FB12: 0 | FC12: 0 | FE12: . . | FF12: 0 | FG12: . . | FJ12: 0 | FK12: 0 | FP12: 0 | FR12: 0 | FS12: Nao | FX12: / / | FZ12: S | GA12: 0 | GB12: / / | GE12: 0 | GG12: 0 | GN12: 0 | GO12: Comprando | GQ12: 0 | GU12: 0 | GY12: Não | HB12: 0 | HE12: 0 | HF12: 0 | HG12: 0 | HK12: / / | HM12: 1a Unidade de Medida | HN12: 0 | HP12: 0 | HQ12: 0 | HR12: / / | HS12: Nao | HT12: 0 | HU12: 0 | HW12: 0 | HX12: 0 | HY12: 0 | HZ12: Não | IA12: 0 | IB12: Não | ID12: Não | IF12: 0 | IG12: / / | II12: / / | IR12: Não | IT12: 0 | IY12: Sim | IZ12: Nao | JC12: Nao | JE12: 0 | JF12: 0 | JI12: / / | JJ12: 0 | JK12: 0 | JL12: 0 | JM12: 0 | JQ12: Nao | JT12: 0 | JU12: / / | JW12: 0 | KA12: 0 | KF12: 0 | KG12: 0 | KH12: 0 | KI12: 0 | KS12: . . | KT12: 0 | KU12: 0 | KV12: 0 | KX12: 0 | KZ12: 0 | LF12: 0 | LH12: 0 | LI12: 0
A13: 1 | B13: 12258 | C13: TUBO GALV 4 PAREDES 3,35MM C/ ROSCA | D13: AI | E13: UN | F13: 80 | G13: 9000 | H13: 0 | I13: . . | L13: 0 | M13: 0 | N13: 0 | R13: 0 | S13: 0 | W13: Multiplicador | X13: 0 | Z13: 1 | AA13: 0 | AB13: 0 | AC13: 0 | AD13: 40779 | AE13: 330 | AF13: 0 | AH13: 0 | AJ13: 0 | AL13: 0 | AM13: 0 | AN13: 16601003 | AO13: 0 | AP13: 1000 | AT13: 0 | AU13: Direto | AW13: Normal | AX13: 0 | AY13: 40779 | BA13: 40779 | BB13: Nao utiliza | BD13: 0 | BF13: Nao | BG13: / / | BH13: 0 | BI13: 1 | BJ13: 0 | BK13: 0 | BM13: / / | BN13: 0 | BR13: Nao | BS13: Nao | BT13: Nao | BW13: 83 | CA13: 0 | CB13: N | CE13: Nao | CH13: Nao | CN13: SigaQuality | CO13: Nao | CP13: 1 | CQ13: 0 | CS13: 0 | CT13: 0 | CU13: 0 | CV13: Não | CW13: 0 | CX13: 0 | CY13: 0 | CZ13: 0 | DB13: 0 | DC13: Nao | DF13: Nao permite | DH13: 0 | DJ13: 0 | DK13: Normal | DL13: 0 | DN13: 0 | DO13: / / | DP13: 0 | DQ13: 0 | DS13: 0 | DU13: 0 | DW13: 0 | DX13: Nao | DY13: 0 | DZ13: 0 | EA13: 0 | ED13: Não | EE13: 0 | EF13: 0 | EQ13: Sim | ES13: Normal | ET13: 0 | EV13: 0 | EY13: Moeda1 | EZ13: 0 | FA13: Nao | FB13: 0 | FC13: 0 | FE13: . . | FF13: 0 | FG13: . . | FJ13: 0 | FK13: 0 | FP13: 0 | FR13: 0 | FS13: Nao | FX13: / / | FZ13: S | GA13: 0 | GB13: / / | GE13: 0 | GG13: 0 | GN13: 0 | GO13: Comprando | GQ13: 0 | GU13: 0 | GY13: Não | HB13: 0 | HE13: 0 | HF13: 0 | HG13: 0 | HK13: / / | HM13: 1a Unidade de Medida | HN13: 0 | HP13: 0 | HQ13: 0 | HR13: / / | HS13: Nao | HT13: 0 | HU13: 0 | HW13: 0 | HX13: 0 | HY13: 0 | HZ13: Não | IA13: 0 | IB13: Não | ID13: Não | IF13: 0 | IG13: / / | II13: / / | IR13: Não | IT13: 0 | IY13: Sim | IZ13: Nao | JC13: Nao | JE13: 0 | JF13: 0 | JI13: / / | JJ13: 0 | JK13: 0 | JL13: 0 | JM13: 0 | JQ13: Nao | JT13: 0 | JU13: / / | JW13: 0 | KA13: 0 | KF13: 0 | KG13: 0 | KH13: 0 | KI13: 0 | KS13: . . | KT13: 0 | KU13: 0 | KV13: 0 | KX13: 0 | KZ13: 0 | LF13: 0 | LH13: 0 | LI13: 0
A14: 1 | B14: 12259 | C14: ELETRIFICACAO FESTOON FORCA/COMANDO 29M | D14: AI | E14: UN | F14: 80 | G14: 9000 | H14: 0 | I14: 8431.10.90 | L14: 0 | M14: 0 | N14: 0 | R14: 0 | S14: 0 | W14: Multiplicador | X14: 0 | Z14: 1 | AA14: 0 | AB14: 0 | AC14: 8350 | AD14: / / | AE14: 0 | AF14: 0 | AH14: 0 | AJ14: 0 | AL14: 0 | AM14: 0 | AN14: 16601001 | AO14: 0 | AP14: 1000 | AT14: 0 | AU14: Direto | AW14: Normal | AX14: 0 | AY14: 40779 | BA14: 40779 | BB14: Nao utiliza | BD14: 0 | BF14: Nao | BG14: / / | BH14: 0 | BI14: 1 | BJ14: 0 | BK14: 0 | BM14: / / | BN14: 0 | BR14: Nao | BS14: Nao | BT14: Nao | BW14: 83 | CA14: 0 | CB14: N | CE14: Nao | CH14: Nao | CN14: SigaQuality | CO14: Nao | CP14: 1 | CQ14: 0 | CS14: 0 | CT14: 0 | CU14: 0 | CV14: Não | CW14: 0 | CX14: 0 | CY14: 0 | CZ14: 0 | DB14: 0 | DC14: Nao | DF14: Nao permite | DH14: 0 | DJ14: 0 | DK14: Normal | DL14: 0 | DN14: 0 | DO14: / / | DP14: 0 | DQ14: 0 | DS14: 0 | DU14: 0 | DW14: 0 | DX14: Nao | DY14: 0 | DZ14: 0 | EA14: 0 | ED14: Não | EE14: 0 | EF14: 0 | EQ14: Sim | ES14: Normal | ET14: 0 | EV14: 0 | EY14: Moeda1 | EZ14: 0 | FA14: Nao | FB14: 0 | FC14: 0 | FE14: . . | FF14: 0 | FG14: . . | FJ14: 0 | FK14: 0 | FP14: 0 | FR14: 0 | FS14: Nao | FX14: / / | FZ14: S | GA14: 0 | GB14: / / | GE14: 0 | GG14: 0 | GN14: 0 | GO14: Comprando | GQ14: 0 | GU14: 0 | GY14: Não | HB14: 0 | HE14: 0 | HF14: 0 | HG14: 0 | HK14: / / | HM14: 1a Unidade de Medida | HN14: 0 | HP14: 0 | HQ14: 0 | HR14: / / | HS14: Nao | HT14: 0 | HU14: 0 | HW14: 0 | HX14: 0 | HY14: 0 | HZ14: Não | IA14: 0 | IB14: Não | ID14: Não | IF14: 0 | IG14: / / | II14: / / | IR14: Não | IT14: 0 | IY14: Sim | IZ14: Nao | JC14: Nao | JE14: 0 | JF14: 0 | JI14: / / | JJ14: 0 | JK14: 0 | JL14: 0 | JM14: 0 | JQ14: Nao | JT14: 0 | JU14: / / | JW14: 0 | KA14: 0 | KF14: 0 | KG14: 0 | KH14: 0 | KI14: 0 | KS14: . . | KT14: 0 | KU14: 0 | KV14: 0 | KX14: 0 | KZ14: 0 | LF14: 0 | LH14: 0 | LI14: 0
A15: 1 | B15: 1226 | C15: ELETROD. PVC FLEX CORRUGADO 20MM - 25 METROS | D15: PA | E15: MT | F15: 1 | G15: 160 | H15: 0 | I15: 3917.23.00 | L15: 0 | M15: 0 | N15: 0 | Q15: 516 | R15: 0 | S15: 0 | W15: Multiplicador | X15: 0 | Z15: 25 | AA15: 16.1443 | AB15: 2281 | AC15: 0.5894 | AD15: 44664 | AE15: 0.86 | AF15: 0.051 | AH15: 256 | AJ15: 1 | AK15: Dias | AL15: 11875 | AM15: 212 | AN15: 11501001 | AO15: 0 | AP15: 1001 | AT15: 1 | AU15: Direto | AV15: Nao | AW15: Normal | AX15: 5 | AY15: 43274 | BA15: 44659 | BB15: Nao utiliza | BD15: 0 | BF15: Sim | BG15: 42705 | BH15: 0 | BI15: 33 | BJ15: 0 | BK15: 0 | BM15: 42723 | BN15: 0 | BO15: 7897801317108 | BR15: Nao | BS15: Nao | BT15: Nao | BV15: 1 | BW15: 30 | BY15: 66 | CA15: 0 | CB15: Nao | CE15: Nao | CH15: Nao | CI15: KRONA | CK15: NÒo usa | CN15: SigaQuality | CP15: 1 | CQ15: 0 | CS15: 0 | CT15: 0 | CU15: 0 | CV15: Não | CW15: 0 | CX15: 0 | CY15: 0 | CZ15: 0 | DA15: 35 | DB15: 0 | DH15: 0 | DJ15: 0 | DL15: 0 | DN15: 0 | DO15: / / | DP15: 0 | DQ15: 7.6 | DS15: 0 | DU15: 1.65 | DW15: 0 | DY15: 0 | DZ15: 0 | EA15: 0 | EB15: 17897801317105 | EE15: 0 | EF15: 0 | EL15: 57897801317103 | EN15: Rolos | EO15: Sim | ET15: 0 | EV15: 0 | EY15: Moeda1 | EZ15: 0 | FA15: Nao | FB15: 0 | FC15: 0 | FD15: T | FE15: . . | FF15: 0 | FG15: . . | FH15: 27897801317102 | FJ15: 0 | FK15: 0 | FP15: 0 | FR15: 0 | FS15: Nao | FX15: / / | GA15: 0 | GB15: / / | GD15: 16 | GE15: 0 | GG15: 0 | GN15: 0 | GO15: Produzindo | GQ15: 0 | GU15: 4 | GY15: Não | HB15: 0 | HE15: 0 | HF15: 0 | HG15: 0.01547 | HK15: / / | HL15: S | HM15: 0 | HN15: 0 | HO15: 24 | HP15: 0.0497 | HQ15: 0 | HR15: / / | HT15: 0 | HU15: 0 | HW15: 0 | HX15: 7056 | HY15: 1 | IA15: 0.86 | IF15: 1800 | IG15: 42709 | IH15: Embalagem | II15: / / | IR15: Não | IT15: 0 | JE15: 0 | JF15: 0 | JI15: / / | JJ15: 0 | JK15: 0 | JL15: 0 | JM15: 0 | JT15: 0 | JU15: / / | JW15: 0 | KA15: 0 | KF15: 0 | KG15: 0 | KH15: 0 | KI15: 0 | KS15: 10.006.00 | KT15: 0 | KU15: 0 | KV15: 0 | KX15: 0 | KZ15: 0 | LF15: 0 | LH15: 223104 | LI15: 0
A16: 1 | B16: 12260 | C16: ELETRIFICACAO FESTOON FORCA/COMANDO 24,2M | D16: AI | E16: UN | F16: 80 | G16: 9000 | H16: 0 | I16: 8431.10.90 | L16: 0 | M16: 0 | N16: 0 | R16: 0 | S16: 0 | W16: Multiplicador | X16: 0 | Z16: 1 | AA16: 0 | AB16: 0 | AC16: 12478 | AD16: / / | AE16: 0 | AF16: 0 | AH16: 0 | AJ16: 0 | AL16: 0 | AM16: 0 | AN16: 16601001 | AO16: 0 | AP16: 1000 | AT16: 0 | AU16: Direto | AW16: Normal | AX16: 0 | AY16: 40779 | BA16: 40779 | BB16: Nao utiliza | BD16: 0 | BF16: Nao | BG16: / / | BH16: 0 | BI16: 1 | BJ16: 0 | BK16: 0 | BM16: / / | BN16: 0 | BR16: Nao | BS16: Nao | BT16: Nao | BW16: 83 | CA16: 0 | CB16: N | CE16: Nao | CH16: Nao | CN16: SigaQuality | CO16: Nao | CP16: 1 | CQ16: 0 | CS16: 0 | CT16: 0 | CU16: 0 | CV16: Não | CW16: 0 | CX16: 0 | CY16: 0 | CZ16: 0 | DB16: 0 | DC16: Nao | DF16: Nao permite | DH16: 0 | DJ16: 0 | DK16: Normal | DL16: 0 | DN16: 0 | DO16: / / | DP16: 0 | DQ16: 0 | DS16: 0 | DU16: 0 | DW16: 0 | DX16: Nao | DY16: 0 | DZ16: 0 | EA16: 0 | ED16: Não | EE16: 0 | EF16: 0 | EQ16: Sim | ES16: Normal | ET16: 0 | EV16: 0 | EY16: Moeda1 | EZ16: 0 | FA16: Nao | FB16: 0 | FC16: 0 | FE16: . . | FF16: 0 | FG16: . . | FJ16: 0 | FK16: 0 | FP16: 0 | FR16: 0 | FS16: Nao | FX16: / / | FZ16: S | GA16: 0 | GB16: / / | GE16: 0 | GG16: 0 | GN16: 0 | GO16: Comprando | GQ16: 0 | GU16: 0 | GY16: Não | HB16: 0 | HE16: 0 | HF16: 0 | HG16: 0 | HK16: / / | HM16: 1a Unidade de Medida | HN16: 0 | HP16: 0 | HQ16: 0 | HR16: / / | HS16: Nao | HT16: 0 | HU16: 0 | HW16: 0 | HX16: 0 | HY16: 0 | HZ16: Não | IA16: 0 | IB16: Não | ID16: Não | IF16: 0 | IG16: / / | II16: / / | IR16: Não | IT16: 0 | IY16: Sim | IZ16: Nao | JC16: Nao | JE16: 0 | JF16: 0 | JI16: / / | JJ16: 0 | JK16: 0 | JL16: 0 | JM16: 0 | JQ16: Nao | JT16: 0 | JU16: / / | JW16: 0 | KA16: 0 | KF16: 0 | KG16: 0 | KH16: 0 | KI16: 0 | KS16: . . | KT16: 0 | KU16: 0 | KV16: 0 | KX16: 0 | KZ16: 0 | LF16: 0 | LH16: 0 | LI16: 0
A17: 1 | B17: 12261 | C17: LICENCA APPLIANCE SONICWALL NSA2400 3 ANOS+DP | D17: IM | E17: UN | F17: 80 | G17: 8800 | H17: 0 | I17: . . | L17: 0 | M17: 0 | N17: 0 | R17: 0 | S17: 0 | W17: Multiplicador | X17: 0 | Z17: 1 | AA17: 0 | AB17: 0 | AC17: 18682.44 | AD17: 40785 | AE17: 18682.44 | AF17: 0 | AH17: 0 | AJ17: 0 | AL17: 0 | AM17: 0 | AN17: 16301013 | AO17: 0 | AP17: 2720 | AT17: 0 | AU17: Direto | AW17: Normal | AX17: 0 | AY17: 40780 | BA17: 40780 | BB17: Nao utiliza | BD17: 0 | BF17: Nao | BG17: / / | BH17: 0 | BI17: 1 | BJ17: 0 | BK17: 0 | BM17: / / | BN17: 0 | BR17: Nao | BS17: Nao | BT17: Nao | BW17: 70 | CA17: 0 | CB17: N | CE17: Nao | CH17: Nao | CN17: SigaQuality | CO17: Nao | CP17: 1 | CQ17: 0 | CS17: 0 | CT17: 0 | CU17: 0 | CV17: Não | CW17: 0 | CX17: 0 | CY17: 0 | CZ17: 0 | DB17: 0 | DC17: Nao | DF17: Nao permite | DH17: 0 | DJ17: 0 | DK17: Normal | DL17: 0 | DN17: 0 | DO17: / / | DP17: 0 | DQ17: 0 | DS17: 0 | DU17: 0 | DW17: 0 | DX17: Nao | DY17: 0 | DZ17: 0 | EA17: 0 | ED17: Não | EE17: 0 | EF17: 0 | EQ17: Sim | ES17: Normal | ET17: 0 | EV17: 0 | EY17: Moeda1 | EZ17: 0 | FA17: Nao | FB17: 0 | FC17: 0 | FE17: . . | FF17: 0 | FG17: . . | FJ17: 0 | FK17: 0 | FP17: 0 | FR17: 0 | FS17: Nao | FX17: / / | FZ17: S | GA17: 0 | GB17: / / | GE17: 0 | GG17: 0 | GN17: 0 | GO17: Comprando | GQ17: 0 | GU17: 0 | GY17: Não | HB17: 0 | HE17: 0 | HF17: 0 | HG17: 0 | HK17: / / | HM17: 1a Unidade de Medida | HN17: 0 | HP17: 0 | HQ17: 0 | HR17: / / | HS17: Nao | HT17: 0 | HU17: 0 | HW17: 0 | HX17: 0 | HY17: 0 | HZ17: Não | IA17: 0 | IB17: Não | ID17: Não | IF17: 0 | IG17: / / | II17: / / | IR17: Não | IT17: 0 | IY17: Sim | IZ17: Nao | JC17: Nao | JE17: 0 | JF17: 0 | JI17: / / | JJ17: 0 | JK17: 0 | JL17: 0 | JM17: 0 | JQ17: Nao | JT17: 0 | JU17: / / | JW17: 0 | KA17: 0 | KF17: 0 | KG17: 0 | KH17: 0 | KI17: 0 | KS17: . . | KT17: 0 | KU17: 0 | KV17: 0 | KX17: 0 | KZ17: 0 | LF17: 0 | LH17: 0 | LI17: 0
A18: 1 | B18: 12262 | C18: GUIA DO CABO 191 GM 5/16 ANT 13021 | D18: AI | E18: PC | F18: 80 | G18: 9000 | H18: 0 | I18: 8431.10.90 | L18: 0 | M18: 0 | N18: 0 | R18: 0 | S18: 0 | W18: Multiplicador | X18: 0 | Z18: 1 | AA18: 0 | AB18: 0 | AC18: 4412.92 | AD18: 43903 | AE18: 4050.87 | AF18: 0 | AH18: 0 | AJ18: 0 | AL18: 0 | AM18: 0 | AN18: 16601001 | AO18: 0 | AP18: 1000 | AT18: 0 | AU18: Direto | AW18: Normal | AX18: 0 | AY18: 40780 | BA18: 40780 | BB18: Nao utiliza | BD18: 0 | BF18: Nao | BG18: / / | BH18: 0 | BI18: 1 | BJ18: 0 | BK18: 0 | BM18: / / | BN18: 0 | BR18: Nao | BS18: Nao | BT18: Nao | BW18: 83 | CA18: 0 | CB18: N | CE18: Nao | CH18: Nao | CN18: SigaQuality | CO18: Nao | CP18: 1 | CQ18: 0 | CS18: 0 | CT18: 0 | CU18: 0 | CV18: Não | CW18: 0 | CX18: 0 | CY18: 0 | CZ18: 0 | DB18: 0 | DC18: Nao | DF18: Nao permite | DH18: 0 | DJ18: 0 | DK18: Normal | DL18: 0 | DN18: 0 | DO18: / / | DP18: 0 | DQ18: 0 | DS18: 0 | DU18: 0 | DW18: 0 | DX18: Nao | DY18: 0 | DZ18: 0 | EA18: 0 | ED18: Não | EE18: 0 | EF18: 0 | EQ18: Sim | ES18: Normal | ET18: 0 | EV18: 0 | EY18: Moeda1 | EZ18: 0 | FA18: Nao | FB18: 0 | FC18: 0 | FE18: . . | FF18: 0 | FG18: . . | FJ18: 0 | FK18: 0 | FP18: 0 | FR18: 0 | FS18: Nao | FX18: / / | FZ18: S | GA18: 0 | GB18: / / | GE18: 0 | GG18: 0 | GN18: 0 | GO18: Comprando | GQ18: 0 | GU18: 0 | GY18: Não | HB18: 0 | HE18: 0 | HF18: 0 | HG18: 0 | HK18: / / | HM18: 1a Unidade de Medida | HN18: 0 | HP18: 0 | HQ18: 0 | HR18: / / | HS18: Nao | HT18: 0 | HU18: 0 | HW18: 0 | HX18: 0 | HY18: 1 | HZ18: Não | IA18: 4050.87 | IB18: Não | ID18: Não | IF18: 0 | IG18: / / | II18: / / | IR18: Não | IT18: 0 | IY18: Sim | IZ18: Nao | JC18: Nao | JE18: 0 | JF18: 0 | JI18: / / | JJ18: 0 | JK18: 0 | JL18: 0 | JM18: 0 | JQ18: Nao | JT18: 0 | JU18: / / | JW18: 0 | KA18: 0 | KF18: 0 | KG18: 0 | KH18: 0 | KI18: 0 | KS18: . . | KT18: 0 | KU18: 0 | KV18: 0 | KX18: 0 | KZ18: 0 | LF18: 0 | LH18: 0 | LI18: 0
A19: 1 | B19: 12263 | C19: CABO FLEX 1KV 16MM BR | D19: AI | E19: MT | F19: 80 | G19: 9000 | H19: 0 | I19: 8544.49.00 | L19: 0 | M19: 0 | N19: 0 | R19: 0 | S19: 0 | W19: Multiplicador | X19: 0 | Z19: 1 | AA19: 0 | AB19: 0 | AC19: 16.14 | AD19: 40781 | AE19: 5.94 | AF19: 0 | AH19: 0 | AJ19: 0 | AL19: 0 | AM19: 0 | AN19: 16601001 | AO19: 0 | AP19: 1000 | AT19: 0 | AU19: Direto | AW19: Normal | AX19: 0 | AY19: 40781 | BA19: 40781 | BB19: Nao utiliza | BD19: 0 | BF19: Nao | BG19: / / | BH19: 0 | BI19: 1 | BJ19: 0 | BK19: 0 | BM19: / / | BN19: 0 | BR19: Nao | BS19: Nao | BT19: Nao | BW19: 63 | CA19: 0 | CB19: N | CE19: Nao | CH19: Nao | CN19: Materiais | CO19: Nao | CP19: 1 | CQ19: 0 | CS19: 0 | CT19: 0 | CU19: 0 | CV19: Não | CW19: 0 | CX19: 0 | CY19: 0 | CZ19: 0 | DB19: 0 | DC19: Nao | DF19: Nao permite | DH19: 0 | DJ19: 0 | DK19: Normal | DL19: 0 | DN19: 0 | DO19: / / | DP19: 0 | DQ19: 0 | DS19: 0 | DU19: 0 | DW19: 0 | DX19: Nao | DY19: 0 | DZ19: 0 | EA19: 0 | ED19: Não | EE19: 0 | EF19: 0 | EQ19: Sim | ES19: Normal | ET19: 0 | EV19: 0 | EY19: Moeda1 | EZ19: 0 | FA19: Nao | FB19: 0 | FC19: 0 | FE19: . . | FF19: 0 | FG19: . . | FJ19: 0 | FK19: 0 | FP19: 0 | FR19: 0 | FX19: / / | FZ19: S | GA19: 0 | GB19: / / | GE19: 0 | GG19: 0 | GN19: 0 | GO19: Comprando | GQ19: 0 | GU19: 0 | GY19: Não | HB19: 0 | HE19: 0 | HF19: 0 | HG19: 0 | HK19: / / | HM19: 1a Unidade de Medida | HN19: 0 | HP19: 0 | HQ19: 0 | HR19: / / | HS19: Nao | HT19: 0 | HU19: 0 | HW19: 0 | HX19: 0 | HY19: 0 | HZ19: Não | IA19: 0 | IB19: Não | ID19: Não | IF19: 0 | IG19: / / | II19: / / | IR19: Não | IT19: 0 | IY19: Sim | IZ19: Nao | JC19: Nao | JE19: 0 | JF19: 0 | JI19: / / | JJ19: 0 | JK19: 0 | JL19: 0 | JM19: 0 | JQ19: Nao | JT19: 0 | JU19: / / | JW19: 0 | KA19: 0 | KF19: 0 | KG19: 0 | KH19: 0 | KI19: 0 | KS19: . . | KT19: 0 | KU19: 0 | KV19: 0 | KX19: 0 | KZ19: 0 | LF19: 0 | LH19: 0 | LI19: 0
A20: 1 | B20: 12264 | C20: LUMINARIA NE 220V BALIZAMENTO AUREON | D20: AI | E20: PC | F20: 80 | G20: 9000 | H20: 0 | I20: 8504.10.00 | L20: 0 | M20: 0 | N20: 0 | R20: 0 | S20: 0 | W20: Multiplicador | X20: 0 | Z20: 1 | AA20: 0 | AB20: 0 | AC20: 486.2367 | AD20: 40766 | AE20: 467.78 | AF20: 0 | AH20: 0 | AJ20: 0 | AL20: 0 | AM20: 0 | AN20: 16601001 | AO20: 0 | AP20: 1000 | AT20: 0 | AU20: Direto | AW20: Normal | AX20: 0 | AY20: 40781 | BA20: 40781 | BB20: Nao utiliza | BD20: 0 | BF20: Nao | BG20: / / | BH20: 0 | BI20: 1 | BJ20: 0 | BK20: 0 | BM20: / / | BN20: 0 | BR20: Nao | BS20: Nao | BT20: Nao | BW20: 83 | CA20: 0 | CB20: N | CE20: Nao | CH20: Nao | CN20: SigaQuality | CO20: Nao | CP20: 1 | CQ20: 0 | CS20: 0 | CT20: 0 | CU20: 0 | CV20: Não | CW20: 0 | CX20: 0 | CY20: 0 | CZ20: 0 | DB20: 0 | DC20: Nao | DF20: Nao permite | DH20: 0 | DJ20: 0 | DK20: Normal | DL20: 0 | DN20: 0 | DO20: / / | DP20: 0 | DQ20: 0 | DS20: 0 | DU20: 0 | DW20: 0 | DX20: Nao | DY20: 0 | DZ20: 0 | EA20: 0 | ED20: Não | EE20: 0 | EF20: 0 | EQ20: Sim | ES20: Normal | ET20: 0 | EV20: 0 | EY20: Moeda1 | EZ20: 0 | FA20: Nao | FB20: 0 | FC20: 0 | FE20: . . | FF20: 0 | FG20: . . | FJ20: 0 | FK20: 0 | FP20: 0 | FR20: 0 | FS20: Nao | FX20: / / | FZ20: S | GA20: 0 | GB20: / / | GE20: 0 | GG20: 0 | GN20: 0 | GO20: Comprando | GQ20: 0 | GU20: 0 | GY20: Não | HB20: 0 | HE20: 0 | HF20: 0 | HG20: 0 | HK20: / / | HM20: 1a Unidade de Medida | HN20: 0 | HP20: 0 | HQ20: 0 | HR20: / / | HS20: Nao | HT20: 0 | HU20: 0 | HW20: 0 | HX20: 0 | HY20: 0 | HZ20: Não | IA20: 0 | IB20: Não | ID20: Não | IF20: 0 | IG20: / / | II20: / / | IR20: Não | IT20: 0 | IY20: Sim | IZ20: Nao | JC20: Nao | JE20: 0 | JF20: 0 | JI20: / / | JJ20: 0 | JK20: 0 | JL20: 0 | JM20: 0 | JQ20: Nao | JT20: 0 | JU20: / / | JW20: 0 | KA20: 0 | KF20: 0 | KG20: 0 | KH20: 0 | KI20: 0 | KS20: . . | KT20: 0 | KU20: 0 | KV20: 0 | KX20: 0 | KZ20: 0 | LF20: 0 | LH20: 0 | LI20: 0
A21: 1 | B21: 12265 | C21: PARAFUSO CAB LENT AUTO TRAV ZINC 5/16X1/2 | D21: MA | E21: PC | F21: 80 | G21: 49 | H21: 0 | I21: 7318.15.00 | L21: 0 | M21: 0 | N21: 0 | R21: 0 | S21: 0 | W21: Multiplicador | X21: 0 | Z21: 1 | AA21: 0 | AB21: 0 | AC21: 0.15 | AD21: 40780 | AE21: 1 | AF21: 0 | AH21: 0 | AJ21: 0 | AL21: 1 | AM21: 0 | AN21: 16601001 | AO21: 0 | AP21: 1000 | AT21: 0 | AU21: Direto | AW21: Normal | AX21: 0 | AY21: 40781 | BA21: 40781 | BB21: Nao utiliza | BD21: 0 | BF21: Nao | BG21: / / | BH21: 0 | BI21: 1 | BJ21: 0 | BK21: 0 | BM21: / / | BN21: 0 | BR21: Nao | BS21: Nao | BT21: Nao | BW21: 60 | CA21: 0 | CB21: N | CE21: Nao | CH21: Nao | CN21: SigaQuality | CO21: Nao | CP21: 1 | CQ21: 0 | CS21: 0 | CT21: 0 | CU21: 0 | CV21: Não | CW21: 0 | CX21: 0 | CY21: 0 | CZ21: 0 | DB21: 0 | DC21: Nao | DF21: Nao permite | DH21: 0 | DJ21: 0 | DK21: Normal | DL21: 0 | DN21: 0 | DO21: / / | DP21: 0 | DQ21: 0 | DS21: 0 | DU21: 0 | DW21: 0 | DX21: Nao | DY21: 0 | DZ21: 0 | EA21: 0 | ED21: Não | EE21: 0 | EF21: 0 | EQ21: Sim | ES21: Normal | ET21: 0 | EV21: 0 | EY21: Moeda1 | EZ21: 0 | FA21: Nao | FB21: 0 | FC21: 0 | FE21: . . | FF21: 0 | FG21: . . | FJ21: 0 | FK21: 0 | FP21: 0 | FR21: 0 | FS21: Nao | FX21: / / | FZ21: S | GA21: 0 | GB21: / / | GE21: 0 | GG21: 0 | GN21: 0 | GO21: Comprando | GQ21: 0 | GU21: 0 | GY21: Não | HB21: 0 | HE21: 0 | HF21: 0 | HG21: 0 | HK21: / / | HM21: 1a Unidade de Medida | HN21: 0 | HP21: 0 | HQ21: 0 | HR21: / / | HS21: Nao | HT21: 0 | HU21: 0 | HW21: 0 | HX21: 0 | HY21: 0 | HZ21: Não | IA21: 0 | IB21: Não | ID21: Não | IF21: 0 | IG21: / / | II21: / / | IR21: Não | IT21: 0 | IY21: Sim | IZ21: Nao | JC21: Nao | JE21: 0 | JF21: 0 | JI21: / / | JJ21: 0 | JK21: 0 | JL21: 0 | JM21: 0 | JQ21: Nao | JT21: 0 | JU21: / / | JW21: 0 | KA21: 0 | KF21: 0 | KG21: 0 | KH21: 0 | KI21: 0 | KS21: . . | KT21: 0 | KU21: 0 | KV21: 0 | KX21: 0 | KZ21: 0 | LF21: 0 | LH21: 0 | LI21: 0
A22: 1 | B22: 12266 | C22: LUMINARIA FLUXEON 2X11N 220V BALIZ AUREON | D22: AI | E22: PC | F22: 80 | G22: 9000 | H22: 0 | I22: 8504.10.00 | L22: 0 | M22: 0 | N22: 0 | R22: 0 | S22: 0 | W22: Multiplicador | X22: 0 | Z22: 1 | AA22: 0 | AB22: 0 | AC22: 346.6467 | AD22: 40780 | AE22: 333.47 | AF22: 0 | AH22: 0 | AJ22: 0 | AL22: 0 | AM22: 0 | AN22: 16601001 | AO22: 0 | AP22: 1000 | AT22: 0 | AU22: Direto | AW22: Normal | AX22: 0 | AY22: 40781 | BA22: 40781 | BB22: Nao utiliza | BD22: 0 | BF22: Nao | BG22: / / | BH22: 0 | BI22: 1 | BJ22: 0 | BK22: 0 | BM22: / / | BN22: 0 | BR22: Nao | BS22: Nao | BT22: Nao | BW22: 83 | CA22: 0 | CB22: N | CE22: Nao | CH22: Nao | CN22: SigaQuality | CO22: Nao | CP22: 1 | CQ22: 0 | CS22: 0 | CT22: 0 | CU22: 0 | CV22: Não | CW22: 0 | CX22: 0 | CY22: 0 | CZ22: 0 | DB22: 0 | DC22: Nao | DF22: Nao permite | DH22: 0 | DJ22: 0 | DK22: Normal | DL22: 0 | DN22: 0 | DO22: / / | DP22: 0 | DQ22: 0 | DS22: 0 | DU22: 0 | DW22: 0 | DX22: Nao | DY22: 0 | DZ22: 0 | EA22: 0 | ED22: Não | EE22: 0 | EF22: 0 | EQ22: Sim | ES22: Normal | ET22: 0 | EV22: 0 | EY22: Moeda1 | EZ22: 0 | FA22: Nao | FB22: 0 | FC22: 0 | FE22: . . | FF22: 0 | FG22: . . | FJ22: 0 | FK22: 0 | FP22: 0 | FR22: 0 | FS22: Nao | FX22: / / | FZ22: S | GA22: 0 | GB22: / / | GE22: 0 | GG22: 0 | GN22: 0 | GO22: Comprando | GQ22: 0 | GU22: 0 | GY22: Não | HB22: 0 | HE22: 0 | HF22: 0 | HG22: 0 | HK22: / / | HM22: 1a Unidade de Medida | HN22: 0 | HP22: 0 | HQ22: 0 | HR22: / / | HS22: Nao | HT22: 0 | HU22: 0 | HW22: 0 | HX22: 0 | HY22: 0 | HZ22: Não | IA22: 0 | IB22: Não | ID22: Não | IF22: 0 | IG22: / / | II22: / / | IR22: Não | IT22: 0 | IY22: Sim | IZ22: Nao | JC22: Nao | JE22: 0 | JF22: 0 | JI22: / / | JJ22: 0 | JK22: 0 | JL22: 0 | JM22: 0 | JQ22: Nao | JT22: 0 | JU22: / / | JW22: 0 | KA22: 0 | KF22: 0 | KG22: 0 | KH22: 0 | KI22: 0 | KS22: . . | KT22: 0 | KU22: 0 | KV22: 0 | KX22: 0 | KZ22: 0 | LF22: 0 | LH22: 0 | LI22: 0
A23: 1 | B23: 12267 | C23: CABO FLEX 1KV AFUMEX 16MM PT | D23: AI | E23: PC | F23: 80 | G23: 9000 | H23: 0 | I23: 8544.49.00 | L23: 0 | M23: 0 | N23: 0 | R23: 0 | S23: 0 | W23: Multiplicador | X23: 0 | Z23: 1 | AA23: 0 | AB23: 0 | AC23: 8.85 | AD23: 40780 | AE23: 5.95 | AF23: 0 | AH23: 0 | AJ23: 0 | AL23: 1 | AM23: 0 | AN23: 16601001 | AO23: 0 | AP23: 1000 | AT23: 0 | AU23: Direto | AW23: Normal | AX23: 0 | AY23: 40781 | BA23: 40781 | BB23: Nao utiliza | BD23: 0 | BF23: Nao | BG23: / / | BH23: 0 | BI23: 1 | BJ23: 0 | BK23: 0 | BM23: / / | BN23: 0 | BR23: Nao | BS23: Nao | BT23: Nao | BW23: 83 | CA23: 0 | CB23: N | CE23: Nao | CH23: Nao | CN23: SigaQuality | CO23: Nao | CP23: 1 | CQ23: 0 | CS23: 0 | CT23: 0 | CU23: 0 | CV23: Não | CW23: 0 | CX23: 0 | CY23: 0 | CZ23: 0 | DB23: 0 | DC23: Nao | DF23: Nao permite | DH23: 0 | DJ23: 0 | DK23: Normal | DL23: 0 | DN23: 0 | DO23: / / | DP23: 0 | DQ23: 0 | DS23: 0 | DU23: 0 | DW23: 0 | DX23: Nao | DY23: 0 | DZ23: 0 | EA23: 0 | ED23: Não | EE23: 0 | EF23: 0 | EQ23: Sim | ES23: Normal | ET23: 0 | EV23: 0 | EY23: Moeda1 | EZ23: 0 | FA23: Nao | FB23: 0 | FC23: 0 | FE23: . . | FF23: 0 | FG23: . . | FJ23: 0 | FK23: 0 | FP23: 0 | FR23: 0 | FS23: Nao | FX23: / / | FZ23: S | GA23: 0 | GB23: / / | GE23: 0 | GG23: 0 | GN23: 0 | GO23: Comprando | GQ23: 0 | GU23: 0 | GY23: Não | HB23: 0 | HE23: 0 | HF23: 0 | HG23: 0 | HK23: / / | HM23: 1a Unidade de Medida | HN23: 0 | HP23: 0 | HQ23: 0 | HR23: / / | HS23: Nao | HT23: 0 | HU23: 0 | HW23: 0 | HX23: 0 | HY23: 0 | HZ23: Não | IA23: 0 | IB23: Não | ID23: Não | IF23: 0 | IG23: / / | II23: / / | IR23: Não | IT23: 0 | IY23: Sim | IZ23: Nao | JC23: Nao | JE23: 0 | JF23: 0 | JI23: / / | JJ23: 0 | JK23: 0 | JL23: 0 | JM23: 0 | JQ23: Nao | JT23: 0 | JU23: / / | JW23: 0 | KA23: 0 | KF23: 0 | KG23: 0 | KH23: 0 | KI23: 0 | KS23: . . | KT23: 0 | KU23: 0 | KV23: 0 | KX23: 0 | KZ23: 0 | LF23: 0 | LH23: 0 | LI23: 0
A24: 1 | B24: 12268 | C24: CABO FLEX 1KV AFUMEX 16MM BR | D24: AI | E24: PC | F24: 80 | G24: 9000 | H24: 0 | I24: 8544.49.00 | L24: 0 | M24: 0 | N24: 0 | R24: 0 | S24: 0 | W24: Multiplicador | X24: 0 | Z24: 1 | AA24: 0 | AB24: 0 | AC24: 2.4423 | AD24: 40780 | AE24: 5.95 | AF24: 0 | AH24: 0 | AJ24: 0 | AL24: 0 | AM24: 0 | AN24: 16601001 | AO24: 0 | AP24: 1000 | AT24: 0 | AU24: Direto | AW24: Normal | AX24: 0 | AY24: 40781 | BA24: 40781 | BB24: Nao utiliza | BD24: 0 | BF24: Nao | BG24: / / | BH24: 0 | BI24: 1 | BJ24: 0 | BK24: 0 | BM24: / / | BN24: 0 | BR24: Nao | BS24: Nao | BT24: Nao | BW24: 83 | CA24: 0 | CB24: N | CE24: Nao | CH24: Nao | CN24: SigaQuality | CO24: Nao | CP24: 1 | CQ24: 0 | CS24: 0 | CT24: 0 | CU24: 0 | CV24: Não | CW24: 0 | CX24: 0 | CY24: 0 | CZ24: 0 | DB24: 0 | DC24: Nao | DF24: Nao permite | DH24: 0 | DJ24: 0 | DK24: Normal | DL24: 0 | DN24: 0 | DO24: / / | DP24: 0 | DQ24: 0 | DS24: 0 | DU24: 0 | DW24: 0 | DX24: Nao | DY24: 0 | DZ24: 0 | EA24: 0 | ED24: Não | EE24: 0 | EF24: 0 | EQ24: Sim | ES24: Normal | ET24: 0 | EV24: 0 | EY24: Moeda1 | EZ24: 0 | FA24: Nao | FB24: 0 | FC24: 0 | FE24: . . | FF24: 0 | FG24: . . | FJ24: 0 | FK24: 0 | FP24: 0 | FR24: 0 | FS24: Nao | FX24: / / | FZ24: S | GA24: 0 | GB24: / / | GE24: 0 | GG24: 0 | GN24: 0 | GO24: Comprando | GQ24: 0 | GU24: 0 | GY24: Não | HB24: 0 | HE24: 0 | HF24: 0 | HG24: 0 | HK24: / / | HM24: 1a Unidade de Medida | HN24: 0 | HP24: 0 | HQ24: 0 | HR24: / / | HS24: Nao | HT24: 0 | HU24: 0 | HW24: 0 | HX24: 0 | HY24: 0 | HZ24: Não | IA24: 0 | IB24: Não | ID24: Não | IF24: 0 | IG24: / / | II24: / / | IR24: Não | IT24: 0 | IY24: Sim | IZ24: Nao | JC24: Nao | JE24: 0 | JF24: 0 | JI24: / / | JJ24: 0 | JK24: 0 | JL24: 0 | JM24: 0 | JQ24: Nao | JT24: 0 | JU24: / / | JW24: 0 | KA24: 0 | KF24: 0 | KG24: 0 | KH24: 0 | KI24: 0 | KS24: . . | KT24: 0 | KU24: 0 | KV24: 0 | KX24: 0 | KZ24: 0 | LF24: 0 | LH24: 0 | LI24: 0
A25: 1 | B25: 12269 | C25: CABO FLEX 1KV AFUMEX 16MM VM | D25: AI | E25: PC | F25: 80 | G25: 9000 | H25: 0 | I25: 8544.49.00 | L25: 0 | M25: 0 | N25: 0 | R25: 0 | S25: 0 | W25: Multiplicador | X25: 0 | Z25: 1 | AA25: 0 | AB25: 0 | AC25: 2.4427 | AD25: 40781 | AE25: 5.95 | AF25: 0 | AH25: 0 | AJ25: 0 | AL25: 0 | AM25: 0 | AN25: 16601001 | AO25: 0 | AP25: 1000 | AT25: 0 | AU25: Direto | AW25: Normal | AX25: 0 | AY25: 40781 | BA25: 40781 | BB25: Nao utiliza | BD25: 0 | BF25: Nao | BG25: / / | BH25: 0 | BI25: 1 | BJ25: 0 | BK25: 0 | BM25: / / | BN25: 0 | BR25: Nao | BS25: Nao | BT25: Nao | BW25: 83 | CA25: 0 | CB25: N | CE25: Nao | CH25: Nao | CN25: SigaQuality | CO25: Nao | CP25: 1 | CQ25: 0 | CS25: 0 | CT25: 0 | CU25: 0 | CV25: Não | CW25: 0 | CX25: 0 | CY25: 0 | CZ25: 0 | DB25: 0 | DC25: Nao | DF25: Nao permite | DH25: 0 | DJ25: 0 | DK25: Normal | DL25: 0 | DN25: 0 | DO25: / / | DP25: 0 | DQ25: 0 | DS25: 0 | DU25: 0 | DW25: 0 | DX25: Nao | DY25: 0 | DZ25: 0 | EA25: 0 | ED25: Não | EE25: 0 | EF25: 0 | EQ25: Sim | ES25: Normal | ET25: 0 | EV25: 0 | EY25: Moeda1 | EZ25: 0 | FA25: Nao | FB25: 0 | FC25: 0 | FE25: . . | FF25: 0 | FG25: . . | FJ25: 0 | FK25: 0 | FP25: 0 | FR25: 0 | FS25: Nao | FX25: / / | FZ25: S | GA25: 0 | GB25: / / | GE25: 0 | GG25: 0 | GN25: 0 | GO25: Comprando | GQ25: 0 | GU25: 0 | GY25: Não | HB25: 0 | HE25: 0 | HF25: 0 | HG25: 0 | HK25: / / | HM25: 1a Unidade de Medida | HN25: 0 | HP25: 0 | HQ25: 0 | HR25: / / | HS25: Nao | HT25: 0 | HU25: 0 | HW25: 0 | HX25: 0 | HY25: 0 | HZ25: Não | IA25: 0 | IB25: Não | ID25: Não | IF25: 0 | IG25: / / | II25: / / | IR25: Não | IT25: 0 | IY25: Sim | IZ25: Nao | JC25: Nao | JE25: 0 | JF25: 0 | JI25: / / | JJ25: 0 | JK25: 0 | JL25: 0 | JM25: 0 | JQ25: Nao | JT25: 0 | JU25: / / | JW25: 0 | KA25: 0 | KF25: 0 | KG25: 0 | KH25: 0 | KI25: 0 | KS25: . . | KT25: 0 | KU25: 0 | KV25: 0 | KX25: 0 | KZ25: 0 | LF25: 0 | LH25: 0 | LI25: 0
A26: 1 | B26: 1227 | C26: ELETROD. PVC FLEX CORRUGADO 25MM - 10 METROS | D26: PA | E26: MT | F26: 1 | G26: 160 | H26: 0 | I26: 3917.23.00 | L26: 0 | M26: 0 | N26: 0 | Q26: 516 | R26: 0 | S26: 0 | W26: Multiplicador | X26: 0 | Z26: 10 | AA26: 23.7353 | AB26: 10480 | AC26: 0.7812 | AD26: 44648 | AE26: 0.992 | AF26: 0.0647 | AH26: 2131 | AJ26: 1 | AK26: Dias | AL26: 49430 | AM26: 90 | AN26: 11501001 | AO26: 0 | AP26: 1001 | AT26: 1 | AU26: Direto | AV26: Nao | AW26: Normal | AX26: 5 | AY26: 43274 | BA26: 44524 | BB26: Nao utiliza | BD26: 0 | BF26: Sim | BG26: 42640 | BH26: 0 | BI26: 33 | BJ26: 0 | BK26: 0 | BM26: 42642 | BN26: 0 | BO26: 7897801317115 | BR26: Nao | BS26: Nao | BT26: Nao | BV26: 1 | BW26: 30 | BY26: 66 | CA26: 0 | CB26: Nao | CE26: Nao | CH26: Nao | CI26: KRONA | CK26: NÒo usa | CN26: SigaQuality | CP26: 1 | CQ26: 80 | CS26: 0 | CT26: 0 | CU26: 0 | CV26: Não | CW26: 0 | CX26: 0 | CY26: 0 | CZ26: 0 | DA26: 37 | DB26: 0 | DH26: 0 | DJ26: 0 | DL26: 0 | DN26: 0 | DO26: / / | DP26: 0 | DQ26: 7.6 | DS26: 0 | DU26: 1.65 | DW26: 0 | DY26: 0 | DZ26: 0 | EA26: 0 | EB26: 17897801317112 | EE26: 0 | EF26: 0 | EL26: 57897801317110 | EN26: Rolos | EO26: Sim | ET26: 0 | EV26: 0 | EY26: Moeda1 | EZ26: 0 | FA26: Nao | FB26: 0 | FC26: 0 | FD26: T | FE26: . . | FF26: 0 | FG26: . . | FH26: 27897801317119 | FJ26: 0 | FK26: 0 | FP26: 0 | FR26: 0 | FS26: Nao | FX26: / / | GA26: 0 | GB26: / / | GD26: 16 | GE26: 0 | GG26: 0 | GN26: 0 | GO26: Produzindo | GQ26: 0 | GU26: 4 | GY26: Não | HB26: 0 | HE26: 0 | HF26: 0 | HG26: 0.01297 | HK26: / / | HL26: S | HM26: 0 | HN26: 0 | HO26: 24 | HP26: 0.0643 | HQ26: 0 | HR26: / / | HT26: 0 | HU26: 0 | HW26: 0 | HX26: 30158 | HY26: 1 | IA26: 0.99 | IF26: 1240 | IG26: 42678 | IH26: Embalagem | II26: / / | IR26: Não | IT26: 0 | JE26: 0 | JF26: 0 | JI26: / / | JJ26: 0 | JK26: 0 | JL26: 0 | JM26: 0 | JT26: 0 | JU26: / / | JW26: 0 | KA26: 0 | KF26: 0 | KG26: 0 | KH26: 0 | KI26: 0 | KS26: 10.006.00 | KT26: 0 | KU26: 0 | KV26: 0 | KX26: 0 | KZ26: 0 | LF26: 0 | LH26: 40656 | LI26: 0
A27: 1 | B27: 12270 | C27: CABO FLEX 1KV AFUMEX 16MM AZ | D27: AI | E27: PC | F27: 80 | G27: 9000 | H27: 0 | I27: 8544.49.00 | L27: 0 | M27: 0 | N27: 0 | R27: 0 | S27: 0 | W27: Multiplicador | X27: 0 | Z27: 1 | AA27: 0 | AB27: 0 | AC27: 6.51 | AD27: 40781 | AE27: 5.95 | AF27: 0 | AH27: 0 | AJ27: 0 | AL27: 1 | AM27: 0 | AN27: 16601001 | AO27: 0 | AP27: 1000 | AT27: 0 | AU27: Direto | AW27: Normal | AX27: 0 | AY27: 40781 | BA27: 40781 | BB27: Nao utiliza | BD27: 0 | BF27: Nao | BG27: / / | BH27: 0 | BI27: 1 | BJ27: 0 | BK27: 0 | BM27: / / | BN27: 0 | BR27: Nao | BS27: Nao | BT27: Nao | BW27: 83 | CA27: 0 | CB27: N | CE27: Nao | CH27: Nao | CN27: SigaQuality | CO27: Nao | CP27: 1 | CQ27: 0 | CS27: 0 | CT27: 0 | CU27: 0 | CV27: Não | CW27: 0 | CX27: 0 | CY27: 0 | CZ27: 0 | DB27: 0 | DC27: Nao | DF27: Nao permite | DH27: 0 | DJ27: 0 | DK27: Normal | DL27: 0 | DN27: 0 | DO27: / / | DP27: 0 | DQ27: 0 | DS27: 0 | DU27: 0 | DW27: 0 | DX27: Nao | DY27: 0 | DZ27: 0 | EA27: 0 | ED27: Não | EE27: 0 | EF27: 0 | EQ27: Sim | ES27: Normal | ET27: 0 | EV27: 0 | EY27: Moeda1 | EZ27: 0 | FA27: Nao | FB27: 0 | FC27: 0 | FE27: . . | FF27: 0 | FG27: . . | FJ27: 0 | FK27: 0 | FP27: 0 | FR27: 0 | FS27: Nao | FX27: / / | FZ27: S | GA27: 0 | GB27: / / | GE27: 0 | GG27: 0 | GN27: 0 | GO27: Comprando | GQ27: 0 | GU27: 0 | GY27: Não | HB27: 0 | HE27: 0 | HF27: 0 | HG27: 0 | HK27: / / | HM27: 1a Unidade de Medida | HN27: 0 | HP27: 0 | HQ27: 0 | HR27: / / | HS27: Nao | HT27: 0 | HU27: 0 | HW27: 0 | HX27: 0 | HY27: 0 | HZ27: Não | IA27: 0 | IB27: Não | ID27: Não | IF27: 0 | IG27: / / | II27: / / | IR27: Não | IT27: 0 | IY27: Sim | IZ27: Nao | JC27: Nao | JE27: 0 | JF27: 0 | JI27: / / | JJ27: 0 | JK27: 0 | JL27: 0 | JM27: 0 | JQ27: Nao | JT27: 0 | JU27: / / | JW27: 0 | KA27: 0 | KF27: 0 | KG27: 0 | KH27: 0 | KI27: 0 | KS27: . . | KT27: 0 | KU27: 0 | KV27: 0 | KX27: 0 | KZ27: 0 | LF27: 0 | LH27: 0 | LI27: 0
A28: 1 | B28: 12271 | C28: CABO FLEX 1KV AFUMEX 16MM VD | D28: AI | E28: PC | F28: 80 | G28: 9000 | H28: 0 | I28: 8544.49.00 | L28: 0 | M28: 0 | N28: 0 | R28: 0 | S28: 0 | W28: Multiplicador | X28: 0 | Z28: 1 | AA28: 0 | AB28: 0 | AC28: 4.7917 | AD28: 42032 | AE28: 5.28 | AF28: 0 | AH28: 0 | AJ28: 0 | AL28: 1 | AM28: 0 | AN28: 16601001 | AO28: 0 | AP28: 1000 | AT28: 0 | AU28: Direto | AW28: Normal | AX28: 0 | AY28: 40781 | BA28: 40781 | BB28: Nao utiliza | BD28: 0 | BF28: Nao | BG28: / / | BH28: 0 | BI28: 1 | BJ28: 0 | BK28: 0 | BM28: / / | BN28: 0 | BR28: Nao | BS28: Nao | BT28: Nao | BW28: 83 | CA28: 0 | CB28: N | CE28: Nao | CH28: Nao | CN28: SigaQuality | CO28: Nao | CP28: 1 | CQ28: 0 | CS28: 0 | CT28: 0 | CU28: 0 | CV28: Não | CW28: 0 | CX28: 0 | CY28: 0 | CZ28: 0 | DB28: 0 | DC28: Nao | DF28: Nao permite | DH28: 0 | DJ28: 0 | DK28: Normal | DL28: 0 | DN28: 0 | DO28: / / | DP28: 0 | DQ28: 0 | DS28: 0 | DU28: 0 | DW28: 0 | DX28: Nao | DY28: 0 | DZ28: 0 | EA28: 0 | ED28: Não | EE28: 0 | EF28: 0 | EQ28: Sim | ES28: Normal | ET28: 0 | EV28: 0 | EY28: Moeda1 | EZ28: 0 | FA28: Nao | FB28: 0 | FC28: 0 | FE28: . . | FF28: 0 | FG28: . . | FJ28: 0 | FK28: 0 | FP28: 0 | FR28: 0 | FS28: Nao | FX28: / / | FZ28: S | GA28: 0 | GB28: / / | GE28: 0 | GG28: 0 | GN28: 0 | GO28: Comprando | GQ28: 0 | GU28: 0 | GY28: Não | HB28: 0 | HE28: 0 | HF28: 0 | HG28: 0 | HK28: / / | HM28: 1a Unidade de Medida | HN28: 0 | HP28: 0 | HQ28: 0 | HR28: / / | HS28: Nao | HT28: 0 | HU28: 0 | HW28: 0 | HX28: 0 | HY28: 0 | HZ28: Não | IA28: 0 | IB28: Não | ID28: Não | IF28: 0 | IG28: / / | II28: / / | IR28: Não | IT28: 0 | IY28: Sim | IZ28: Nao | JC28: Nao | JE28: 0 | JF28: 0 | JI28: / / | JJ28: 0 | JK28: 0 | JL28: 0 | JM28: 0 | JQ28: Nao | JT28: 0 | JU28: / / | JW28: 0 | KA28: 0 | KF28: 0 | KG28: 0 | KH28: 0 | KI28: 0 | KS28: . . | KT28: 0 | KU28: 0 | KV28: 0 | KX28: 0 | KZ28: 0 | LF28: 0 | LH28: 0 | LI28: 0
A29: 1 | B29: 12272 | C29: CABO FLEX 1 KV AFUMEX 4MM VM | D29: AI | E29: MT | F29: 80 | G29: 9000 | H29: 0 | I29: 8544.49.00 | L29: 0 | M29: 0 | N29: 0 | R29: 0 | S29: 0 | W29: Multiplicador | X29: 0 | Z29: 1 | AA29: 0 | AB29: 0 | AC29: 1.7671 | AD29: 40781 | AE29: 1.7 | AF29: 0 | AH29: 0 | AJ29: 0 | AL29: 0 | AM29: 0 | AN29: 16601001 | AO29: 0 | AP29: 1000 | AT29: 0 | AU29: Direto | AW29: Normal | AX29: 0 | AY29: 40781 | BA29: 40781 | BB29: Nao utiliza | BD29: 0 | BF29: Nao | BG29: / / | BH29: 0 | BI29: 1 | BJ29: 0 | BK29: 0 | BM29: / / | BN29: 0 | BR29: Nao | BS29: Nao | BT29: Nao | BW29: 83 | CA29: 0 | CB29: N | CE29: Nao | CH29: Nao | CN29: Materiais | CO29: Nao | CP29: 1 | CQ29: 0 | CS29: 0 | CT29: 0 | CU29: 0 | CV29: Não | CW29: 0 | CX29: 0 | CY29: 0 | CZ29: 0 | DB29: 0 | DC29: Nao | DF29: Nao permite | DH29: 0 | DJ29: 0 | DK29: Normal | DL29: 0 | DN29: 0 | DO29: / / | DP29: 0 | DQ29: 0 | DS29: 0 | DU29: 0 | DW29: 0 | DX29: Nao | DY29: 0 | DZ29: 0 | EA29: 0 | ED29: Não | EE29: 0 | EF29: 0 | EQ29: Sim | ES29: Normal | ET29: 0 | EV29: 0 | EY29: Moeda1 | EZ29: 0 | FA29: Nao | FB29: 0 | FC29: 0 | FE29: . . | FF29: 0 | FG29: . . | FJ29: 0 | FK29: 0 | FP29: 0 | FR29: 0 | FX29: / / | FZ29: S | GA29: 0 | GB29: / / | GE29: 0 | GG29: 0 | GN29: 0 | GO29: Comprando | GQ29: 0 | GU29: 0 | GY29: Não | HB29: 0 | HE29: 0 | HF29: 0 | HG29: 0 | HK29: / / | HM29: 1a Unidade de Medida | HN29: 0 | HP29: 0 | HQ29: 0 | HR29: / / | HS29: Nao | HT29: 0 | HU29: 0 | HW29: 0 | HX29: 0 | HY29: 0 | HZ29: Não | IA29: 0 | IB29: Não | ID29: Não | IF29: 0 | IG29: / / | II29: / / | IR29: Não | IT29: 0 | IY29: Sim | IZ29: Nao | JC29: Nao | JE29: 0 | JF29: 0 | JI29: / / | JJ29: 0 | JK29: 0 | JL29: 0 | JM29: 0 | JQ29: Nao | JT29: 0 | JU29: / / | JW29: 0 | KA29: 0 | KF29: 0 | KG29: 0 | KH29: 0 | KI29: 0 | KS29: . . | KT29: 0 | KU29: 0 | KV29: 0 | KX29: 0 | KZ29: 0 | LF29: 0 | LH29: 0 | LI29: 0
A30: 1 | B30: 12273 | C30: CABO FLEX 750V AFUMEX 35MM VD | D30: AI | E30: PC | F30: 80 | G30: 9000 | H30: 0 | I30: 8544.49.00 | L30: 0 | M30: 0 | N30: 0 | R30: 0 | S30: 0 | W30: Multiplicador | X30: 0 | Z30: 1 | AA30: 0 | AB30: 0 | AC30: 13.107 | AD30: 40781 | AE30: 12.61 | AF30: 0 | AH30: 0 | AJ30: 0 | AL30: 1 | AM30: 0 | AN30: 16601001 | AO30: 0 | AP30: 1000 | AT30: 0 | AU30: Direto | AW30: Normal | AX30: 0 | AY30: 40781 | BA30: 40781 | BB30: Nao utiliza | BD30: 0 | BF30: Nao | BG30: / / | BH30: 0 | BI30: 1 | BJ30: 0 | BK30: 0 | BM30: 42744 | BN30: 0 | BR30: Nao | BS30: Nao | BT30: Nao | BW30: 83 | CA30: 0 | CB30: N | CE30: Nao | CH30: Nao | CN30: SigaQuality | CO30: Nao | CP30: 1 | CQ30: 0 | CS30: 0 | CT30: 0 | CU30: 0 | CV30: Não | CW30: 0 | CX30: 0 | CY30: 0 | CZ30: 0 | DB30: 0 | DC30: Nao | DF30: Nao permite | DH30: 0 | DJ30: 0 | DK30: Normal | DL30: 0 | DN30: 0 | DO30: / / | DP30: 0 | DQ30: 0 | DS30: 0 | DU30: 0 | DW30: 0 | DX30: Nao | DY30: 0 | DZ30: 0 | EA30: 0 | ED30: Não | EE30: 0 | EF30: 0 | EQ30: Sim | ES30: Normal | ET30: 0 | EV30: 0 | EY30: Moeda1 | EZ30: 0 | FA30: Nao | FB30: 0 | FC30: 0 | FE30: . . | FF30: 0 | FG30: . . | FJ30: 0 | FK30: 0 | FP30: 0 | FR30: 0 | FS30: Nao | FX30: / / | FZ30: S | GA30: 0 | GB30: / / | GE30: 0 | GG30: 0 | GN30: 0 | GO30: Comprando | GQ30: 0 | GU30: 0 | GY30: Não | HB30: 0 | HE30: 0 | HF30: 0 | HG30: 0 | HK30: / / | HM30: 1a Unidade de Medida | HN30: 0 | HP30: 0 | HQ30: 0 | HR30: / / | HS30: Nao | HT30: 0 | HU30: 0 | HW30: 0 | HX30: 0 | HY30: 0 | HZ30: Não | IA30: 0 | IB30: Não | ID30: Não | IF30: 0 | IG30: / / | II30: / / | IR30: Não | IT30: 0 | IY30: Sim | IZ30: Nao | JC30: Nao | JE30: 0 | JF30: 0 | JI30: / / | JJ30: 0 | JK30: 0 | JL30: 0 | JM30: 0 | JQ30: Nao | JT30: 0 | JU30: / / | JW30: 0 | KA30: 0 | KF30: 0 | KG30: 0 | KH30: 0 | KI30: 0 | KS30: . . | KT30: 0 | KU30: 0 | KV30: 0 | KX30: 0 | KZ30: 0 | LF30: 0 | LH30: 0 | LI30: 0
A31: 1 | B31: 12274 | C31: CABO FLEX.1KV AFUMEX 95,0MM PT | D31: AI | E31: PC | F31: 80 | G31: 9000 | H31: 0 | I31: 8544.49.00 | L31: 0 | M31: 0 | N31: 0 | R31: 0 | S31: 0 | W31: Multiplicador | X31: 0 | Z31: 1 | AA31: 0 | AB31: 0 | AC31: 27.79 | AD31: 40781 | AE31: 37.5 | AF31: 0 | AH31: 0 | AJ31: 0 | AL31: 1 | AM31: 0 | AN31: 16601001 | AO31: 0 | AP31: 1000 | AT31: 0 | AU31: Direto | AW31: Normal | AX31: 0 | AY31: 40781 | BA31: 40781 | BB31: Nao utiliza | BD31: 0 | BF31: Nao | BG31: / / | BH31: 0 | BI31: 1 | BJ31: 0 | BK31: 0 | BM31: / / | BN31: 0 | BR31: Nao | BS31: Nao | BT31: Nao | BW31: 83 | CA31: 0 | CB31: N | CE31: Nao | CH31: Nao | CN31: SigaQuality | CO31: Nao | CP31: 1 | CQ31: 0 | CS31: 0 | CT31: 0 | CU31: 0 | CV31: Não | CW31: 0 | CX31: 0 | CY31: 0 | CZ31: 0 | DB31: 0 | DC31: Nao | DF31: Nao permite | DH31: 0 | DJ31: 0 | DK31: Normal | DL31: 0 | DN31: 0 | DO31: / / | DP31: 0 | DQ31: 0 | DS31: 0 | DU31: 0 | DW31: 0 | DX31: Nao | DY31: 0 | DZ31: 0 | EA31: 0 | ED31: Não | EE31: 0 | EF31: 0 | EQ31: Sim | ES31: Normal | ET31: 0 | EV31: 0 | EY31: Moeda1 | EZ31: 0 | FA31: Nao | FB31: 0 | FC31: 0 | FE31: . . | FF31: 0 | FG31: . . | FJ31: 0 | FK31: 0 | FP31: 0 | FR31: 0 | FS31: Nao | FX31: / / | FZ31: S | GA31: 0 | GB31: / / | GE31: 0 | GG31: 0 | GN31: 0 | GO31: Comprando | GQ31: 0 | GU31: 0 | GY31: Não | HB31: 0 | HE31: 0 | HF31: 0 | HG31: 0 | HK31: / / | HM31: 1a Unidade de Medida | HN31: 0 | HP31: 0 | HQ31: 0 | HR31: / / | HS31: Nao | HT31: 0 | HU31: 0 | HW31: 0 | HX31: 0 | HY31: 0 | HZ31: Não | IA31: 0 | IB31: Não | ID31: Não | IF31: 0 | IG31: / / | II31: / / | IR31: Não | IT31: 0 | IY31: Sim | IZ31: Nao | JC31: Nao | JE31: 0 | JF31: 0 | JI31: / / | JJ31: 0 | JK31: 0 | JL31: 0 | JM31: 0 | JQ31: Nao | JT31: 0 | JU31: / / | JW31: 0 | KA31: 0 | KF31: 0 | KG31: 0 | KH31: 0 | KI31: 0 | KS31: . . | KT31: 0 | KU31: 0 | KV31: 0 | KX31: 0 | KZ31: 0 | LF31: 0 | LH31: 0 | LI31: 0
A32: 1 | B32: 12275 | C32: CABO FLEX.1KV AFUMEX 50,0MM VD | D32: AI | E32: PC | F32: 80 | G32: 9000 | H32: 0 | I32: 8544.49.00 | L32: 0 | M32: 0 | N32: 0 | R32: 0 | S32: 0 | W32: Multiplicador | X32: 0 | Z32: 1 | AA32: 0 | AB32: 0 | AC32: 19.729 | AD32: 40781 | AE32: 20.28 | AF32: 0 | AH32: 0 | AJ32: 0 | AL32: 0 | AM32: 0 | AN32: 16601001 | AO32: 0 | AP32: 1000 | AT32: 0 | AU32: Direto | AW32: Normal | AX32: 0 | AY32: 40781 | BA32: 40781 | BB32: Nao utiliza | BD32: 0 | BF32: Nao | BG32: / / | BH32: 0 | BI32: 1 | BJ32: 0 | BK32: 0 | BM32: / / | BN32: 0 | BR32: Nao | BS32: Nao | BT32: Nao | BW32: 83 | CA32: 0 | CB32: N | CE32: Nao | CH32: Nao | CN32: SigaQuality | CO32: Nao | CP32: 1 | CQ32: 0 | CS32: 0 | CT32: 0 | CU32: 0 | CV32: Não | CW32: 0 | CX32: 0 | CY32: 0 | CZ32: 0 | DB32: 0 | DC32: Nao | DF32: Nao permite | DH32: 0 | DJ32: 0 | DK32: Normal | DL32: 0 | DN32: 0 | DO32: / / | DP32: 0 | DQ32: 0 | DS32: 0 | DU32: 0 | DW32: 0 | DX32: Nao | DY32: 0 | DZ32: 0 | EA32: 0 | ED32: Não | EE32: 0 | EF32: 0 | EQ32: Sim | ES32: Normal | ET32: 0 | EV32: 0 | EY32: Moeda1 | EZ32: 0 | FA32: Nao | FB32: 0 | FC32: 0 | FE32: . . | FF32: 0 | FG32: . . | FJ32: 0 | FK32: 0 | FP32: 0 | FR32: 0 | FS32: Nao | FX32: / / | FZ32: S | GA32: 0 | GB32: / / | GE32: 0 | GG32: 0 | GN32: 0 | GO32: Comprando | GQ32: 0 | GU32: 0 | GY32: Não | HB32: 0 | HE32: 0 | HF32: 0 | HG32: 0 | HK32: / / | HM32: 1a Unidade de Medida | HN32: 0 | HP32: 0 | HQ32: 0 | HR32: / / | HS32: Nao | HT32: 0 | HU32: 0 | HW32: 0 | HX32: 0 | HY32: 0 | HZ32: Não | IA32: 0 | IB32: Não | ID32: Não | IF32: 0 | IG32: / / | II32: / / | IR32: Não | IT32: 0 | IY32: Sim | IZ32: Nao | JC32: Nao | JE32: 0 | JF32: 0 | JI32: / / | JJ32: 0 | JK32: 0 | JL32: 0 | JM32: 0 | JQ32: Nao | JT32: 0 | JU32: / / | JW32: 0 | KA32: 0 | KF32: 0 | KG32: 0 | KH32: 0 | KI32: 0 | KS32: . . | KT32: 0 | KU32: 0 | KV32: 0 | KX32: 0 | KZ32: 0 | LF32: 0 | LH32: 0 | LI32: 0
A33: 1 | B33: 12276 | C33: CABO FLEX. 1KV AFUMEX 4MM BR | D33: AI | E33: PC | F33: 80 | G33: 9000 | H33: 0 | I33: 8544.49.00 | L33: 0 | M33: 0 | N33: 0 | R33: 0 | S33: 0 | W33: Multiplicador | X33: 0 | Z33: 1 | AA33: 0 | AB33: 0 | AC33: 1.7671 | AD33: 40781 | AE33: 1.7 | AF33: 0 | AH33: 0 | AJ33: 0 | AL33: 0 | AM33: 0 | AN33: 16601001 | AO33: 0 | AP33: 1000 | AT33: 0 | AU33: Direto | AW33: Normal | AX33: 0 | AY33: 40781 | BA33: 40781 | BB33: Nao utiliza | BD33: 0 | BF33: Nao | BG33: / / | BH33: 0 | BI33: 1 | BJ33: 0 | BK33: 0 | BM33: / / | BN33: 0 | BR33: Nao | BS33: Nao | BT33: Nao | BW33: 83 | CA33: 0 | CB33: N | CE33: Nao | CH33: Nao | CN33: SigaQuality | CO33: Nao | CP33: 1 | CQ33: 0 | CS33: 0 | CT33: 0 | CU33: 0 | CV33: Não | CW33: 0 | CX33: 0 | CY33: 0 | CZ33: 0 | DB33: 0 | DC33: Nao | DF33: Nao permite | DH33: 0 | DJ33: 0 | DK33: Normal | DL33: 0 | DN33: 0 | DO33: / / | DP33: 0 | DQ33: 0 | DS33: 0 | DU33: 0 | DW33: 0 | DX33: Nao | DY33: 0 | DZ33: 0 | EA33: 0 | ED33: Não | EE33: 0 | EF33: 0 | EQ33: Sim | ES33: Normal | ET33: 0 | EV33: 0 | EY33: Moeda1 | EZ33: 0 | FA33: Nao | FB33: 0 | FC33: 0 | FE33: . . | FF33: 0 | FG33: . . | FJ33: 0 | FK33: 0 | FP33: 0 | FR33: 0 | FS33: Nao | FX33: / / | FZ33: S | GA33: 0 | GB33: / / | GE33: 0 | GG33: 0 | GN33: 0 | GO33: Comprando | GQ33: 0 | GU33: 0 | GY33: Não | HB33: 0 | HE33: 0 | HF33: 0 | HG33: 0 | HK33: / / | HM33: 1a Unidade de Medida | HN33: 0 | HP33: 0 | HQ33: 0 | HR33: / / | HS33: Nao | HT33: 0 | HU33: 0 | HW33: 0 | HX33: 0 | HY33: 0 | HZ33: Não | IA33: 0 | IB33: Não | ID33: Não | IF33: 0 | IG33: / / | II33: / / | IR33: Não | IT33: 0 | IY33: Sim | IZ33: Nao | JC33: Nao | JE33: 0 | JF33: 0 | JI33: / / | JJ33: 0 | JK33: 0 | JL33: 0 | JM33: 0 | JQ33: Nao | JT33: 0 | JU33: / / | JW33: 0 | KA33: 0 | KF33: 0 | KG33: 0 | KH33: 0 | KI33: 0 | KS33: . . | KT33: 0 | KU33: 0 | KV33: 0 | KX33: 0 | KZ33: 0 | LF33: 0 | LH33: 0 | LI33: 0
A34: 1 | B34: 12277 | C34: CABO FLEX 1KV AFUMEX 6MM VM | D34: AI | E34: MT | F34: 80 | G34: 9000 | H34: 0 | I34: 8544.49.00 | L34: 0 | M34: 0 | N34: 0 | R34: 0 | S34: 0 | W34: Multiplicador | X34: 0 | Z34: 1 | AA34: 0 | AB34: 0 | AC34: 2.4532 | AD34: 40781 | AE34: 2.35 | AF34: 0 | AH34: 0 | AJ34: 0 | AL34: 0 | AM34: 0 | AN34: 16601001 | AO34: 0 | AP34: 1000 | AT34: 0 | AU34: Direto | AW34: Normal | AX34: 0 | AY34: 40781 | BA34: 40781 | BB34: Nao utiliza | BD34: 0 | BF34: Nao | BG34: / / | BH34: 0 | BI34: 1 | BJ34: 0 | BK34: 0 | BM34: / / | BN34: 0 | BR34: Nao | BS34: Nao | BT34: Nao | BW34: 83 | CA34: 0 | CB34: N | CE34: Nao | CH34: Nao | CN34: Materiais | CO34: Nao | CP34: 1 | CQ34: 0 | CS34: 0 | CT34: 0 | CU34: 0 | CV34: Não | CW34: 0 | CX34: 0 | CY34: 0 | CZ34: 0 | DB34: 0 | DC34: Nao | DF34: Nao permite | DH34: 0 | DJ34: 0 | DK34: Normal | DL34: 0 | DN34: 0 | DO34: / / | DP34: 0 | DQ34: 0 | DS34: 0 | DU34: 0 | DW34: 0 | DX34: Nao | DY34: 0 | DZ34: 0 | EA34: 0 | ED34: Não | EE34: 0 | EF34: 0 | EQ34: Sim | ES34: Normal | ET34: 0 | EV34: 0 | EY34: Moeda1 | EZ34: 0 | FA34: Nao | FB34: 0 | FC34: 0 | FE34: . . | FF34: 0 | FG34: . . | FJ34: 0 | FK34: 0 | FP34: 0 | FR34: 0 | FX34: / / | FZ34: S | GA34: 0 | GB34: / / | GE34: 0 | GG34: 0 | GN34: 0 | GO34: Comprando | GQ34: 0 | GU34: 0 | GY34: Não | HB34: 0 | HE34: 0 | HF34: 0 | HG34: 0 | HK34: / / | HM34: 1a Unidade de Medida | HN34: 0 | HP34: 0 | HQ34: 0 | HR34: / / | HS34: Nao | HT34: 0 | HU34: 0 | HW34: 0 | HX34: 0 | HY34: 0 | HZ34: Não | IA34: 0 | IB34: Não | ID34: Não | IF34: 0 | IG34: / / | II34: / / | IR34: Não | IT34: 0 | IY34: Sim | IZ34: Nao | JC34: Nao | JE34: 0 | JF34: 0 | JI34: / / | JJ34: 0 | JK34: 0 | JL34: 0 | JM34: 0 | JQ34: Nao | JT34: 0 | JU34: / / | JW34: 0 | KA34: 0 | KF34: 0 | KG34: 0 | KH34: 0 | KI34: 0 | KS34: . . | KT34: 0 | KU34: 0 | KV34: 0 | KX34: 0 | KZ34: 0 | LF34: 0 | LH34: 0 | LI34: 0
A35: 1 | B35: 12278 | C35: CABO FLEX 1KV AFUMEX 6MM BR | D35: AI | E35: MT | F35: 80 | G35: 9000 | H35: 0 | I35: 8544.49.00 | L35: 0 | M35: 0 | N35: 0 | R35: 0 | S35: 0 | W35: Multiplicador | X35: 0 | Z35: 1 | AA35: 0 | AB35: 0 | AC35: 2.4532 | AD35: 40781 | AE35: 2.35 | AF35: 0 | AH35: 0 | AJ35: 0 | AL35: 0 | AM35: 0 | AN35: 16601001 | AO35: 0 | AP35: 1000 | AT35: 0 | AU35: Direto | AW35: Normal | AX35: 0 | AY35: 40781 | BA35: 40781 | BB35: Nao utiliza | BD35: 0 | BF35: Nao | BG35: / / | BH35: 0 | BI35: 1 | BJ35: 0 | BK35: 0 | BM35: / / | BN35: 0 | BR35: Nao | BS35: Nao | BT35: Nao | BW35: 83 | CA35: 0 | CB35: N | CE35: Nao | CH35: Nao | CN35: Materiais | CO35: Nao | CP35: 1 | CQ35: 0 | CS35: 0 | CT35: 0 | CU35: 0 | CV35: Não | CW35: 0 | CX35: 0 | CY35: 0 | CZ35: 0 | DB35: 0 | DC35: Nao | DF35: Nao permite | DH35: 0 | DJ35: 0 | DK35: Normal | DL35: 0 | DN35: 0 | DO35: / / | DP35: 0 | DQ35: 0 | DS35: 0 | DU35: 0 | DW35: 0 | DX35: Nao | DY35: 0 | DZ35: 0 | EA35: 0 | ED35: Não | EE35: 0 | EF35: 0 | EQ35: Sim | ES35: Normal | ET35: 0 | EV35: 0 | EY35: Moeda1 | EZ35: 0 | FA35: Nao | FB35: 0 | FC35: 0 | FE35: . . | FF35: 0 | FG35: . . | FJ35: 0 | FK35: 0 | FP35: 0 | FR35: 0 | FX35: / / | FZ35: S | GA35: 0 | GB35: / / | GE35: 0 | GG35: 0 | GN35: 0 | GO35: Comprando | GQ35: 0 | GU35: 0 | GY35: Não | HB35: 0 | HE35: 0 | HF35: 0 | HG35: 0 | HK35: / / | HM35: 1a Unidade de Medida | HN35: 0 | HP35: 0 | HQ35: 0 | HR35: / / | HS35: Nao | HT35: 0 | HU35: 0 | HW35: 0 | HX35: 0 | HY35: 0 | HZ35: Não | IA35: 0 | IB35: Não | ID35: Não | IF35: 0 | IG35: / / | II35: / / | IR35: Não | IT35: 0 | IY35: Sim | IZ35: Nao | JC35: Nao | JE35: 0 | JF35: 0 | JI35: / / | JJ35: 0 | JK35: 0 | JL35: 0 | JM35: 0 | JQ35: Nao | JT35: 0 | JU35: / / | JW35: 0 | KA35: 0 | KF35: 0 | KG35: 0 | KH35: 0 | KI35: 0 | KS35: . . | KT35: 0 | KU35: 0 | KV35: 0 | KX35: 0 | KZ35: 0 | LF35: 0 | LH35: 0 | LI35: 0
A36: 1 | B36: 12279 | C36: CABO FLEX.1KV AFUMEX 185,0MM PT | D36: AI | E36: PC | F36: 80 | G36: 9000 | H36: 0 | I36: 8544.49.00 | L36: 0 | M36: 0 | N36: 0 | R36: 0 | S36: 0 | W36: Multiplicador | X36: 0 | Z36: 1 | AA36: 0 | AB36: 0 | AC36: 73.0249 | AD36: 40781 | AE36: 70.25 | AF36: 0 | AH36: 0 | AJ36: 0 | AL36: 0 | AM36: 0 | AN36: 16601001 | AO36: 0 | AP36: 1000 | AT36: 0 | AU36: Direto | AW36: Normal | AX36: 0 | AY36: 40781 | BA36: 40781 | BB36: Nao utiliza | BD36: 0 | BF36: Nao | BG36: / / | BH36: 0 | BI36: 1 | BJ36: 0 | BK36: 0 | BM36: / / | BN36: 0 | BR36: Nao | BS36: Nao | BT36: Nao | BW36: 83 | CA36: 0 | CB36: N | CE36: Nao | CH36: Nao | CN36: SigaQuality | CO36: Nao | CP36: 1 | CQ36: 0 | CS36: 0 | CT36: 0 | CU36: 0 | CV36: Não | CW36: 0 | CX36: 0 | CY36: 0 | CZ36: 0 | DB36: 0 | DC36: Nao | DF36: Nao permite | DH36: 0 | DJ36: 0 | DK36: Normal | DL36: 0 | DN36: 0 | DO36: / / | DP36: 0 | DQ36: 0 | DS36: 0 | DU36: 0 | DW36: 0 | DX36: Nao | DY36: 0 | DZ36: 0 | EA36: 0 | ED36: Não | EE36: 0 | EF36: 0 | EQ36: Sim | ES36: Normal | ET36: 0 | EV36: 0 | EY36: Moeda1 | EZ36: 0 | FA36: Nao | FB36: 0 | FC36: 0 | FE36: . . | FF36: 0 | FG36: . . | FJ36: 0 | FK36: 0 | FP36: 0 | FR36: 0 | FS36: Nao | FX36: / / | FZ36: S | GA36: 0 | GB36: / / | GE36: 0 | GG36: 0 | GN36: 0 | GO36: Comprando | GQ36: 0 | GU36: 0 | GY36: Não | HB36: 0 | HE36: 0 | HF36: 0 | HG36: 0 | HK36: / / | HM36: 1a Unidade de Medida | HN36: 0 | HP36: 0 | HQ36: 0 | HR36: / / | HS36: Nao | HT36: 0 | HU36: 0 | HW36: 0 | HX36: 0 | HY36: 0 | HZ36: Não | IA36: 0 | IB36: Não | ID36: Não | IF36: 0 | IG36: / / | II36: / / | IR36: Não | IT36: 0 | IY36: Sim | IZ36: Nao | JC36: Nao | JE36: 0 | JF36: 0 | JI36: / / | JJ36: 0 | JK36: 0 | JL36: 0 | JM36: 0 | JQ36: Nao | JT36: 0 | JU36: / / | JW36: 0 | KA36: 0 | KF36: 0 | KG36: 0 | KH36: 0 | KI36: 0 | KS36: . . | KT36: 0 | KU36: 0 | KV36: 0 | KX36: 0 | KZ36: 0 | LF36: 0 | LH36: 0 | LI36: 0
